Workbook

Sheet COMPRAS E INV
A1: OJO NO USAR ESTE | B1: referencias | E1: PEDIDO SUR | F1: PEDIDO NORTE | H1: INVENT SUR mar 21 | I1: INVENT NTE | J1: FECHA VCMTO | K1: PRECIO COMPRA | L1: precio venta | M1: IVA | N1: PRECIO MALTERO | O1: % | P1: VR PEDIDO
A2: abre bocas Umbrella | E2: 0 | F2: 0 | G2: Pluss Dent GAB VEL | H2: 0 | I2: 0 | K2: =9288*1.19 -> 11052.72 | L2: 15000 | O2: =(L2/K2)-1 -> 0.357132 | P2: =K2*F2 -> 0
A3: Abreboca manual gancho DOBLE EXTREMO NEGRO | E3: 0 | F3: 0 | G3: IMPORTADA | I3: 8 | K3: 8746 | L3: 30000 | M3: 19 | O3: =(L3/K3)-1 -> 2.4301395 | P3: =K3*F3 -> 0
A4: Abreboca manual gancho DOBLE EXTREMO TRANSPARENTE | E4: 0 | F4: 0 | G4: IMPORTADA | I4: 50 | K4: =1962*2 -> 3924 | L4: 30000 | O4: =(L4/K4)-1 -> 6.6452599 | P4: =K4*F4 -> 0
A5: Abreboca manual gancho PEQUEÑO | E5: 0 | F5: 0 | G5: IMPORTADA | I5: 100 | K5: 1712 | L5: 10000 | O5: =(L5/K5)-1 -> 4.8411215 | P5: =K5*F5 -> 0
A6: Abreboca AZUL Y ROJO AMARILLO | E6: 0 | F6: 0 | G6: ELVER LOZANO BOGOTA | I6: rojo 1 azul 1 | K6: 4500 | L6: 12000 | O6: =(L6/K6)-1 -> 1.6666667 | P6: =K6*F6 -> 0
A7: abreboca Con retractor adulto | E7: 0 | F7: 0 | G7: UPEGUI | I7: BLANCO 43 NEGRO 10 | K7: 16900 | L7: 24000 | O7: =(L7/K7)-1 -> 0.42011834 | P7: =K7*F7 -> 0
A8: abreboca Con retractor PEDIATRICO | E8: 0 | F8: 0 | G8: UPEGUI | I8: 20 | K8: 16900 | L8: 24000 | O8: =(L8/K8)-1 -> 0.42011834 | P8: =K8*F8 -> 0
A9: Abreboca manual gancho GRANDE | E9: 0 | F9: 0 | G9: IMPORTADA | I9: 50 | K9: 1426.9789 | L9: 10000 | O9: =(L9/K9)-1 -> 6.0078119 | P9: =K9*F9 -> 0
A10: Abreboca sencillo adulto | B10: OXXI $ 11067 NISSI $7556 | E10: 20 | F10: 20 | G10: OXXI NISSI | I10: =8+16*5 -> 88 | K10: =9300*1.19/5 -> 2213.4 | L10: 8000 | O10: =(L10/K10)-1 -> 2.614349 | P10: =K10*F10 -> 44268
A11: Abreboca sencillo niño | B11: OXXI $ 11067 NISSI $7557 | E11: 10 | F11: 0 | G11: OXXI NISSI | I11: 26 | K11: =9300*1.19/5 -> 2213.4 | L11: 8000 | O11: =(L11/K11)-1 -> 2.614349 | P11: =K11*F11 -> 0
A12: abreboca sin retractor | E12: 0 | F12: 0 | G12: UPEGUI | I12: 10 | K12: 16900 | L12: 24000 | O12: =(L12/K12)-1 -> 0.42011834 | P12: =K12*F12 -> 0
A13: abrebocas aclaramiento tipo optragate | E13: 0 | F13: 0 | G13: IMPORTADA | I13: 58 | K13: 4602 | L13: 12000 | O13: =(L13/K13)-1 -> 1.6075619 | P13: =K13*F13 -> 0
A14: Accufilm Papel de articular aqua film x 280 tiras | E14: 0 | F14: 0 | G14: La muela miguel | I14: 1 | K14: =65000/200 -> 325 | L14: 800 | O14: =(L14/K14)-1 -> 1.4615385 | P14: =K14*F14 -> 0
A15: Accufilm Papel de articular CIRENE aqua film x 280 tiras | E15: 0 | F15: 0 | G15: La muela miguel | K15: 65000 | L15: 105000 | N15: 90000 | O15: =(L15/K15)-1 -> 0.61538462 | P15: =K15*F15 -> 0
A16: Aceite 3 en 1 | E16: 0 | G16: CENTRO HOYOSTOOL | K16: =3200*1.19 -> 3808 | L16: 6000 | O16: =(L16/K16)-1 -> 0.57563025 | P16: =K16*F16 -> 0
A17: aceite lubricante - pieza de mano Dental handpiece 300ml | E17: 0 | F17: 0 | G17: DTM | K17: 28000 | L17: 48000 | N17: 38000 | O17: =(L17/K17)-1 -> 0.71428571
A18: aceite lubricante - pieza de mano Dental handpiece 550ml | E18: 0 | F18: 0 | G18: DTM | K18: 35000 | L18: 54000 | N18: 44000 | O18: =(L18/K18)-1 -> 0.54285714
A19: aceite lubricante - pieza de mano PANASPRAY PLUS NSK 480ML | B19: NSK | E19: 0 | F19: 0 | G19: LA MUELA | I19: 10 | J19: 45717 | K19: =121849*1.19 -> 145000.31 | L19: 178000 | N19: 168000 | O19: =(L19/K19)-1 -> 0.22758358 | P19: =K19*F19 -> 0
A20: aceite lubricante - pieza de mano WYH 400ML | B20: euro $96250 | G20: MASDENTAL EURODENT | I20: 0 | K20: 116000 | L20: 145000 | N20: 120000 | O20: =(L20/K20)-1 -> 0.25 | P20: =K20*F20 -> 0
A21: Aceite lubricante Bendechk 300ml | E21: 0 | F21: 0 | G21: makrodent DTM | K21: 35000 | L21: 48000 | O21: =(L21/K21)-1 -> 0.37142857 | P21: =K21*F21 -> 0
A22: aceite lubricante de piezas digixpray 240ml | E22: 0 | F22: 0 | G22: muela | K22: 24850 | L22: 48000 | M22: iva | N22: 34000
A23: Aceite lubricante en Spray 200 ml- KAVO | C23: AGOTADO | E23: 0 | F23: 0 | G23: Pluss Dent GAB VEL | H23: 0 | I23: 0 | K23: 49504 | L23: 65000 | O23: =(L23/K23)-1 -> 0.31302521 | P23: =K23*F23 -> 0
A24: aceite lubricante pequeño - pieza de mano 50 ml | E24: 0 | G24: RAMON | K24: 7400 | L24: 12000 | O24: =(L24/K24)-1 -> 0.62162162 | P24: =K24*F24 -> 0
A25: Aceite lubricante Quiruspray 200 cc - pieza de mano | B25: ramon $29.500 aquiles $24.871 | E25: 0 | G25: RAMON AQUILES | K25: =24789.92*1.19 -> 29500.005 | L25: 39000 | O25: =(L25/K25)-1 -> 0.32203368 | P25: =K25*F25 -> 0
A26: Aceite lubricante Universal en Spray 250 ml- Adensys | E26: 0 | F26: 0 | G26: Pluss Dent GAB VEL | H26: 0 | I26: 10 | J26: 46174 | K26: =50500*1.19 -> 60095 | L26: 76000 | N26: 65000 | O26: =(L26/K26)-1 -> 0.26466428 | P26: =K26*F27 -> 0
A27: Aceite LUBRICANTE X200 ML Maquira | E27: 0 | F27: 0 | G27: SOCCIDENTALES | I27: 0 | J27: 46174 | K27: =26000*1.19 -> 30940 | L27: 55000 | O27: =(L27/K27)-1 -> 0.77763413 | P27: =K27*#REF! -> #REF!
A28: Aceite super lubry 50ml | E28: 0 | F28: 0 | G28: AQUILES | I28: 0 | J28: 46174 | K28: 7500 | L28: 12000 | O28: =(L28/K28)-1 -> 0.6 | P28: =K28*F28 -> 0
A29: acetato lamina rosada 0.6 | E29: 0 | G29: RAMON | K29: 1800 | L29: 3500 | O29: =(L29/K29)-1 -> 0.94444444 | P29: =K29*F29 -> 0
A30: acetato rigido ACE | E30: 0 | G30: RAMON | K30: 6400 | L30: 9000 | O30: =(L30/K30)-1 -> 0.40625 | P30: =K30*F30 -> 0
A31: acido clorhidrico removedor de manchas opalustre FGM whiteness RM 6% | B31: antioq $95200 soccid $ 80,206 plus $79968 | E31: 0 | F31: 0 | G31: FGM soccident | I31: 0 | J31: 46082 | K31: =100000*0.8*1.19 -> 95200 | L31: 145000 | O31: =(L31/K31)-1 -> 0.52310924 | P31: =K31*F31 -> 0
A32: Acido desmineralizante 2.5 coltene | B32: ACIDO | E32: 0 | F32: 0 | G32: Ultradental | I32: 0 | K32: 10868 | L32: 18000 | O32: =(L32/K32)-1 -> 0.6562385 | P32: =K32*F32 -> 0
A33: acido desmineralizante 2.5 Densell 12g 35% | B33: ACIDO | E33: 0 | F33: 0 | G33: La muela - ramon | J33: 46478 | K33: 12000 | L33: 20000 | M33: exc | N33: 18000 | O33: =(L33/K33)-1 -> 0.66666667 | P33: =K33*F33 -> 0
A34: Acido desmineralizante 35% ultradent 1.2ml | B34: ACIDO | E34: 2 | F34: 0 | G34: Gabriel Vel pluss | H34: 2 | I34: 3 | K34: 13272 | L34: 22000 | O34: =(L34/K34)-1 -> 0.65762508 | P34: =K34*F34 -> 0
A35: acido desmineralizante 37% fosforico MAQUIRA 2.5 | B35: ACIDO | C35: PRECIO MAYO 20 | D35: =(6500*1.19)/3 -> 2578.3333 | E35: 0 | F35: 0 | G35: RAMON CLAUDIA SOCCIDENTALES | J35: 45962 | K35: =(11654*1.19)/3 -> 4622.7533 | L35: 13000 | M35: EXC | O35: =(L35/K35)-1 -> 1.8121769 | P35: =K35*F35 -> 0
A36: acido desmineralizante angelus 3 grs | B36: ACIDO | E36: 0 | F36: 0 | G36: CLAUDIA | I36: 0 | K36: 2000 | L36: 10000 | O36: =(L36/K36)-1 -> 4 | P36: =K36*F36 -> 0
A37: Acido desmineralizante FGM condac 12.5 ML | B37: ACIDO promo antoq $24375 SOCCIDEN 20825 plus20000 | E37: 0 | F37: 0 | G37: FGM soccident | I37: 0 | J37: 45992 | K37: =32500*0.8 -> 26000 | L37: 35000 | M37: exc | O37: =(L37/K37)-1 -> 0.34615385 | P37: =K37*F37 -> 0
A38: Acido Desmineralizante proquident 10ML jumbo | B38: ACIDO | G38: PROQUIDENT | I38: 2 | J38: 46844 | K38: 14173 | L38: 24000 | O38: =(L38/K38)-1 -> 0.69336062 | P38: =K38*#REF! -> #REF!
A39: Acido Desmineralizante Select H V ETCH 5ML Bisco | B39: promo $48.450 mayo/25 | G39: JULVIDENT bisco | I39: 11 | J39: 46447 | K39: 54000 | L39: 68000 | M39: EXC | O39: =(L39/K39)-1 -> 0.25925926 | P39: =K39*F39 -> 0
A40: Acido desmineralizante SUPER ETCH SDI 12 gm | B40: ACIDO | E40: 0 | F40: 0 | G40: ABRAHAM | I40: 6 | J40: 46296 | K40: 33800 | L40: 42500 | M40: exc | O40: =(L40/K40)-1 -> 0.25739645 | P40: =K40*F40 -> 0
A41: Acido desmineralizante ultra ETCH 30ml ultradent | B41: ACIDO | E41: 0 | F41: 0 | G41: Gabriel Vel pluss | H41: 1 | I41: 3 | K41: 150579 | L41: 210000 | N41: tempo $150,000 | O41: =(L41/K41)-1 -> 0.39461678 | P41: =K41*F41 -> 0
A42: Acido Desmineralizante Zafira 10 ml | B42: ACIDO | C42: kit zafira | G42: New Stetic | H42: 10 | J42: revisar | K42: 12400 | L42: 18000 | M42: exc | N42: 15000 | O42: =(L42/K42)-1 -> 0.4516129 | P42: =K42*F42 -> 0
A43: acido fluorhidrico 10% Jeringa 2.5 ml Angelus | E43: 0 | F43: 0 | G43: CLAUDIA | I43: 0 | K43: 37140 | L43: 46400 | O43: =(L43/K43)-1 -> 0.24932687 | P43: =K43*F43 -> 0
A44: acido fluorhidrico 10% Jeringa 2.5 ml Maquira | E44: 0 | F44: 0 | G44: SOCCIDENTALES CLAUDIA | I44: 8 | K44: =21315*1.19 -> 25364.85 | L44: 38000 | M44: EXC | N44: 32000 | O44: =(L44/K44)-1 -> 0.4981362 | P44: =K44*F44 -> 0
A45: ACIDO FLUORHIDRICO 3ML (JERINGA) prodont | E45: 0 | F45: 0 | G45: PRODONT | I45: 5 | J45: 46478 | K45: =23294*1.19 -> 27719.86 | L45: 40000 | N45: 35000 | O45: =(L45/K45)-1 -> 0.44300873 | P45: =K45*F45 -> 0
A46: acido fluorhidrico 5% 3 g BM4 | E46: 0 | F46: 0 | G46: CLAUDIA | I46: 0 | K46: 10320 | L46: 30000 | O46: =(L46/K46)-1 -> 1.9069767 | P46: =K46*F46 -> 0
A47: acido fluorhidrico 5% porcelana jeringa 2.5 ml FGM | B47: SOCCID $24514 plus $25600 | E47: 0 | F47: 0 | G47: FGM soccident | I47: 0 | J47: 46023 | K47: =40000*0.8*1.19 -> 38080 | L47: 56000 | O47: =(L47/K47)-1 -> 0.47058824 | P47: =K47*F47 -> 0
A48: ACIDO FLUORHIDRICO 7ML (GOTERO) prodont | E48: 0 | F48: 10 | G48: PRODONT | I48: 4 | J48: 46569 | K48: =25757*1.19 -> 30650.83 | L48: 45000 | N48: 38000 | O48: =(L48/K48)-1 -> 0.46814948 | P48: =K48*F48 -> 306508.3
A49: acido fluorhidrico 9.6% Jeringa 2 g Eufar | B49: Aquiles $32000 ramon $32000 EUFAR $29354 | E49: 0 | F49: 0 | G49: AQUILES RAMON GABRIEL VELASQUEZ Eufar | K49: =24667*1.19 -> 29353.73 | L49: 45000 | N49: 35000 | O49: =(L49/K49)-1 -> 0.53302493 | P49: =K49*F49 -> 0
A50: Acido fluorhidrico grabador para porcelana ultradent | B50: pluss $24804 | E50: 0 | F50: 0 | G50: Gabriel Vel pluss | H50: 3 | I50: 6 | K50: 30257 | L50: 52000 | M50: EXC | N50: 38000 | O50: =(L50/K50)-1 -> 0.71861057 | P50: =K50*F50 -> 0
A51: Acido Fluorhidrico porcelain etch 9,5% Bisco | B51: promo $106.250 mayo/25 | G51: JULVIDENT bisco | I51: 3 | K51: 118000 | L51: 170000 | M51: EXC | O51: =(L51/K51)-1 -> 0.44067797 | P51: =K51*F51 -> 0
A52: aclaramiento casero Clariant 16% Angelus | E52: 0 | F52: 0 | G52: ABRAHAM | I52: 3 | K52: 19710 | L52: 24630 | O52: =(L52/K52)-1 -> 0.24961948 | P52: =K52*F52 -> 0
A53: Aclaramiento casero OPALECENSE x 2 JERINGAS | C53: Casero | E53: 0 | F53: 0 | G53: CLAUDIA pluss dent | H53: 3 | I53: 4 | J53: revisar | K53: 45031 | L53: 58000 | M53: iva | O53: =(L53/K53)-1 -> 0.2880016 | P53: =K53*F53 -> 0
A54: Aclaramiento casero Opalecense Go caja x 10 | B54: pluss $211.000 promo 2x 159 gabriel velasq promo x 2 155 | C54: Casero | E54: 1 | F54: 0 | G54: CLAUDIA pluss dent | H54: 1 | I54: 2 | J54: 45931 | K54: 211194 | L54: 248000 | O54: =(L54/K54)-1 -> 0.17427578 | P54: =K54*F54 -> 0
A55: Aclaramiento casero Opalecense Go x unidad | C55: Casero | E55: 0 | F55: 0 | G55: CLAUDIA pluss dent | H55: 0 | K55: 25000 | L55: 30000 | O55: =(L55/K55)-1 -> 0.2 | P55: =K55*F55 -> 0
A56: Aclaramiento casero Polanight | E56: 0 | F56: 0 | G56: CLAUDIA abraham | I56: 0 | K56: 26900 | L56: 33600 | O56: =(L56/K56)-1 -> 0.24907063 | P56: =K56*F56 -> 0
A57: Aclaramiento casero Potenza 16% | C57: Casero | G57: New Stetic | H57: 0 | J57: 46113 | K57: 13953 | L57: 22000 | O57: =(L57/K57)-1 -> 0.57672185 | P57: =K57*F57 -> 0
A58: Aclaramiento casero Potenza 22% | C58: Casero | G58: New Stetic | H58: 0 | K58: 15153 | L58: 22000 | O58: =(L58/#REF!)-1 -> #REF! | P58: =#REF!*K58 -> #REF!
A59: Aclaramiento casero Power bleaching bM4 16 % | E59: 0 | F59: 0 | G59: SOCCIDENTALES | I59: 0 | K59: =8070*1.19 -> 9603.3 | L59: 20000 | O59: =(L59/K59)-1 -> 1.0826174 | P59: =K59*F59 -> 0
A60: Aclaramiento casero Power bleaching bM4 22 % | E60: 0 | F60: 0 | G60: SOCCIDENTALES | I60: 0 | K60: =8070*1.19 -> 9603.3 | L60: 20000 | O60: =(L60/K60)-1 -> 1.0826174 | P60: =K60*F60 -> 0
A61: Aclaramiento casero Whiteness perfect FGM 16% | B61: antioq $16800 promo $15000 soccid $14500 plus $15232 | C61: Casero | E61: 0 | F61: 0 | G61: FGM soccident | I61: 0 | J61: 1/11/2025 3-2025 | K61: 16800 | L61: 25000 | N61: 22000 | O61: =(L61/K61)-1 -> 0.48809524 | P61: =K61*F61 -> 0
A62: Aclaramiento casero Whiteness perfect FGM 22% | B62: antioq $16800 promo $15000 soccid $14500 plus $15232 | C62: Casero | E62: 0 | F62: 0 | G62: FGM soccident | I62: 0 | J62: 45717 | K62: 16800 | L62: 25000 | O62: =(L62/K62)-1 -> 0.48809524 | P62: =K62*F62 -> 0
A63: Aclaramiento casero withegold | E63: 0 | G63: DORA ramon | K63: 11700 | L63: 18000 | O63: =(L63/K63)-1 -> 0.53846154 | P63: =K63*F63 -> 0
A64: Aclaramiento consultorio AZUL HP BLUE FGM 35% JERINGA | B64: SOCCID 38714 plus $37334 | C64: PRECIO MAYO 20 | D64: =(195200+37088)/6 -> 38714.667 | E64: 0 | F64: 0 | G64: FGM soccident | I64: 0 | J64: 46023 | K64: =245000*0.8*1.19/6 -> 38873.333 | L64: 65000 | N64: 48000 | O64: =(L64/K64)-1 -> 0.67209741 | P64: =K64*F64 -> 0
A65: Aclaramiento consultorio AZUL HP BLUE FGM 35% MINI KIT | B65: antioq $76160 soccid $66800 | C65: aclaramiento FGM | E65: 0 | F65: 0 | G65: FGM soccident | K65: =80000*0.8*1.19 -> 76160 | L65: 100000 | O65: =(L65/K65)-1 -> 0.31302521 | P65: =K65*F65 -> 0
A66: aclaramiento consultorio Clariant 35% Angelus | C66: PRECIO 20 MAYO | D66: 38000 | E66: 0 | F66: 0 | G66: ABRAHAM | I66: 0 | K66: 36130 | L66: 49000 | O66: =(L66/K66)-1 -> 0.35621367 | P66: =K66*F66 -> 0
A67: Aclaramiento consultorio FGM 35% ROJO HP | B67: antioq $200000 promo $196350 soccid $202.300 | C67: aclaramiento FGM | E67: 0 | F67: 0 | G67: FGM soccident | J67: FGM 1/11/2025 brasil 04-2025 | K67: =250000*0.8 -> 200000 | L67: 270000 | O67: =(L67/K67)-1 -> 0.35 | P67: =K67*F67 -> 0
A68: Aclaramiento consultorio FGM 35% ROJO HP Mini kit | C68: aclaramiento FGM | E68: 0 | F68: 0 | G68: FGM soccident | K68: 89000 | L68: 119000 | O68: =(L68/K68)-1 -> 0.33707865 | P68: =K68*F68 -> 0
A69: Aclaramiento consultorio FGM 35% VERDE HP AUTOMIX JERINGA CONSULTORIO | C69: aclaramiento FGM | E69: 0 | F69: 0 | G69: FGM soccident | K69: 190000 | L69: 220000 | O69: =(L69/K69)-1 -> 0.15789474 | P69: =K69*F69 -> 0
A70: Aclaramiento consultorio FGM 35% VERDE HP MAXX | B70: antioq $233240 soccid $180000 plus $208012 | C70: aclaramiento FGM | E70: 0 | F70: 0 | G70: FGM soccident | K70: 200000 | L70: 270000 | O70: =(L70/K70)-1 -> 0.35 | P70: =K70*F70 -> 0
A71: Aclaramiento consultorio FGM 35% VERDE MINI KIT HP MAXX | B71: antioq $117096 soccid $66800 | C71: aclaramiento FGM | D71: FGM | E71: 0 | F71: 0 | G71: FGM soccident | K71: =123000*0.8*1.19 -> 117096 | L71: 165000 | O71: =(L71/K71)-1 -> 0.40910023 | P71: =K71*F71 -> 0
A72: Aclaramiento consultorio OPALECENSE BOOTS + barrera gingival OPALDAM | E72: 0 | F72: 0 | G72: CLAUDIA pluss dent | H72: 4 | I72: 0 | K72: 115250 | L72: 148000 | M72: iva | O72: =(L72/K72)-1 -> 0.28416486 | P72: =K72*F72 -> 0
A73: Aclaramiento consultorio OPALECENSE BOOTS 40% | B73: compre $90200 | E73: 1 | F73: 0 | G73: CLAUDIA pluss dent | H73: 1 | I73: 2 | J73: 45901 | K73: 97429 | L73: 125000 | M73: iva | O73: =(L73/K73)-1 -> 0.28298556 | P73: =K73*F73 -> 0
A74: Aclaramiento consultorio Pola Office + LISTO 1PCTE | E74: 0 | F74: 0 | G74: abraham | I74: 0 | K74: 141000 | L74: 175000 | O74: =(L74/K74)-1 -> 0.24113475 | P74: =K74*F74 -> 0
A75: Aclaramiento consultorio Pola Office 3 PCTE S POLVO Y LIQUIDO | E75: 0 | F75: 0 | G75: abraham | I75: 0 | K75: 292000 | L75: 365000 | O75: =(L75/K75)-1 -> 0.25 | P75: =K75*F75 -> 0
A76: Aclaramiento consultorio pola office bulk kit | E76: 2 | F76: 0 | G76: abraham | I76: 0 | J76: 45748 | K76: 287900 | L76: 359800 | O76: =(L76/K76)-1 -> 0.24973949 | P76: =K76*F76 -> 0
A77: Aclaramiento consultorio Potenza 38% (1,3+0,4) | G77: New stetic | H77: 0 | I77: 0 | J77: 45870 | K77: 42000 | L77: 65000 | O77: =(L77/K77)-1 -> 0.54761905 | P77: =K77*F77 -> 0
A78: Aclaramiento consultorio Potenza 38% 1 jeringa+ Barrera 1g+ 1 frasco Neutralizador | G78: New stetic | H78: 0 | I78: 0 | J78: 45869 | K78: 65450 | L78: 88000 | O78: =(L78/K78)-1 -> 0.34453782 | P78: =K78*F78 -> 0
A79: aclaramiento HP BLUE 6 JERINGAS | E79: 0 | F79: 0 | L79: 312000
A80: ACONDICIONADOR DE TEJIDOS COE CONFORT LIQUIDO | B80: GC | C80: promo $77.700 | E80: 0 | F80: 0 | G80: LA MUELA - DORA - RAMON - masdental | K80: 80808 | L80: 120000 | M80: exc | N80: 110000 | O80: =(L80/K80)-1 -> 0.48500149 | P80: =K80*F80 -> 0
A81: ACONDICIONADOR DE TEJIDOS COE CONFORT POLVO | B81: GC | E81: 0 | F81: 0 | G81: LA MUELA - DORA - RAMON - masdental | K81: 97275 | L81: 130000 | M81: exc | N81: 120000 | O81: =(L81/K81)-1 -> 0.33641737 | P81: =K81*F81 -> 0
A82: ACONDICIONADOR DE TEJIDOS COE CONFORT Y COE SOFT X PORCION | B82: GC | E82: 0 | F82: 0 | G82: La Muela | K82: =130000/15 -> 8666.6667 | L82: 20000 | O82: =(L82/K82)-1 -> 1.3076923 | P82: =K82*F81 -> 0
A83: ACONDICIONADOR DE TEJIDOS COE SOFT LIQUIDO | B83: GC | E83: 0 | F83: 0 | G83: LA MUELA - DORA - RAMON - masdental | K83: 80808 | L83: 120000 | M83: exc | O83: =(L83/K83)-1 -> 0.48500149 | P83: =K83*F83 -> 0
A84: ACONDICIONADOR DE TEJIDOS COE SOFT POLVO | B84: GC | E84: 0 | F84: 0 | G84: LA MUELA - DORA - RAMON - masdental | K84: 87241 | L84: 120000 | M84: exc | O84: =(L84/K84)-1 -> 0.37550005 | P84: =K84*F84 -> 0
A85: ACOPLE CORDEN PARA PIEZAS UNIDAD | E85: 0 | F85: 0 | G85: larry alfredo | K85: 25000 | L85: 35000 | O85: =(L85/K85)-1 -> 0.4 | P85: =K85*F85 -> 0
A86: Acrilico auto 125 g JB | G86: New Stetic | H86: 0 | I86: 15 | K86: 18683 | L86: 24000 | M86: 1.19 | N86: 22000 | O86: =(L86/K86)-1 -> 0.28459027 | P86: =K86*F86 -> 0
A87: Acrilico auto 125 g TRANSPARENTE | G87: New Stetic | H87: 0 | I87: 19 | K87: 18683 | L87: 24000 | M87: 1.19 | N87: 22000 | O87: =(L87/K87)-1 -> 0.28459027 | P87: =K87*F87 -> 0
A88: Acrilico auto 125 g VR1 | G88: New Stetic | H88: 0 | I88: 15 | K88: 18683 | L88: 24000 | M88: 1.19 | N88: 22000 | O88: =(L88/K88)-1 -> 0.28459027 | P88: =K88*F88 -> 0
A89: Acrilico auto 60 g A 3.5 | G89: New Stetic | H89: 0 | I89: 3 | K89: 18683 | L89: 24000 | M89: 1.19 | N89: 21000 | O89: =(L89/K89)-1 -> 0.28459027 | P89: =K89*F89 -> 0
A90: Acrilico auto 60 g A0 | G90: New Stetic | H90: 0 | I90: 1 | K90: 18683 | L90: 24000 | M90: 1.19 | N90: 21000 | O90: =(L90/K90)-1 -> 0.28459027 | P90: =K90*F90 -> 0
A91: Acrilico Auto 60 g A1 | G91: New Stetic | H91: 0 | I91: 12 | K91: 18683 | L91: 24000 | M91: 1.19 | N91: 21000 | O91: =(L91/K91)-1 -> 0.28459027 | P91: =K91*F91 -> 0
A92: Acrilico auto 60 g A2 | G92: New Stetic | H92: 0 | I92: 7 | K92: 18683 | L92: 24000 | M92: 1.19 | N92: 21000 | O92: =(L92/K92)-1 -> 0.28459027 | P92: =K92*F92 -> 0
A93: Acrilico auto 60 g A3 | G93: New Stetic | H93: 0 | I93: 5 | K93: 18683 | L93: 24000 | M93: 1.19 | N93: 21000 | O93: =(L93/K93)-1 -> 0.28459027 | P93: =K93*F93 -> 0
A94: Acrilico Auto 60 g B2 | G94: New Stetic | H94: 0 | I94: 4 | K94: 18683 | L94: 24000 | M94: 1.19 | N94: 21000 | O94: =(L94/K94)-1 -> 0.28459027 | P94: =K94*F94 -> 0
A95: Acrilico auto 60 g JB | G95: New Stetic | H95: 0 | I95: 10 | K95: 9639 | L95: 14000 | M95: 1.19 | N95: 12000 | O95: =(L95/K95)-1 -> 0.45243282 | P95: =K95*F95 -> 0
A96: Acrilico auto 60 g Transparente | G96: New Stetic | H96: 0 | I96: 14 | K96: 9639 | L96: 14000 | M96: 1.19 | N96: 12000 | O96: =(L96/K96)-1 -> 0.45243282 | P96: =K96*F96 -> 0
A97: Acrilico auto 60 g VR1 | G97: New Stetic | H97: 0 | I97: 7 | K97: 9639 | L97: 14000 | M97: 1.19 | N97: 12000 | O97: =(L97/K97)-1 -> 0.45243282 | P97: =K97*F97 -> 0
A98: Acrilico auto 60 g VRX | G98: New Stetic | H98: 0 | I98: 10 | K98: 9639 | L98: 14000 | M98: 1.19 | N98: 12000 | O98: =(L98/K98)-1 -> 0.45243282 | P98: =K98*F98 -> 0
A99: Acrilico auto JB 500 gm | G99: New Stetic | H99: 0 | I99: 2 | J99: 1/10/2025 09-2026 | K99: 55167 | L99: 70000 | N99: 64000 | O99: =(L99/K99)-1 -> 0.26887451 | P99: =K99*F99 -> 0
A100: Acrilico auto liquido 1000 cc | G100: New Stetic | H100: 0 | I100: 1 | J100: 46508 | K100: =54400*1.19 -> 64736 | L100: 78000 | N100: 72000 | O100: =(L100/K100)-1 -> 0.20489372 | P100: =K100*F100 -> 0
...

Sheet OXXI
B1: referencias | E1: PEDIDO SUR | F1: PEDIDO NORTE | G1: TOTAL
A2: Abreboca sencillo adulto | B2: OXXI $ 11067 NISSI $7556 | E2: 20 | F2: 20 | G2: 40 | H2: =G2*7556 -> 302240
A3: Abreboca sencillo niño | B3: OXXI $ 11067 NISSI $7557 | E3: 10 | F3: 0 | G3: 10 | H3: =10*7557 -> 75570
A4: CAJA RETENEDORA PEQUEÑA | B4: oxxi $1220 orhto prof $1071 | E4: 100 | F4: 200 | G4: 300 | H4: =300*1071 -> 321300

Sheet THERACEM
A1: THERACEM
C3: FECHA VCT | D3: LOTE
A4: NORTE | B4: 9 | C4: 46021 | D4: 2400004102
A5: NORTE | B5: 1 | C5: 45931 | D5: 2400002387
A6: CESAR | B6: 6 | C6: 45931 | D6: 2400002664
A7: SUR | B7: 4 | C7: 45935 | D7: 2400002664
A8: SUR | B8: 1 | C8: 45934 | D8: 2400002387
A12: THERACEM
C14: FECHA VCT | D14: LOTE
A15: NORTE | B15: 9 | C15: 46021 | D15: 2400004102
A16: NORTE | B16: 2 | C16: 45931 | D16: 2400002387
B17: 10 | C17: 45931 | D17: 2400002664

Sheet FECHA VTO CORTA
A2: PRODUCTO | B2: PROVEDOR | D2: FECHA DE VENCIMIENTO | E2: COSTO | F2: VENTA | G2: PRECIO PROMO | H2: PRECIO MALETERO
A3: Adhesivo bond 2.1 4ml maquira | B3: SOCCIDEN $22000 | D3: 45901 | E3: 24000 | F3: 44000
A4: Adhesivo coltene COAT BOND | B4: promo nov $72348 | D4: 46082 | E4: 87000 | F4: 105000
A5: Barrera Gingival Max Dam Jeringa 2 g Maquira | B5: COMPRE 17600 | C5: PRECIO 20 MAYO | D5: 46023 | E5: 21120 | F5: 38000
A6: Barrera Gingival Top Dam 2 g FGM | B6: SOCCID $19700 X 50 | C6: Barrera | D6: 46054 | E6: 19200 | F6: 32000
A7: cemento temporal Applic 2g maquira x 2 jeringas | D7: 45839 | E7: =38104/2 -> 19052 | F7: 34000
A8: CHOISE Try-in paste traslucido 2g bisco Probador | C8: promo $85 | D8: 45839 | E8: =86000 -> 86000 | F8: 105000
A9: fix RESINA ortodoncia 2.5ml | B9: ortho $35000 | D9: 45992 | E9: 47430 | F9: 78000
A10: FUJI 1 CEMENTANTE BLANCO LETRA ROJA | B10: masdental $158900 la muela promo $121500 | D10: 45962 | E10: 121500 | F10: 165000
A11: FUJI 2 RESTAURATIVO BLANCO CON VERDE AUTO | B11: promo $121500 | D11: 46113 | E11: 121500 | F11: 165000
A12: orthocem resina ortodoncia FGM | B12: antioq $45000 soccid $ 47000 plus $68000 | D12: 45809 | E12: =85000*0.8 -> 68000 | F12: 85000
A13: Resina Charisma jeringa 4gr BL | C13: ALTA ESTETICA | D13: 45870 | E13: 180000 | F13: 260000
A14: Thera CEM Bisco | B14: promo 208200 | C14: en promo se compro a $289167 | D14: 1/12/2025 10-2025 | E14: 315455 | F14: 390000
A15: PARACORE | D15: 1 21-08-2025 2 1-02-2025 | E15: 350000 | F15: 290000

Sheet TEMPO NORTE PEDIDO BIODENTALES
A1: pedi junio 28 | B1: referencias | E1: PEDIDO SUR | F1: PEDIDO NORTE | H1: INVENT SUR mar 21 | I1: INVENT NTE | J1: FECHA VCMTO | K1: PRECIO COMPRA | L1: precio venta
A2: ARTICULADOR plastico PASTA transparenteñ | F2: 0 | G2: biodentales Monica jorge - aquiles | K2: 3374 | L2: 6000
A3: Cera azul WHIPMIX PAQUETE X 20 BARRAS VTA UNIDAD | F3: 0 | G3: Biodentales | I3: 20 | K3: =22950*1.19/20 -> 1365.525 | L3: 2000
A4: Cera Blanca marfil WHIPMIX PAQUETE X 120 BARRAS | F4: 0 | G4: Biodentales | I4: 20 | K4: =(81855*1.19)/120 -> 811.72875 | L4: 2000
A5: Cera Blanca marfil WHIPMIX PAQUETE X 20 BARRAS | F5: 0 | G5: Biodentales | I5: 20 | K5: =22950*1.19/20 -> 1365.525 | L5: 2000
A6: Cera rojo WHIPMIX PAQUETE X 20 BARRAS VTA UNIDAD | F6: 0 | G6: Biodentales | I6: 20 | K6: =22950*1.19/20 -> 1365.525 | L6: 2000
A7: Cera verde WHIPMIX PAQUETE X 20 BARRAS VTA UNIDAD | F7: 0 | G7: Biodentales | I7: 20 | J7: 46722 | K7: =22950*1.19/20 -> 1365.525 | L7: 2000
A8: cerafina x 60 | F8: 0 | G8: monica - ramon biodentales | J8: 45992 | K8: =4563*1.19 -> 5429.97 | L8: 8000
A9: cerafina x 90 | F9: 0 | G9: monica - ramon biodentales | K9: =7677*1.19 -> 9135.63 | L9: 12000
A10: CUBETA PLASTICA IMPRESION PARA NIÑO JUEGO X6 | F10: 0 | G10: biodentales-NATURAL SISTEM | I10: 8 | K10: =11640*1.19 -> 13851.6 | L10: 20000
A11: Fresa carburo 1/2 HP Tallo largo | C11: CARBURO | F11: 0 | G11: biodentaleS MDS masterdent ramon | K11: =34290*1.19/5 -> 8161.02 | L11: 18000
A12: fresa carburo 245 FG Tallo Corto pediatrica | C12: CARBURO | F12: 0 | G12: biodentaleS MDS ramon | K12: =34290*1.19/5 -> 8161.02 | L12: 18000
A13: fresa carburo 330 FG Tallo Corto pediatrica | C13: CARBURO | F13: 0 | G13: biodentaleS MDS ramon | K13: =34290*1.19/5 -> 8161.02 | L13: 18000
A14: fresa carburo 331 FG Tallo Corto | C14: CARBURO | F14: 0 | G14: biodentaleS MDS ramon | K14: =34290*1.19/5 -> 8161.02 | L14: 18000
A15: fresa carburo 331 L FG Tallo Corto | C15: CARBURO | F15: 0 | G15: biodentaleS MDS ramon | K15: =34290*1.19/5 -> 8161.02 | L15: 18000
A16: FRESA CARBURO FG 700 Tallo Corto | C16: CARBURO | F16: 0 | G16: biodentaleS MDS ramon | K16: =34290*1.19/5 -> 8161.02 | L16: 18000
A17: FRESA CARBURO FG 701 Tallo Corto | C17: CARBURO | F17: 0 | G17: biodentaleS MDS ramon | K17: =34290*1.19/5 -> 8161.02 | L17: 18000
A18: FRESA CARBURO FG 702 Tallo Corto | B18: 245034 | C18: CARBURO | F18: 0 | G18: biodentaleS MDS ramon | K18: =34290*1.19/5 -> 8161.02 | L18: 18000
A19: FRESA CARBURO FG 703 Tallo Corto | B19: 245035 | C19: CARBURO | F19: 0 | G19: biodentaleS MDS ramon | K19: =34290*1.19/5 -> 8161.02 | L19: 18000
A20: FRESA CARBURO HP 700 Tallo Largo | B20: 245032 | C20: CARBURO | F20: 0 | G20: biodentaleS MDS masterdent ramon | K20: 6378 | L20: 18000
A21: FRESA CARBURO HP 701 Tallo Largo | B21: 245033 | C21: CARBURO | F21: 0 | G21: biodentaleS MDS masterdent ramon | K21: 6378 | L21: 18000
A22: FRESA CARBURO HP 702 Tallo Largo | B22: 245034 | C22: CARBURO | F22: 0 | G22: biodentaleS MDS masterdent ramon | K22: 6378 | L22: 18000
A23: FRESA CARBURO HP 703 Tallo Largo | B23: 245035 | C23: CARBURO | F23: 0 | G23: biodentaleS MDS masterdent ramon | K23: 6378 | L23: 18000
A24: fresa carburo N° 1 FG Tallo Corto | C24: CARBURO | F24: 0 | G24: biodentaleS MDS ramon | K24: =34290*1.19/5 -> 8161.02 | L24: 18000
A25: fresa carburo N° 1 HP Tallo largo | C25: CARBURO | F25: 0 | G25: biodentaleS MDS masterdent ramon | K25: =34290*1.19/5 -> 8161.02 | L25: 18000
A26: fresa carburo N° 1/2 FG Tallo Corto pediatrica | C26: CARBURO | F26: 0 | G26: biodentaleS MDS ramon | K26: =34290*1.19/5 -> 8161.02 | L26: 18000
A27: fresa carburo N° 1/4 FG Tallo Corto pediatrica | C27: CARBURO | F27: 0 | G27: biodentaleS MDS ramon | K27: =34290*1.19/5 -> 8161.02 | L27: 18000
A28: fresa carburo N° 1P FG Tallo Corto pediatrica | C28: CARBURO | F28: 0 | G28: biodentaleS MDS ramon | K28: =34290*1.19/5 -> 8161.02 | L28: 18000
A29: fresa carburo N° 2 FG Tallo Corto | C29: CARBURO | F29: 0 | G29: biodentaleS MDS ramon | K29: =34290*1.19/5 -> 8161.02 | L29: 18000
A30: fresa carburo N° 2P FG Tallo Corto pediatrica | C30: CARBURO | F30: 0 | G30: biodentaleS MDS ramon | K30: =34290*1.19/5 -> 8161.02 | L30: 18000
A31: fresa carburo N° 3 FG Tallo Corto | C31: CARBURO | F31: 0 | G31: biodentaleS MDS ramon | K31: =34290*1.19/5 -> 8161.02 | L31: 18000
A32: fresa carburo N° 3 HP Tallo largo | C32: CARBURO | F32: 0 | G32: biodentaleS MDS masterdent ramon | K32: =34290*1.19/5 -> 8161.02 | L32: 18000
A33: fresa carburo N° 3P FG Tallo Corto pediatrica | C33: CARBURO | F33: 0 | G33: biodentaleS MDS ramon | K33: =34290*1.19/5 -> 8161.02 | L33: 18000
A34: fresa carburo N° 4 FG Tallo Corto | C34: CARBURO | F34: 0 | G34: biodentaleS MDS ramon | K34: =34290*1.19/5 -> 8161.02 | L34: 18000
A35: fresa carburo N° 4 HP tallo largo | B35: 245039 | C35: CARBURO | F35: 0 | G35: biodentaleS MDS masterdent ramon | K35: 6378 | L35: 18000
A36: fresa carburo N° 5 FG Tallo Corto | C36: CARBURO | F36: 0 | G36: biodentaleS MDS ramon | K36: =34290*1.19/5 -> 8161.02 | L36: 18000
A37: fresa carburo N° 5 HP tallo largo | C37: CARBURO | F37: 0 | G37: biodentaleS MDS masterdent ramon | K37: =34290*1.19/5 -> 8161.02 | L37: 18000
A38: fresa carburo N° 6 FG Tallo Corto | C38: CARBURO | F38: 0 | G38: biodentaleS MDS ramon | K38: =34290*1.19/5 -> 8161.02 | L38: 18000
A39: fresa carburo N° 6 HP tallo largo | B39: 245041 | C39: CARBURO | F39: 0 | G39: biodentaleS MDS masterdent ramon | K39: 6378 | L39: 18000
A40: fresa carburo N° 7 FG tallo corto | C40: CARBURO | F40: 0 | G40: biodentaleS MDS ramon | K40: =34290*1.19/5 -> 8161.02 | L40: 18000
A41: fresa carburo N° 7 HP tallo largo | C41: CARBURO | F41: 0 | G41: biodentaleS MDS masterdent ramon | K41: =34290*1.19/5 -> 8161.02 | L41: 18000
A42: fresa carburo N° 8 FG Tallo Corto | C42: CARBURO | F42: 0 | G42: biodentaleS MDS ramon | K42: =34290*1.19/5 -> 8161.02 | L42: 18000
A43: fresa carburo N° 8 HP tallo largo | B43: 245043 | C43: CARBURO | F43: 0 | G43: biodentaleS MDS masterdent ramon | K43: 6378 | L43: 18000
A44: NASION COMPLETO WHIPMIX ORIGINAL | F44: 0 | G44: Biodentales | K44: 244200 | L44: 290000
A45: YESO WHIPMIX X 70 GR MOUNTING STONE | B45: OK | F45: 0 | G45: Biodentales | I45: 130 | K45: =494050/214 -> 2308.6449 | L45: 3500
A46: YESO WHIPMIX X LB 500 GR MOUNTING STONE | F46: 66 | G46: Biodentales | I46: 25 | K46: =492980/33 -> 14938.788 | L46: 18000
A47: Yeso WHIPMIX TIPO 2 X 100 GR LABORATORY PLASTER | B47: OK | F47: 0 | G47: Biodentales | I47: 100 | K47: =323440/150 -> 2156.2667 | L47: 3500
A48: Yeso WHIPMIX TIPO 2 X Lb 500 LABORATORY PLASTER | F48: 0 | G48: Biodentales | I48: =33+33+33 -> 99 | K48: =322260/33 -> 9765.4545 | L48: 15000
A49: YESO WHIPMIX TIPO 3 X 100 GR QUICKSTONE (AMARILLO) | B49: OK | F49: 214 | G49: Biodentales | I49: 40 | K49: =384270/150 -> 2561.8 | L49: 3500
A50: YESO WHIPMIX TIPO 3 X LB 500 GR QUICKSTONE (AMARILLO) | F50: 33 | G50: Biodentales | I50: =33+25 -> 58 | K50: =382880/33 -> 11602.424 | L50: 18000
A51: YESO WHIPMIX TIPO 4 LB X 500 GR SILKY ROCK (ROSADO) | F51: 33 | G51: Biodentales | I51: =33+15 -> 48 | K51: =412440/33 -> 12498.182 | L51: 18000
A52: YESO WHIPMIX TIPO 4 X 100 GR SILKY ROCK (ROSADO) | B52: OK | F52: 0 | G52: Biodentales | I52: 50 | K52: =413830/150 -> 2758.8667 | L52: 3500
A53: YESO WHIPMIX TIPO 5 LB X 500GR jadestone VERDE | F53: 33 | G53: Biodentales | I53: 25 | K53: =446500/33 -> 13530.303 | L53: 18000
A54: YESO WHIPMIX TIPO 5 X 100 GR (VERDE) jadestone | B54: OK | F54: 0 | G54: Biodentales | I54: 50 | K54: =448110/150 -> 2987.4 | L54: 3500

Sheet COPIA NORTE 28 JUN 
B1: referencias | E1: PEDIDO SUR | F1: PEDIDO NORTE | H1: INVENT SUR mar 21 | I1: INVENT NTE | J1: FECHA VCMTO | K1: PRECIO COMPRA | L1: precio venta | M1: IVA | N1: PRECIO MALTERO | O1: % | P1: VR PEDIDO
A2: abre bocas Umbrella | E2: 0 | F2: 0 | G2: Pluss Dent GAB VEL | H2: 0 | I2: 0 | K2: =9288*1.19 -> 11052.72 | L2: 15000 | O2: =(L2/K2)-1 -> 0.357132 | P2: =K2*F2 -> 0
A3: Abreboca manual gancho DOBLE EXTREMO NEGRO | E3: 0 | F3: 0 | G3: IMPORTADA | I3: 8 | K3: 8746 | L3: 30000 | M3: 19 | O3: =(L3/K3)-1 -> 2.4301395 | P3: =K3*F3 -> 0
A4: Abreboca manual gancho DOBLE EXTREMO TRANSPARENTE | E4: 0 | F4: 0 | G4: IMPORTADA | I4: 50 | K4: =1962*2 -> 3924 | L4: 30000 | O4: =(L4/K4)-1 -> 6.6452599 | P4: =K4*F4 -> 0
A5: Abreboca manual gancho PEQUEÑO | E5: 0 | F5: 0 | G5: IMPORTADA | I5: 100 | K5: 1712 | L5: 10000 | O5: =(L5/K5)-1 -> 4.8411215 | P5: =K5*F5 -> 0
A6: Abreboca AZUL Y ROJO AMARILLO | E6: 0 | F6: 0 | G6: ELVER LOZANO BOGOTA | I6: rojo 1 azul 1 | K6: 4500 | L6: 12000 | O6: =(L6/K6)-1 -> 1.6666667 | P6: =K6*F6 -> 0
A7: abreboca Con retractor adulto | E7: 0 | F7: 0 | G7: UPEGUI | I7: BLANCO 43 NEGRO 10 | K7: 16900 | L7: 24000 | O7: =(L7/K7)-1 -> 0.42011834 | P7: =K7*F7 -> 0
A8: abreboca Con retractor PEDIATRICO | E8: 0 | F8: 0 | G8: UPEGUI | I8: 20 | K8: 16900 | L8: 24000 | O8: =(L8/K8)-1 -> 0.42011834 | P8: =K8*F8 -> 0
A9: Abreboca manual gancho GRANDE | E9: 0 | F9: 0 | G9: IMPORTADA | I9: 50 | K9: 1426.9789 | L9: 10000 | O9: =(L9/K9)-1 -> 6.0078119 | P9: =K9*F9 -> 0
A10: Abreboca sencillo adulto | B10: OXXI $ 11067 NISSI $7556 | E10: 20 | F10: 20 | G10: OXXI NISSI | I10: =8+16*5 -> 88 | K10: =9300*1.19/5 -> 2213.4 | L10: 8000 | O10: =(L10/K10)-1 -> 2.614349 | P10: =K10*F10 -> 44268
A11: Abreboca sencillo niño | B11: OXXI $ 11067 NISSI $7557 | E11: 10 | F11: 0 | G11: OXXI NISSI | I11: 26 | K11: =9300*1.19/5 -> 2213.4 | L11: 8000 | O11: =(L11/K11)-1 -> 2.614349 | P11: =K11*F11 -> 0
A12: abreboca sin retractor | E12: 0 | F12: 0 | G12: UPEGUI | I12: 10 | K12: 16900 | L12: 24000 | O12: =(L12/K12)-1 -> 0.42011834 | P12: =K12*F12 -> 0
A13: abrebocas aclaramiento tipo optragate | E13: 0 | F13: 0 | G13: IMPORTADA | I13: 58 | K13: 4602 | L13: 12000 | O13: =(L13/K13)-1 -> 1.6075619 | P13: =K13*F13 -> 0
A14: Accufilm Papel de articular aqua film x 280 tiras | E14: 0 | F14: 0 | G14: La muela miguel | I14: 1 | K14: =65000/200 -> 325 | L14: 800 | O14: =(L14/K14)-1 -> 1.4615385 | P14: =K14*F14 -> 0
A15: Accufilm Papel de articular CIRENE aqua film x 280 tiras | E15: 0 | F15: 0 | G15: La muela miguel | K15: 65000 | L15: 105000 | N15: 90000 | O15: =(L15/K15)-1 -> 0.61538462 | P15: =K15*F15 -> 0
A16: Aceite 3 en 1 | E16: 0 | G16: CENTRO HOYOSTOOL | K16: =3200*1.19 -> 3808 | L16: 6000 | O16: =(L16/K16)-1 -> 0.57563025 | P16: =K16*F16 -> 0
A17: aceite lubricante - pieza de mano Dental handpiece 300ml | E17: 0 | F17: 0 | G17: DTM | K17: 28000 | L17: 48000 | N17: 38000 | O17: =(L17/K17)-1 -> 0.71428571
A18: aceite lubricante - pieza de mano Dental handpiece 550ml | E18: 0 | F18: 0 | G18: DTM | K18: 35000 | L18: 54000 | N18: 44000 | O18: =(L18/K18)-1 -> 0.54285714
A19: aceite lubricante - pieza de mano PANASPRAY PLUS NSK 480ML | B19: NSK | E19: 0 | F19: 0 | G19: LA MUELA | I19: 10 | J19: 45717 | K19: =121849*1.19 -> 145000.31 | L19: 178000 | N19: 168000 | O19: =(L19/K19)-1 -> 0.22758358 | P19: =K19*F19 -> 0
A20: aceite lubricante - pieza de mano WYH 400ML | B20: euro $96250 | G20: MASDENTAL EURODENT | I20: 0 | K20: 116000 | L20: 145000 | N20: 120000 | O20: =(L20/K20)-1 -> 0.25 | P20: =K20*F20 -> 0
A21: Aceite lubricante Bendechk 300ml | E21: 0 | F21: 0 | G21: makrodent DTM | K21: 35000 | L21: 48000 | O21: =(L21/K21)-1 -> 0.37142857 | P21: =K21*F21 -> 0
A22: aceite lubricante de piezas digixpray 240ml | E22: 0 | F22: 0 | G22: muela | K22: 24850 | L22: 48000 | M22: iva | N22: 34000
A23: Aceite lubricante en Spray 200 ml- KAVO | C23: AGOTADO | E23: 0 | F23: 0 | G23: Pluss Dent GAB VEL | H23: 0 | I23: 0 | K23: 49504 | L23: 65000 | O23: =(L23/K23)-1 -> 0.31302521 | P23: =K23*F23 -> 0
A24: aceite lubricante pequeño - pieza de mano 50 ml | E24: 0 | G24: RAMON | K24: 7400 | L24: 12000 | O24: =(L24/K24)-1 -> 0.62162162 | P24: =K24*F24 -> 0
A25: Aceite lubricante Quiruspray 200 cc - pieza de mano | B25: ramon $29.500 aquiles $24.871 | E25: 0 | G25: RAMON AQUILES | K25: =24789.92*1.19 -> 29500.005 | L25: 39000 | O25: =(L25/K25)-1 -> 0.32203368 | P25: =K25*F25 -> 0
A26: Aceite lubricante Universal en Spray 250 ml- Adensys | E26: 0 | F26: 0 | G26: Pluss Dent GAB VEL | H26: 0 | I26: 10 | J26: 46174 | K26: =50500*1.19 -> 60095 | L26: 76000 | N26: 65000 | O26: =(L26/K26)-1 -> 0.26466428 | P26: =K26*F27 -> 0
A27: Aceite LUBRICANTE X200 ML Maquira | E27: 0 | F27: 0 | G27: SOCCIDENTALES | I27: 0 | J27: 46174 | K27: =26000*1.19 -> 30940 | L27: 55000 | O27: =(L27/K27)-1 -> 0.77763413 | P27: =K27*#REF! -> #REF!
A28: Aceite super lubry 50ml | E28: 0 | F28: 0 | G28: AQUILES | I28: 0 | J28: 46174 | K28: 7500 | L28: 12000 | O28: =(L28/K28)-1 -> 0.6 | P28: =K28*F28 -> 0
A29: acetato lamina rosada 0.6 | E29: 0 | G29: RAMON | K29: 1800 | L29: 3500 | O29: =(L29/K29)-1 -> 0.94444444 | P29: =K29*F29 -> 0
A30: acetato rigido ACE | E30: 0 | G30: RAMON | K30: 6400 | L30: 9000 | O30: =(L30/K30)-1 -> 0.40625 | P30: =K30*F30 -> 0
A31: acido clorhidrico removedor de manchas opalustre FGM whiteness RM 6% | B31: antioq $95200 soccid $ 80,206 plus $79968 | E31: 0 | F31: 0 | G31: FGM soccident | I31: 0 | J31: 46082 | K31: =100000*0.8*1.19 -> 95200 | L31: 145000 | O31: =(L31/K31)-1 -> 0.52310924 | P31: =K31*F31 -> 0
A32: Acido desmineralizante 2.5 coltene | B32: ACIDO | E32: 0 | F32: 0 | G32: Ultradental | I32: 0 | K32: 10868 | L32: 18000 | O32: =(L32/K32)-1 -> 0.6562385 | P32: =K32*F32 -> 0
A33: acido desmineralizante 2.5 Densell 12g 35% | B33: ACIDO | E33: 0 | F33: 0 | G33: La muela - ramon | J33: 46478 | K33: 12000 | L33: 20000 | M33: exc | N33: 18000 | O33: =(L33/K33)-1 -> 0.66666667 | P33: =K33*F33 -> 0
A34: Acido desmineralizante 35% ultradent 1.2ml | B34: ACIDO | E34: 2 | F34: 0 | G34: Gabriel Vel pluss | H34: 2 | I34: 3 | K34: 13272 | L34: 22000 | O34: =(L34/K34)-1 -> 0.65762508 | P34: =K34*F34 -> 0
A35: acido desmineralizante 37% fosforico MAQUIRA 2.5 | B35: ACIDO | C35: PRECIO MAYO 20 | D35: =(6500*1.19)/3 -> 2578.3333 | E35: 0 | F35: 0 | G35: RAMON CLAUDIA SOCCIDENTALES | J35: 45962 | K35: =(11654*1.19)/3 -> 4622.7533 | L35: 13000 | M35: EXC | O35: =(L35/K35)-1 -> 1.8121769 | P35: =K35*F35 -> 0
A36: acido desmineralizante angelus 3 grs | B36: ACIDO | E36: 0 | F36: 0 | G36: CLAUDIA | I36: 0 | K36: 2000 | L36: 10000 | O36: =(L36/K36)-1 -> 4 | P36: =K36*F36 -> 0
A37: Acido desmineralizante FGM condac 12.5 ML | B37: ACIDO promo antoq $24375 SOCCIDEN 20825 plus20000 | E37: 0 | F37: 0 | G37: FGM soccident | I37: 0 | J37: 45992 | K37: =32500*0.8 -> 26000 | L37: 35000 | M37: exc | O37: =(L37/K37)-1 -> 0.34615385 | P37: =K37*F37 -> 0
A38: Acido Desmineralizante proquident 10ML jumbo | B38: ACIDO | G38: PROQUIDENT | I38: 2 | J38: 46844 | K38: 14173 | L38: 24000 | O38: =(L38/K38)-1 -> 0.69336062 | P38: =K38*#REF! -> #REF!
A39: Acido Desmineralizante Select H V ETCH 5ML Bisco | B39: promo $48.450 mayo/25 | G39: JULVIDENT bisco | I39: 11 | J39: 46447 | K39: 54000 | L39: 68000 | M39: EXC | O39: =(L39/K39)-1 -> 0.25925926 | P39: =K39*F39 -> 0
A40: Acido desmineralizante SUPER ETCH SDI 12 gm | B40: ACIDO | F40: 0 | G40: ABRAHAM | J40: 46296 | K40: 33800 | L40: 42500 | M40: exc | O40: =(L40/K40)-1 -> 0.25739645 | P40: =K40*F40 -> 0
A41: Acido desmineralizante ultra ETCH 30ml ultradent | B41: ACIDO | E41: 0 | F41: 0 | G41: Gabriel Vel pluss | H41: 1 | I41: 3 | K41: 150579 | L41: 210000 | N41: tempo $150,000 | O41: =(L41/K41)-1 -> 0.39461678 | P41: =K41*F41 -> 0
A42: Acido Desmineralizante Zafira 10 ml | B42: ACIDO | C42: kit zafira | G42: New Stetic | H42: 10 | J42: revisar | K42: 12400 | L42: 18000 | M42: exc | N42: 15000 | O42: =(L42/K42)-1 -> 0.4516129 | P42: =K42*F42 -> 0
A43: acido fluorhidrico 10% Jeringa 2.5 ml Angelus | E43: 0 | F43: 0 | G43: CLAUDIA | I43: 0 | K43: 37140 | L43: 46400 | O43: =(L43/K43)-1 -> 0.24932687 | P43: =K43*F43 -> 0
A44: acido fluorhidrico 10% Jeringa 2.5 ml Maquira | E44: 0 | F44: 0 | G44: SOCCIDENTALES CLAUDIA | I44: 8 | K44: =21315*1.19 -> 25364.85 | L44: 38000 | M44: EXC | N44: 32000 | O44: =(L44/K44)-1 -> 0.4981362 | P44: =K44*F44 -> 0
A45: ACIDO FLUORHIDRICO 3ML (JERINGA) prodont | E45: 0 | F45: 0 | G45: PRODONT | I45: 5 | J45: 46478 | K45: =23294*1.19 -> 27719.86 | L45: 40000 | N45: 35000 | O45: =(L45/K45)-1 -> 0.44300873 | P45: =K45*F45 -> 0
A46: acido fluorhidrico 5% 3 g BM4 | E46: 0 | F46: 0 | G46: CLAUDIA | I46: 0 | K46: 10320 | L46: 30000 | O46: =(L46/K46)-1 -> 1.9069767 | P46: =K46*F46 -> 0
A47: acido fluorhidrico 5% porcelana jeringa 2.5 ml FGM | B47: SOCCID $24514 plus $25600 | E47: 0 | F47: 0 | G47: FGM soccident | I47: 0 | J47: 46023 | K47: =40000*0.8*1.19 -> 38080 | L47: 56000 | O47: =(L47/K47)-1 -> 0.47058824 | P47: =K47*F47 -> 0
A48: ACIDO FLUORHIDRICO 7ML (GOTERO) prodont | E48: 0 | F48: 10 | G48: PRODONT | I48: 4 | J48: 46569 | K48: =25757*1.19 -> 30650.83 | L48: 45000 | N48: 38000 | O48: =(L48/K48)-1 -> 0.46814948 | P48: =K48*F48 -> 306508.3
A49: acido fluorhidrico 9.6% Jeringa 2 g Eufar | B49: Aquiles $32000 ramon $32000 EUFAR $29354 | E49: 0 | F49: 0 | G49: AQUILES RAMON GABRIEL VELASQUEZ Eufar | K49: =24667*1.19 -> 29353.73 | L49: 45000 | N49: 35000 | O49: =(L49/K49)-1 -> 0.53302493 | P49: =K49*F49 -> 0
A50: Acido fluorhidrico grabador para porcelana ultradent | B50: pluss $24804 | E50: 0 | F50: 0 | G50: Gabriel Vel pluss | H50: 3 | I50: 6 | K50: 30257 | L50: 52000 | M50: EXC | N50: 38000 | O50: =(L50/K50)-1 -> 0.71861057 | P50: =K50*F50 -> 0
A51: Acido Fluorhidrico porcelain etch 9,5% Bisco | B51: promo $106.250 mayo/25 | G51: JULVIDENT bisco | I51: 3 | K51: 118000 | L51: 170000 | M51: EXC | O51: =(L51/K51)-1 -> 0.44067797 | P51: =K51*F51 -> 0
A52: aclaramiento casero Clariant 16% Angelus | F52: 0 | G52: ABRAHAM | K52: 19710 | L52: 24630 | O52: =(L52/K52)-1 -> 0.24961948 | P52: =K52*F52 -> 0
A53: Aclaramiento casero OPALECENSE x 2 JERINGAS | C53: Casero | E53: 0 | F53: 0 | G53: CLAUDIA pluss dent | H53: 3 | I53: 4 | J53: revisar | K53: 45031 | L53: 58000 | M53: iva | O53: =(L53/K53)-1 -> 0.2880016 | P53: =K53*F53 -> 0
A54: Aclaramiento casero Opalecense Go caja x 10 | B54: pluss $211.000 promo 2x 159 gabriel velasq promo x 2 155 | C54: Casero | E54: 1 | F54: 0 | G54: CLAUDIA pluss dent | H54: 1 | I54: 2 | J54: 45931 | K54: 211194 | L54: 248000 | O54: =(L54/K54)-1 -> 0.17427578 | P54: =K54*F54 -> 0
A55: Aclaramiento casero Opalecense Go x unidad | C55: Casero | E55: 0 | F55: 0 | G55: CLAUDIA pluss dent | H55: 0 | K55: 25000 | L55: 30000 | O55: =(L55/K55)-1 -> 0.2 | P55: =K55*F55 -> 0
A56: Aclaramiento casero Polanight | F56: 0 | G56: CLAUDIA abraham | K56: 26900 | L56: 33600 | O56: =(L56/K56)-1 -> 0.24907063 | P56: =K56*F56 -> 0
A57: Aclaramiento casero Potenza 16% | C57: Casero | G57: New Stetic | H57: 0 | J57: 46113 | K57: 13953 | L57: 22000 | O57: =(L57/K57)-1 -> 0.57672185 | P57: =K57*F57 -> 0
A58: Aclaramiento casero Potenza 22% | C58: Casero | G58: New Stetic | H58: 0 | K58: 15153 | L58: 22000 | O58: =(L58/#REF!)-1 -> #REF! | P58: =#REF!*K58 -> #REF!
A59: Aclaramiento casero Power bleaching bM4 16 % | E59: 0 | F59: 0 | G59: SOCCIDENTALES | I59: 0 | K59: =8070*1.19 -> 9603.3 | L59: 20000 | O59: =(L59/K59)-1 -> 1.0826174 | P59: =K59*F59 -> 0
A60: Aclaramiento casero Power bleaching bM4 22 % | E60: 0 | F60: 0 | G60: SOCCIDENTALES | I60: 0 | K60: =8070*1.19 -> 9603.3 | L60: 20000 | O60: =(L60/K60)-1 -> 1.0826174 | P60: =K60*F60 -> 0
A61: Aclaramiento casero Whiteness perfect FGM 16% | B61: antioq $16800 promo $15000 soccid $14500 plus $15232 | C61: Casero | E61: 0 | F61: 0 | G61: FGM soccident | I61: 0 | J61: 1/11/2025 3-2025 | K61: 16800 | L61: 25000 | N61: 22000 | O61: =(L61/K61)-1 -> 0.48809524 | P61: =K61*F61 -> 0
A62: Aclaramiento casero Whiteness perfect FGM 22% | B62: antioq $16800 promo $15000 soccid $14500 plus $15232 | C62: Casero | E62: 0 | F62: 0 | G62: FGM soccident | I62: 0 | J62: 45717 | K62: 16800 | L62: 25000 | O62: =(L62/K62)-1 -> 0.48809524 | P62: =K62*F62 -> 0
A63: Aclaramiento casero withegold | E63: 0 | G63: DORA ramon | K63: 11700 | L63: 18000 | O63: =(L63/K63)-1 -> 0.53846154 | P63: =K63*F63 -> 0
A64: Aclaramiento consultorio AZUL HP BLUE FGM 35% JERINGA | B64: SOCCID 38714 plus $37334 | C64: PRECIO MAYO 20 | D64: =(195200+37088)/6 -> 38714.667 | E64: 0 | F64: 0 | G64: FGM soccident | I64: 0 | J64: 46023 | K64: =245000*0.8*1.19/6 -> 38873.333 | L64: 65000 | N64: 48000 | O64: =(L64/K64)-1 -> 0.67209741 | P64: =K64*F64 -> 0
A65: Aclaramiento consultorio AZUL HP BLUE FGM 35% MINI KIT | B65: antioq $76160 soccid $66800 | C65: aclaramiento FGM | E65: 0 | F65: 0 | G65: FGM soccident | K65: =80000*0.8*1.19 -> 76160 | L65: 100000 | O65: =(L65/K65)-1 -> 0.31302521 | P65: =K65*F65 -> 0
A66: aclaramiento consultorio Clariant 35% Angelus | C66: PRECIO 20 MAYO | D66: 38000 | F66: 0 | G66: ABRAHAM | K66: 36130 | L66: 49000 | O66: =(L66/K66)-1 -> 0.35621367 | P66: =K66*F66 -> 0
A67: Aclaramiento consultorio FGM 35% ROJO HP | B67: antioq $200000 promo $196350 soccid $202.300 | C67: aclaramiento FGM | E67: 0 | F67: 0 | G67: FGM soccident | J67: FGM 1/11/2025 brasil 04-2025 | K67: =250000*0.8 -> 200000 | L67: 270000 | O67: =(L67/K67)-1 -> 0.35 | P67: =K67*F67 -> 0
A68: Aclaramiento consultorio FGM 35% ROJO HP Mini kit | C68: aclaramiento FGM | E68: 0 | F68: 0 | G68: FGM soccident | K68: 89000 | L68: 119000 | O68: =(L68/K68)-1 -> 0.33707865 | P68: =K68*F68 -> 0
A69: Aclaramiento consultorio FGM 35% VERDE HP AUTOMIX JERINGA CONSULTORIO | C69: aclaramiento FGM | E69: 0 | F69: 0 | G69: FGM soccident | K69: 190000 | L69: 220000 | O69: =(L69/K69)-1 -> 0.15789474 | P69: =K69*F69 -> 0
A70: Aclaramiento consultorio FGM 35% VERDE HP MAXX | B70: antioq $233240 soccid $180000 plus $208012 | C70: aclaramiento FGM | E70: 0 | F70: 0 | G70: FGM soccident | K70: 200000 | L70: 270000 | O70: =(L70/K70)-1 -> 0.35 | P70: =K70*F70 -> 0
A71: Aclaramiento consultorio FGM 35% VERDE MINI KIT HP MAXX | B71: antioq $117096 soccid $66800 | C71: aclaramiento FGM | D71: FGM | E71: 0 | F71: 0 | G71: FGM soccident | K71: =123000*0.8*1.19 -> 117096 | L71: 165000 | O71: =(L71/K71)-1 -> 0.40910023 | P71: =K71*F71 -> 0
A72: Aclaramiento consultorio OPALECENSE BOOTS + barrera gingival OPALDAM | E72: 0 | F72: 0 | G72: CLAUDIA pluss dent | H72: 4 | I72: 0 | K72: 115250 | L72: 148000 | M72: iva | O72: =(L72/K72)-1 -> 0.28416486 | P72: =K72*F72 -> 0
A73: Aclaramiento consultorio OPALECENSE BOOTS 40% | B73: compre $90200 | E73: 1 | F73: 0 | G73: CLAUDIA pluss dent | H73: 1 | I73: 2 | J73: 45901 | K73: 97429 | L73: 125000 | M73: iva | O73: =(L73/K73)-1 -> 0.28298556 | P73: =K73*F73 -> 0
A74: Aclaramiento consultorio Pola Office + LISTO 1PCTE | F74: 0 | G74: abraham | K74: 141000 | L74: 175000 | O74: =(L74/K74)-1 -> 0.24113475 | P74: =K74*F74 -> 0
A75: Aclaramiento consultorio Pola Office 3 PCTE S POLVO Y LIQUIDO | F75: 0 | G75: abraham | K75: 292000 | L75: 365000 | O75: =(L75/K75)-1 -> 0.25 | P75: =K75*F75 -> 0
A76: Aclaramiento consultorio pola office bulk kit | F76: 0 | G76: abraham | J76: 45748 | K76: 287900 | L76: 359800 | O76: =(L76/K76)-1 -> 0.24973949 | P76: =K76*F76 -> 0
A77: Aclaramiento consultorio Potenza 38% (1,3+0,4) | G77: New stetic | H77: 0 | I77: 0 | J77: 45870 | K77: 42000 | L77: 65000 | O77: =(L77/K77)-1 -> 0.54761905 | P77: =K77*F77 -> 0
A78: Aclaramiento consultorio Potenza 38% 1 jeringa+ Barrera 1g+ 1 frasco Neutralizador | G78: New stetic | H78: 0 | I78: 0 | J78: 45869 | K78: 65450 | L78: 88000 | O78: =(L78/K78)-1 -> 0.34453782 | P78: =K78*F78 -> 0
A79: aclaramiento HP BLUE 6 JERINGAS | E79: 0 | F79: 0 | L79: 312000
A80: ACONDICIONADOR DE TEJIDOS COE CONFORT LIQUIDO | B80: GC | C80: promo $77.700 | E80: 0 | F80: 0 | G80: LA MUELA - DORA - RAMON - masdental | K80: 80808 | L80: 120000 | M80: exc | N80: 110000 | O80: =(L80/K80)-1 -> 0.48500149 | P80: =K80*F80 -> 0
A81: ACONDICIONADOR DE TEJIDOS COE CONFORT POLVO | B81: GC | E81: 0 | F81: 0 | G81: LA MUELA - DORA - RAMON - masdental | K81: 97275 | L81: 130000 | M81: exc | N81: 120000 | O81: =(L81/K81)-1 -> 0.33641737 | P81: =K81*F81 -> 0
A82: ACONDICIONADOR DE TEJIDOS COE CONFORT Y COE SOFT X PORCION | B82: GC | E82: 0 | F82: 0 | G82: La Muela | K82: =130000/15 -> 8666.6667 | L82: 20000 | O82: =(L82/K82)-1 -> 1.3076923 | P82: =K82*F81 -> 0
A83: ACONDICIONADOR DE TEJIDOS COE SOFT LIQUIDO | B83: GC | E83: 0 | F83: 0 | G83: LA MUELA - DORA - RAMON - masdental | K83: 80808 | L83: 120000 | M83: exc | O83: =(L83/K83)-1 -> 0.48500149 | P83: =K83*F83 -> 0
A84: ACONDICIONADOR DE TEJIDOS COE SOFT POLVO | B84: GC | E84: 0 | F84: 0 | G84: LA MUELA - DORA - RAMON - masdental | K84: 87241 | L84: 120000 | M84: exc | O84: =(L84/K84)-1 -> 0.37550005 | P84: =K84*F84 -> 0
A85: ACOPLE CORDEN PARA PIEZAS UNIDAD | E85: 0 | F85: 0 | G85: larry alfredo | K85: 25000 | L85: 35000 | O85: =(L85/K85)-1 -> 0.4 | P85: =K85*F85 -> 0
A86: Acrilico auto 125 g JB | G86: New Stetic | H86: 0 | I86: 15 | K86: 18683 | L86: 24000 | M86: 1.19 | N86: 22000 | O86: =(L86/K86)-1 -> 0.28459027 | P86: =K86*F86 -> 0
A87: Acrilico auto 125 g TRANSPARENTE | G87: New Stetic | H87: 0 | I87: 19 | K87: 18683 | L87: 24000 | M87: 1.19 | N87: 22000 | O87: =(L87/K87)-1 -> 0.28459027 | P87: =K87*F87 -> 0
A88: Acrilico auto 125 g VR1 | G88: New Stetic | H88: 0 | I88: 15 | K88: 18683 | L88: 24000 | M88: 1.19 | N88: 22000 | O88: =(L88/K88)-1 -> 0.28459027 | P88: =K88*F88 -> 0
A89: Acrilico auto 60 g A 3.5 | G89: New Stetic | H89: 0 | I89: 3 | K89: 18683 | L89: 24000 | M89: 1.19 | N89: 21000 | O89: =(L89/K89)-1 -> 0.28459027 | P89: =K89*F89 -> 0
A90: Acrilico auto 60 g A0 | G90: New Stetic | H90: 0 | I90: 1 | K90: 18683 | L90: 24000 | M90: 1.19 | N90: 21000 | O90: =(L90/K90)-1 -> 0.28459027 | P90: =K90*F90 -> 0
A91: Acrilico Auto 60 g A1 | G91: New Stetic | H91: 0 | I91: 12 | K91: 18683 | L91: 24000 | M91: 1.19 | N91: 21000 | O91: =(L91/K91)-1 -> 0.28459027 | P91: =K91*F91 -> 0
A92: Acrilico auto 60 g A2 | G92: New Stetic | H92: 0 | I92: 7 | K92: 18683 | L92: 24000 | M92: 1.19 | N92: 21000 | O92: =(L92/K92)-1 -> 0.28459027 | P92: =K92*F92 -> 0
A93: Acrilico auto 60 g A3 | G93: New Stetic | H93: 0 | I93: 5 | K93: 18683 | L93: 24000 | M93: 1.19 | N93: 21000 | O93: =(L93/K93)-1 -> 0.28459027 | P93: =K93*F93 -> 0
A94: Acrilico Auto 60 g B2 | G94: New Stetic | H94: 0 | I94: 4 | K94: 18683 | L94: 24000 | M94: 1.19 | N94: 21000 | O94: =(L94/K94)-1 -> 0.28459027 | P94: =K94*F94 -> 0
A95: Acrilico auto 60 g JB | G95: New Stetic | H95: 0 | I95: 10 | K95: 9639 | L95: 14000 | M95: 1.19 | N95: 12000 | O95: =(L95/K95)-1 -> 0.45243282 | P95: =K95*F95 -> 0
A96: Acrilico auto 60 g Transparente | G96: New Stetic | H96: 0 | I96: 14 | K96: 9639 | L96: 14000 | M96: 1.19 | N96: 12000 | O96: =(L96/K96)-1 -> 0.45243282 | P96: =K96*F96 -> 0
A97: Acrilico auto 60 g VR1 | G97: New Stetic | H97: 0 | I97: 7 | K97: 9639 | L97: 14000 | M97: 1.19 | N97: 12000 | O97: =(L97/K97)-1 -> 0.45243282 | P97: =K97*F97 -> 0
A98: Acrilico auto 60 g VRX | G98: New Stetic | H98: 0 | I98: 10 | K98: 9639 | L98: 14000 | M98: 1.19 | N98: 12000 | O98: =(L98/K98)-1 -> 0.45243282 | P98: =K98*F98 -> 0
A99: Acrilico auto JB 500 gm | G99: New Stetic | H99: 0 | I99: 2 | J99: 1/10/2025 09-2026 | K99: 55167 | L99: 70000 | N99: 64000 | O99: =(L99/K99)-1 -> 0.26887451 | P99: =K99*F99 -> 0
A100: Acrilico auto liquido 1000 cc | G100: New Stetic | H100: 0 | I100: 1 | J100: 46508 | K100: =54400*1.19 -> 64736 | L100: 78000 | N100: 72000 | O100: =(L100/K100)-1 -> 0.20489372 | P100: =K100*F100 -> 0
...

Sheet Hoja 692
B2: DYMA | D2: FECHA:
C5: INVENTARIO | D5: PEDIDO
B6: Cubetas Plasticas de Colores surtidas paquete x 3 p
B7: Dientes de Endodoncia D ENDO 11 23 25 36
B8: dientes de ivorina
B9: dientes de NISSI
B10: Espatula Plastica de Alginato Zendent
B11: Espatula plastica para alginato (NO NARANJA NI VERDE)
B12: formaletas plasticas L
B13: formaletas plasticas M
B14: formaletas plasticas S
B15: FOSFATO DE ZINC oxifosfato LEE SMITH
B16: macro modelo plastico
B17: medidor de alginato
... B43: VERABOND II LABORATORIO

Sheet COPIA SUR JUN 25
B1: referencias | E1: PEDIDO SUR | F1: PEDIDO NORTE | H1: INVENT SUR mar 21 | I1: INVENT NTE | J1: FECHA VCMTO | K1: PRECIO COMPRA | L1: precio venta | M1: IVA | N1: PRECIO MALTERO | O1: % | P1: VR PEDIDO
A2: abre bocas Umbrella | E2: 0 | F2: 0 | G2: Pluss Dent GAB VEL | H2: 0 | I2: 0 | K2: =9288*1.19 -> 11052.72 | L2: 15000 | O2: =(L2/K2)-1 -> 0.357132 | P2: =K2*F2 -> 0
A3: Abreboca manual gancho DOBLE EXTREMO NEGRO | E3: 0 | F3: 0 | G3: IMPORTADA | I3: 8 | K3: 8746 | L3: 30000 | M3: 19 | O3: =(L3/K3)-1 -> 2.4301395 | P3: =K3*F3 -> 0
A4: Abreboca manual gancho DOBLE EXTREMO TRANSPARENTE | E4: 0 | F4: 0 | G4: IMPORTADA | I4: 50 | K4: =1962*2 -> 3924 | L4: 30000 | O4: =(L4/K4)-1 -> 6.6452599 | P4: =K4*F4 -> 0
A5: Abreboca manual gancho PEQUEÑO | E5: 0 | F5: 0 | G5: IMPORTADA | I5: 100 | K5: 1712 | L5: 10000 | O5: =(L5/K5)-1 -> 4.8411215 | P5: =K5*F5 -> 0
A6: Abreboca AZUL Y ROJO AMARILLO | E6: 0 | F6: 0 | G6: ELVER LOZANO BOGOTA | I6: rojo 1 azul 1 | K6: 4500 | L6: 12000 | O6: =(L6/K6)-1 -> 1.6666667 | P6: =K6*F6 -> 0
A7: abreboca Con retractor adulto | E7: 0 | F7: 0 | G7: UPEGUI | I7: BLANCO 43 NEGRO 10 | K7: 16900 | L7: 24000 | O7: =(L7/K7)-1 -> 0.42011834 | P7: =K7*F7 -> 0
A8: abreboca Con retractor PEDIATRICO | E8: 0 | F8: 0 | G8: UPEGUI | I8: 20 | K8: 16900 | L8: 24000 | O8: =(L8/K8)-1 -> 0.42011834 | P8: =K8*F8 -> 0
A9: Abreboca manual gancho GRANDE | E9: 0 | F9: 0 | G9: IMPORTADA | I9: 50 | K9: 1426.9789 | L9: 10000 | O9: =(L9/K9)-1 -> 6.0078119 | P9: =K9*F9 -> 0
A10: Abreboca sencillo adulto | B10: OXXI $ 11067 NISSI $7556 | E10: 0 | F10: 0 | G10: OXXI NISSI | I10: =8+16*5 -> 88 | K10: =9300*1.19/5 -> 2213.4 | L10: 8000 | O10: =(L10/K10)-1 -> 2.614349 | P10: =K10*F10 -> 0
A11: Abreboca sencillo niño | B11: OXXI $ 11067 NISSI $7557 | E11: 0 | F11: 0 | G11: OXXI NISSI | I11: 26 | K11: =9300*1.19/5 -> 2213.4 | L11: 8000 | O11: =(L11/K11)-1 -> 2.614349 | P11: =K11*F11 -> 0
A12: abreboca sin retractor | E12: 0 | F12: 0 | G12: UPEGUI | I12: 10 | K12: 16900 | L12: 24000 | O12: =(L12/K12)-1 -> 0.42011834 | P12: =K12*F12 -> 0
A13: abrebocas aclaramiento tipo optragate | E13: 0 | F13: 0 | G13: IMPORTADA | I13: 58 | K13: 4602 | L13: 12000 | O13: =(L13/K13)-1 -> 1.6075619 | P13: =K13*F13 -> 0
A14: Accufilm Papel de articular aqua film x 280 tiras | E14: 0 | F14: 0 | G14: La muela miguel | I14: 1 | K14: =65000/200 -> 325 | L14: 800 | O14: =(L14/K14)-1 -> 1.4615385 | P14: =K14*F14 -> 0
A15: Accufilm Papel de articular CIRENE aqua film x 280 tiras | E15: 0 | F15: 0 | G15: La muela miguel | K15: 65000 | L15: 105000 | N15: 90000 | O15: =(L15/K15)-1 -> 0.61538462 | P15: =K15*F15 -> 0
A16: Aceite 3 en 1 | E16: 0 | G16: CENTRO HOYOSTOOL | K16: =3200*1.19 -> 3808 | L16: 6000 | O16: =(L16/K16)-1 -> 0.57563025 | P16: =K16*F16 -> 0
A17: aceite lubricante - pieza de mano Dental handpiece 300ml | E17: 0 | F17: 0 | G17: DTM | K17: 28000 | L17: 48000 | N17: 38000 | O17: =(L17/K17)-1 -> 0.71428571
A18: aceite lubricante - pieza de mano Dental handpiece 550ml | E18: 0 | F18: 0 | G18: DTM | K18: 35000 | L18: 54000 | N18: 44000 | O18: =(L18/K18)-1 -> 0.54285714
A19: aceite lubricante - pieza de mano PANASPRAY PLUS NSK 480ML | B19: NSK | E19: 0 | F19: 0 | G19: LA MUELA | I19: 10 | J19: 45717 | K19: =121849*1.19 -> 145000.31 | L19: 178000 | N19: 168000 | O19: =(L19/K19)-1 -> 0.22758358 | P19: =K19*F19 -> 0
A20: aceite lubricante - pieza de mano WYH 400ML | B20: euro $96250 | G20: MASDENTAL EURODENT | I20: 0 | K20: 116000 | L20: 145000 | N20: 120000 | O20: =(L20/K20)-1 -> 0.25 | P20: =K20*F20 -> 0
A21: Aceite lubricante Bendechk 300ml | E21: 0 | F21: 0 | G21: makrodent DTM | K21: 35000 | L21: 48000 | O21: =(L21/K21)-1 -> 0.37142857 | P21: =K21*F21 -> 0
A22: aceite lubricante de piezas digixpray 240ml | E22: 0 | F22: 0 | G22: muela | K22: 24850 | L22: 48000 | M22: iva | N22: 34000
A23: Aceite lubricante en Spray 200 ml- KAVO | C23: AGOTADO | E23: 0 | F23: 0 | G23: Pluss Dent GAB VEL | H23: 0 | I23: 0 | K23: 49504 | L23: 65000 | O23: =(L23/K23)-1 -> 0.31302521 | P23: =K23*F23 -> 0
A24: aceite lubricante pequeño - pieza de mano 50 ml | E24: 0 | G24: RAMON | K24: 7400 | L24: 12000 | O24: =(L24/K24)-1 -> 0.62162162 | P24: =K24*F24 -> 0
A25: Aceite lubricante Quiruspray 200 cc - pieza de mano | B25: ramon $29.500 aquiles $24.871 | E25: 0 | G25: RAMON AQUILES | K25: =24789.92*1.19 -> 29500.005 | L25: 39000 | O25: =(L25/K25)-1 -> 0.32203368 | P25: =K25*F25 -> 0
A26: Aceite lubricante Universal en Spray 250 ml- Adensys | E26: 0 | F26: 0 | G26: Pluss Dent GAB VEL | H26: 0 | I26: 10 | J26: 46174 | K26: =50500*1.19 -> 60095 | L26: 76000 | N26: 65000 | O26: =(L26/K26)-1 -> 0.26466428 | P26: =K26*F27 -> 0
A27: Aceite LUBRICANTE X200 ML Maquira | E27: 0 | F27: 0 | G27: SOCCIDENTALES | I27: 0 | J27: 46174 | K27: =26000*1.19 -> 30940 | L27: 55000 | O27: =(L27/K27)-1 -> 0.77763413 | P27: =K27*#REF! -> #REF!
A28: Aceite super lubry 50ml | E28: 0 | F28: 0 | G28: AQUILES | I28: 0 | J28: 46174 | K28: 7500 | L28: 12000 | O28: =(L28/K28)-1 -> 0.6 | P28: =K28*F28 -> 0
A29: acetato lamina rosada 0.6 | E29: 0 | G29: RAMON | K29: 1800 | L29: 3500 | O29: =(L29/K29)-1 -> 0.94444444 | P29: =K29*F29 -> 0
A30: acetato rigido ACE | E30: 0 | G30: RAMON | K30: 6400 | L30: 9000 | O30: =(L30/K30)-1 -> 0.40625 | P30: =K30*F30 -> 0
A31: acido clorhidrico removedor de manchas opalustre FGM whiteness RM 6% | B31: antioq $95200 soccid $ 80,206 plus $79968 | E31: 0 | F31: 0 | G31: FGM soccident | I31: 0 | J31: 46082 | K31: =100000*0.8*1.19 -> 95200 | L31: 145000 | O31: =(L31/K31)-1 -> 0.52310924 | P31: =K31*F31 -> 0
A32: Acido desmineralizante 2.5 coltene | B32: ACIDO | E32: 0 | F32: 0 | G32: Ultradental | I32: 0 | K32: 10868 | L32: 18000 | O32: =(L32/K32)-1 -> 0.6562385 | P32: =K32*F32 -> 0
A33: acido desmineralizante 2.5 Densell 12g 35% | B33: ACIDO | E33: 0 | F33: 0 | G33: La muela - ramon | J33: 46478 | K33: 12000 | L33: 20000 | M33: exc | N33: 18000 | O33: =(L33/K33)-1 -> 0.66666667 | P33: =K33*F33 -> 0
A34: Acido desmineralizante 35% ultradent 1.2ml | B34: ACIDO | E34: 2 | F34: 0 | G34: Gabriel Vel pluss | H34: 2 | I34: 3 | K34: 13272 | L34: 22000 | O34: =(L34/K34)-1 -> 0.65762508 | P34: =K34*F34 -> 0
A35: acido desmineralizante 37% fosforico MAQUIRA 2.5 | B35: ACIDO | C35: PRECIO MAYO 20 | D35: =(6500*1.19)/3 -> 2578.3333 | E35: 0 | F35: 0 | G35: RAMON CLAUDIA SOCCIDENTALES | J35: 45962 | K35: =(11654*1.19)/3 -> 4622.7533 | L35: 13000 | M35: EXC | O35: =(L35/K35)-1 -> 1.8121769 | P35: =K35*F35 -> 0
A36: acido desmineralizante angelus 3 grs | B36: ACIDO | E36: 0 | F36: 0 | G36: CLAUDIA | I36: 0 | K36: 2000 | L36: 10000 | O36: =(L36/K36)-1 -> 4 | P36: =K36*F36 -> 0
A37: Acido desmineralizante FGM condac 12.5 ML | B37: ACIDO promo antoq $24375 SOCCIDEN 20825 plus20000 | E37: 0 | F37: 0 | G37: FGM soccident | I37: 0 | J37: 45992 | K37: =32500*0.8 -> 26000 | L37: 35000 | M37: exc | O37: =(L37/K37)-1 -> 0.34615385 | P37: =K37*F37 -> 0
A38: Acido Desmineralizante proquident 10ML jumbo | B38: ACIDO | G38: PROQUIDENT | I38: 2 | J38: 46844 | K38: 14173 | L38: 24000 | O38: =(L38/K38)-1 -> 0.69336062 | P38: =K38*#REF! -> #REF!
A39: Acido Desmineralizante Select H V ETCH 5ML Bisco | B39: promo $48.450 mayo/25 | G39: JULVIDENT bisco | I39: 11 | J39: 46447 | K39: 54000 | L39: 68000 | M39: EXC | O39: =(L39/K39)-1 -> 0.25925926 | P39: =K39*F39 -> 0
A40: Acido desmineralizante SUPER ETCH SDI 12 gm | B40: ACIDO | E40: 0 | F40: 0 | G40: ABRAHAM | I40: 6 | J40: 46296 | K40: 33800 | L40: 42500 | M40: exc | O40: =(L40/K40)-1 -> 0.25739645 | P40: =K40*F40 -> 0
A41: Acido desmineralizante ultra ETCH 30ml ultradent | B41: ACIDO | E41: 0 | F41: 0 | G41: Gabriel Vel pluss | H41: 1 | I41: 3 | K41: 150579 | L41: 210000 | N41: tempo $150,000 | O41: =(L41/K41)-1 -> 0.39461678 | P41: =K41*F41 -> 0
A42: Acido Desmineralizante Zafira 10 ml | B42: ACIDO | C42: kit zafira | G42: New Stetic | H42: 10 | J42: revisar | K42: 12400 | L42: 18000 | M42: exc | N42: 15000 | O42: =(L42/K42)-1 -> 0.4516129 | P42: =K42*F42 -> 0
A43: acido fluorhidrico 10% Jeringa 2.5 ml Angelus | E43: 0 | F43: 0 | G43: CLAUDIA | I43: 0 | K43: 37140 | L43: 46400 | O43: =(L43/K43)-1 -> 0.24932687 | P43: =K43*F43 -> 0
A44: acido fluorhidrico 10% Jeringa 2.5 ml Maquira | E44: 0 | F44: 0 | G44: SOCCIDENTALES CLAUDIA | I44: 8 | K44: =21315*1.19 -> 25364.85 | L44: 38000 | M44: EXC | N44: 32000 | O44: =(L44/K44)-1 -> 0.4981362 | P44: =K44*F44 -> 0
A45: ACIDO FLUORHIDRICO 3ML (JERINGA) prodont | E45: 0 | F45: 0 | G45: PRODONT | I45: 5 | J45: 46478 | K45: =23294*1.19 -> 27719.86 | L45: 40000 | N45: 35000 | O45: =(L45/K45)-1 -> 0.44300873 | P45: =K45*F45 -> 0
A46: acido fluorhidrico 5% 3 g BM4 | E46: 0 | F46: 0 | G46: CLAUDIA | I46: 0 | K46: 10320 | L46: 30000 | O46: =(L46/K46)-1 -> 1.9069767 | P46: =K46*F46 -> 0
A47: acido fluorhidrico 5% porcelana jeringa 2.5 ml FGM | B47: SOCCID $24514 plus $25600 | E47: 0 | F47: 0 | G47: FGM soccident | I47: 0 | J47: 46023 | K47: =40000*0.8*1.19 -> 38080 | L47: 56000 | O47: =(L47/K47)-1 -> 0.47058824 | P47: =K47*F47 -> 0
A48: ACIDO FLUORHIDRICO 7ML (GOTERO) prodont | E48: 0 | F48: 10 | G48: PRODONT | I48: 4 | J48: 46569 | K48: =25757*1.19 -> 30650.83 | L48: 45000 | N48: 38000 | O48: =(L48/K48)-1 -> 0.46814948 | P48: =K48*F48 -> 306508.3
A49: acido fluorhidrico 9.6% Jeringa 2 g Eufar | B49: Aquiles $32000 ramon $32000 EUFAR $29354 | E49: 0 | F49: 0 | G49: AQUILES RAMON GABRIEL VELASQUEZ Eufar | K49: =24667*1.19 -> 29353.73 | L49: 45000 | N49: 35000 | O49: =(L49/K49)-1 -> 0.53302493 | P49: =K49*F49 -> 0
A50: Acido fluorhidrico grabador para porcelana ultradent | B50: pluss $24804 | E50: 0 | F50: 0 | G50: Gabriel Vel pluss | H50: 3 | I50: 6 | K50: 30257 | L50: 52000 | M50: EXC | N50: 38000 | O50: =(L50/K50)-1 -> 0.71861057 | P50: =K50*F50 -> 0
A51: Acido Fluorhidrico porcelain etch 9,5% Bisco | B51: promo $106.250 mayo/25 | G51: JULVIDENT bisco | I51: 3 | K51: 118000 | L51: 170000 | M51: EXC | O51: =(L51/K51)-1 -> 0.44067797 | P51: =K51*F51 -> 0
A52: aclaramiento casero Clariant 16% Angelus | E52: 0 | F52: 0 | G52: ABRAHAM | I52: 3 | K52: 19710 | L52: 24630 | O52: =(L52/K52)-1 -> 0.24961948 | P52: =K52*F52 -> 0
A53: Aclaramiento casero OPALECENSE x 2 JERINGAS | C53: Casero | E53: 0 | F53: 0 | G53: CLAUDIA pluss dent | H53: 3 | I53: 4 | J53: revisar | K53: 45031 | L53: 58000 | M53: iva | O53: =(L53/K53)-1 -> 0.2880016 | P53: =K53*F53 -> 0
A54: Aclaramiento casero Opalecense Go caja x 10 | B54: pluss $211.000 promo 2x 159 gabriel velasq promo x 2 155 | C54: Casero | E54: 1 | F54: 0 | G54: CLAUDIA pluss dent | H54: 1 | I54: 2 | J54: 45931 | K54: 211194 | L54: 248000 | O54: =(L54/K54)-1 -> 0.17427578 | P54: =K54*F54 -> 0
A55: Aclaramiento casero Opalecense Go x unidad | C55: Casero | E55: 0 | F55: 0 | G55: CLAUDIA pluss dent | H55: 0 | K55: 25000 | L55: 30000 | O55: =(L55/K55)-1 -> 0.2 | P55: =K55*F55 -> 0
A56: Aclaramiento casero Polanight | E56: 0 | F56: 0 | G56: CLAUDIA abraham | I56: 0 | K56: 26900 | L56: 33600 | O56: =(L56/K56)-1 -> 0.24907063 | P56: =K56*F56 -> 0
A57: Aclaramiento casero Potenza 16% | C57: Casero | G57: New Stetic | H57: 0 | J57: 46113 | K57: 13953 | L57: 22000 | O57: =(L57/K57)-1 -> 0.57672185 | P57: =K57*F57 -> 0
A58: Aclaramiento casero Potenza 22% | C58: Casero | G58: New Stetic | H58: 0 | K58: 15153 | L58: 22000 | O58: =(L58/#REF!)-1 -> #REF! | P58: =#REF!*K58 -> #REF!
A59: Aclaramiento casero Power bleaching bM4 16 % | E59: 0 | F59: 0 | G59: SOCCIDENTALES | I59: 0 | K59: =8070*1.19 -> 9603.3 | L59: 20000 | O59: =(L59/K59)-1 -> 1.0826174 | P59: =K59*F59 -> 0
A60: Aclaramiento casero Power bleaching bM4 22 % | E60: 0 | F60: 0 | G60: SOCCIDENTALES | I60: 0 | K60: =8070*1.19 -> 9603.3 | L60: 20000 | O60: =(L60/K60)-1 -> 1.0826174 | P60: =K60*F60 -> 0
A61: Aclaramiento casero Whiteness perfect FGM 16% | B61: antioq $16800 promo $15000 soccid $14500 plus $15232 | C61: Casero | E61: 0 | F61: 0 | G61: FGM soccident | I61: 0 | J61: 1/11/2025 3-2025 | K61: 16800 | L61: 25000 | N61: 22000 | O61: =(L61/K61)-1 -> 0.48809524 | P61: =K61*F61 -> 0
A62: Aclaramiento casero Whiteness perfect FGM 22% | B62: antioq $16800 promo $15000 soccid $14500 plus $15232 | C62: Casero | E62: 0 | F62: 0 | G62: FGM soccident | I62: 0 | J62: 45717 | K62: 16800 | L62: 25000 | O62: =(L62/K62)-1 -> 0.48809524 | P62: =K62*F62 -> 0
A63: Aclaramiento casero withegold | E63: 0 | G63: DORA ramon | K63: 11700 | L63: 18000 | O63: =(L63/K63)-1 -> 0.53846154 | P63: =K63*F63 -> 0
A64: Aclaramiento consultorio AZUL HP BLUE FGM 35% JERINGA | B64: SOCCID 38714 plus $37334 | C64: PRECIO MAYO 20 | D64: =(195200+37088)/6 -> 38714.667 | E64: 0 | F64: 0 | G64: FGM soccident | I64: 0 | J64: 46023 | K64: =245000*0.8*1.19/6 -> 38873.333 | L64: 65000 | N64: 48000 | O64: =(L64/K64)-1 -> 0.67209741 | P64: =K64*F64 -> 0
A65: Aclaramiento consultorio AZUL HP BLUE FGM 35% MINI KIT | B65: antioq $76160 soccid $66800 | C65: aclaramiento FGM | E65: 0 | F65: 0 | G65: FGM soccident | K65: =80000*0.8*1.19 -> 76160 | L65: 100000 | O65: =(L65/K65)-1 -> 0.31302521 | P65: =K65*F65 -> 0
A66: aclaramiento consultorio Clariant 35% Angelus | C66: PRECIO 20 MAYO | D66: 38000 | E66: 0 | F66: 0 | G66: ABRAHAM | I66: 0 | K66: 36130 | L66: 49000 | O66: =(L66/K66)-1 -> 0.35621367 | P66: =K66*F66 -> 0
A67: Aclaramiento consultorio FGM 35% ROJO HP | B67: antioq $200000 promo $196350 soccid $202.300 | C67: aclaramiento FGM | E67: 0 | F67: 0 | G67: FGM soccident | J67: FGM 1/11/2025 brasil 04-2025 | K67: =250000*0.8 -> 200000 | L67: 270000 | O67: =(L67/K67)-1 -> 0.35 | P67: =K67*F67 -> 0
A68: Aclaramiento consultorio FGM 35% ROJO HP Mini kit | C68: aclaramiento FGM | E68: 0 | F68: 0 | G68: FGM soccident | K68: 89000 | L68: 119000 | O68: =(L68/K68)-1 -> 0.33707865 | P68: =K68*F68 -> 0
A69: Aclaramiento consultorio FGM 35% VERDE HP AUTOMIX JERINGA CONSULTORIO | C69: aclaramiento FGM | E69: 0 | F69: 0 | G69: FGM soccident | K69: 190000 | L69: 220000 | O69: =(L69/K69)-1 -> 0.15789474 | P69: =K69*F69 -> 0
A70: Aclaramiento consultorio FGM 35% VERDE HP MAXX | B70: antioq $233240 soccid $180000 plus $208012 | C70: aclaramiento FGM | E70: 0 | F70: 0 | G70: FGM soccident | K70: 200000 | L70: 270000 | O70: =(L70/K70)-1 -> 0.35 | P70: =K70*F70 -> 0
A71: Aclaramiento consultorio FGM 35% VERDE MINI KIT HP MAXX | B71: antioq $117096 soccid $66800 | C71: aclaramiento FGM | D71: FGM | E71: 0 | F71: 0 | G71: FGM soccident | K71: =123000*0.8*1.19 -> 117096 | L71: 165000 | O71: =(L71/K71)-1 -> 0.40910023 | P71: =K71*F71 -> 0
A72: Aclaramiento consultorio OPALECENSE BOOTS + barrera gingival OPALDAM | E72: 0 | F72: 0 | G72: CLAUDIA pluss dent | H72: 4 | I72: 0 | K72: 115250 | L72: 148000 | M72: iva | O72: =(L72/K72)-1 -> 0.28416486 | P72: =K72*F72 -> 0
A73: Aclaramiento consultorio OPALECENSE BOOTS 40% | B73: compre $90200 | E73: 1 | F73: 0 | G73: CLAUDIA pluss dent | H73: 1 | I73: 2 | J73: 45901 | K73: 97429 | L73: 125000 | M73: iva | O73: =(L73/K73)-1 -> 0.28298556 | P73: =K73*F73 -> 0
A74: Aclaramiento consultorio Pola Office + LISTO 1PCTE | E74: 0 | F74: 0 | G74: abraham | I74: 0 | K74: 141000 | L74: 175000 | O74: =(L74/K74)-1 -> 0.24113475 | P74: =K74*F74 -> 0
A75: Aclaramiento consultorio Pola Office 3 PCTE S POLVO Y LIQUIDO | E75: 0 | F75: 0 | G75: abraham | I75: 0 | K75: 292000 | L75: 365000 | O75: =(L75/K75)-1 -> 0.25 | P75: =K75*F75 -> 0
A76: Aclaramiento consultorio pola office bulk kit | E76: 2 | F76: 0 | G76: abraham | I76: 0 | J76: 45748 | K76: 287900 | L76: 359800 | O76: =(L76/K76)-1 -> 0.24973949 | P76: =K76*F76 -> 0
A77: Aclaramiento consultorio Potenza 38% (1,3+0,4) | G77: New stetic | H77: 0 | I77: 0 | J77: 45870 | K77: 42000 | L77: 65000 | O77: =(L77/K77)-1 -> 0.54761905 | P77: =K77*F77 -> 0
A78: Aclaramiento consultorio Potenza 38% 1 jeringa+ Barrera 1g+ 1 frasco Neutralizador | G78: New stetic | H78: 0 | I78: 0 | J78: 45869 | K78: 65450 | L78: 88000 | O78: =(L78/K78)-1 -> 0.34453782 | P78: =K78*F78 -> 0
A79: aclaramiento HP BLUE 6 JERINGAS | E79: 0 | F79: 0 | L79: 312000
A80: ACONDICIONADOR DE TEJIDOS COE CONFORT LIQUIDO | B80: GC | C80: promo $77.700 | E80: 0 | F80: 0 | G80: LA MUELA - DORA - RAMON - masdental | K80: 80808 | L80: 120000 | M80: exc | N80: 110000 | O80: =(L80/K80)-1 -> 0.48500149 | P80: =K80*F80 -> 0
A81: ACONDICIONADOR DE TEJIDOS COE CONFORT POLVO | B81: GC | E81: 0 | F81: 0 | G81: LA MUELA - DORA - RAMON - masdental | K81: 97275 | L81: 130000 | M81: exc | N81: 120000 | O81: =(L81/K81)-1 -> 0.33641737 | P81: =K81*F81 -> 0
A82: ACONDICIONADOR DE TEJIDOS COE CONFORT Y COE SOFT X PORCION | B82: GC | E82: 0 | F82: 0 | G82: La Muela | K82: =130000/15 -> 8666.6667 | L82: 20000 | O82: =(L82/K82)-1 -> 1.3076923 | P82: =K82*F81 -> 0
A83: ACONDICIONADOR DE TEJIDOS COE SOFT LIQUIDO | B83: GC | E83: 0 | F83: 0 | G83: LA MUELA - DORA - RAMON - masdental | K83: 80808 | L83: 120000 | M83: exc | O83: =(L83/K83)-1 -> 0.48500149 | P83: =K83*F83 -> 0
A84: ACONDICIONADOR DE TEJIDOS COE SOFT POLVO | B84: GC | E84: 0 | F84: 0 | G84: LA MUELA - DORA - RAMON - masdental | K84: 87241 | L84: 120000 | M84: exc | O84: =(L84/K84)-1 -> 0.37550005 | P84: =K84*F84 -> 0
A85: ACOPLE CORDEN PARA PIEZAS UNIDAD | E85: 0 | F85: 0 | G85: larry alfredo | K85: 25000 | L85: 35000 | O85: =(L85/K85)-1 -> 0.4 | P85: =K85*F85 -> 0
A86: Acrilico auto 125 g JB | G86: New Stetic | H86: 0 | I86: 15 | K86: 18683 | L86: 24000 | M86: 1.19 | N86: 22000 | O86: =(L86/K86)-1 -> 0.28459027 | P86: =K86*F86 -> 0
A87: Acrilico auto 125 g TRANSPARENTE | G87: New Stetic | H87: 0 | I87: 19 | K87: 18683 | L87: 24000 | M87: 1.19 | N87: 22000 | O87: =(L87/K87)-1 -> 0.28459027 | P87: =K87*F87 -> 0
A88: Acrilico auto 125 g VR1 | G88: New Stetic | H88: 0 | I88: 15 | K88: 18683 | L88: 24000 | M88: 1.19 | N88: 22000 | O88: =(L88/K88)-1 -> 0.28459027 | P88: =K88*F88 -> 0
A89: Acrilico auto 60 g A 3.5 | G89: New Stetic | H89: 0 | I89: 3 | K89: 18683 | L89: 24000 | M89: 1.19 | N89: 21000 | O89: =(L89/K89)-1 -> 0.28459027 | P89: =K89*F89 -> 0
A90: Acrilico auto 60 g A0 | G90: New Stetic | H90: 0 | I90: 1 | K90: 18683 | L90: 24000 | M90: 1.19 | N90: 21000 | O90: =(L90/K90)-1 -> 0.28459027 | P90: =K90*F90 -> 0
A91: Acrilico Auto 60 g A1 | G91: New Stetic | H91: 0 | I91: 12 | K91: 18683 | L91: 24000 | M91: 1.19 | N91: 21000 | O91: =(L91/K91)-1 -> 0.28459027 | P91: =K91*F91 -> 0
A92: Acrilico auto 60 g A2 | G92: New Stetic | H92: 0 | I92: 7 | K92: 18683 | L92: 24000 | M92: 1.19 | N92: 21000 | O92: =(L92/K92)-1 -> 0.28459027 | P92: =K92*F92 -> 0
A93: Acrilico auto 60 g A3 | G93: New Stetic | H93: 0 | I93: 5 | K93: 18683 | L93: 24000 | M93: 1.19 | N93: 21000 | O93: =(L93/K93)-1 -> 0.28459027 | P93: =K93*F93 -> 0
A94: Acrilico Auto 60 g B2 | G94: New Stetic | H94: 0 | I94: 4 | K94: 18683 | L94: 24000 | M94: 1.19 | N94: 21000 | O94: =(L94/K94)-1 -> 0.28459027 | P94: =K94*F94 -> 0
A95: Acrilico auto 60 g JB | G95: New Stetic | H95: 0 | I95: 10 | K95: 9639 | L95: 14000 | M95: 1.19 | N95: 12000 | O95: =(L95/K95)-1 -> 0.45243282 | P95: =K95*F95 -> 0
A96: Acrilico auto 60 g Transparente | G96: New Stetic | H96: 0 | I96: 14 | K96: 9639 | L96: 14000 | M96: 1.19 | N96: 12000 | O96: =(L96/K96)-1 -> 0.45243282 | P96: =K96*F96 -> 0
A97: Acrilico auto 60 g VR1 | G97: New Stetic | H97: 0 | I97: 7 | K97: 9639 | L97: 14000 | M97: 1.19 | N97: 12000 | O97: =(L97/K97)-1 -> 0.45243282 | P97: =K97*F97 -> 0
A98: Acrilico auto 60 g VRX | G98: New Stetic | H98: 0 | I98: 10 | K98: 9639 | L98: 14000 | M98: 1.19 | N98: 12000 | O98: =(L98/K98)-1 -> 0.45243282 | P98: =K98*F98 -> 0
A99: Acrilico auto JB 500 gm | G99: New Stetic | H99: 0 | I99: 2 | J99: 1/10/2025 09-2026 | K99: 55167 | L99: 70000 | N99: 64000 | O99: =(L99/K99)-1 -> 0.26887451 | P99: =K99*F99 -> 0
A100: Acrilico auto liquido 1000 cc | G100: New Stetic | H100: 0 | I100: 1 | J100: 46508 | K100: =54400*1.19 -> 64736 | L100: 78000 | N100: 72000 | O100: =(L100/K100)-1 -> 0.20489372 | P100: =K100*F100 -> 0
...

Sheet AGOTADOS SUR
A1: fecha | B1: LO QUE FALTA | C1: observaciones | F1: NOTA NORTE
A2: 45716 | B2: ENDO FROST | C2: PEDIR | D2: norte no hay | E2: PEDIR | F2: pedir
A3: 45783 | B3: cepillos interdentales granel y viajero | C3: norte | D3: agotado norte | E3: PEDIR | F3: ya mandamos junio 28
A4: 45787 | B4: sellantes maquira | C4: DE CUALES ? | D4: ya mande | F4: pedir
A5: 45800 | B5: 6 GUANTES NEGRO NITRILO TALLA S | C5: MIENTRAS PEDIMOS | F5: pedir
A6: 45805 | B6: acido sdi | C6: agotado | F6: ya mandamos junio 28
A7: 45821 | B7: Pesada Zhermack | C7: norte | D7: de las 2 presentciones | F7: ya mandamos junio 28
A8: 45821 | B8: Pesada Panasil | C8: norte | D8: 400ml | F8: ya mandamos junio 28
A9: 45821 | B9: PRIMMA ART | C9: norte | F9: ya mandamos junio 28
A10: 45821 | B10: ENEBRADORES | C10: norte | F10: ya mandamos junio 28
A11: 45827 | B11: felpa peluche | C11: norte | D11: agotado norte | F11: ya se mando pedir
A12: 45827 | B12: felpa pelo de cabra beige HP | C12: norte | D12: agotado norte | F12: ya se mando pedir
A13: 45827 | B13: septanes 1/100 | C13: norte | D13: agotado norte | E13: donde abraham ya llego con bueba fecha | F13: pedir
A14: 45833 | B14: piedra pomex lib | C14: norte | D14: agotado norte | F14: pedir
A15: 45834 | B15: alginato orthopint | C15: norte | D15: agotado | F15: pedir
A16: 45839 | B16: POSTES AMARILLOS | C16: norte
A17: 45839 | B17: ORTHOPRINT | C17: norte

Sheet COPIA INSTRUMENTAL SUR 
A1: Perico | B1: nelly | C1: FERCHO | D1: CRIST | E1: PEDIDO NORTE | H1: PERICO dcto 12% + iva | I1: NELLY dcto 15% + iva | J1: CRISTIAN | K1: AQUILES FERCHO | L1: a quien pedir) | N1: PRECIO DEL PEDIDO | O1: MALETERO | P1: costo | Q1: VR TOTAL | R1: PRECIO DE VENTA | S1: %
E2: 0 | F2: ABREBOCA MOLT ADULTO | H2: =24000*0.88*1.19 -> 25132.8 | L2: PERICO | M2: =24000*0.88*1.19 -> 25132.8 | N2: =E2*J2 -> 0 | P2: =H2*O2 -> 0 | Q2: =R2*O2 -> 0 | R2: 45000 | S2: =(R2/H2)-1 -> 0.79048892
E3: 0 | F3: ABREBOCA MOLT PEDIATRICO | H3: =24000*0.88*1.19 -> 25132.8 | L3: PERICO | M3: =24000*0.88*1.19 -> 25132.8 | N3: =E3*J3 -> 0 | P3: =H3*O3 -> 0 | Q3: =R3*O3 -> 0 | R3: 45000 | S3: =(R3/H3)-1 -> 0.79048892
E4: 0 | F4: ALICATE 2 PICOS # 139 | H4: =18700*0.88*1.19 -> 19582.64 | I4: =+25227*0.85*1.19 -> 25517.11 | K4: =18000*0.85*1.19 -> 18207 | L4: AQUILES | M4: =18000*0.85*1.19 -> 18207 | N4: =K4*E4 -> 0 | O4: 30000 | P4: =C4*K4 -> 0 | Q4: =R4*O4 -> 1020000000 | R4: 34000 | S4: =(R4/H4)-1 -> 0.73623168
E5: 0 | F5: ALICATE 3 PICOS # 200 | H5: =18700*0.88*1.19 -> 19582.64 | I5: =+25227*0.85*1.19 -> 25517.11 | K5: =18000*0.85*1.19 -> 18207 | L5: AQUILES | M5: =18000*0.85*1.19 -> 18207 | N5: =K5*E5 -> 0 | P5: =C5*K5 -> 0 | Q5: =R5*O5 -> 0 | R5: 34000 | S5: =(R5/H5)-1 -> 0.73623168
E6: 10 | F6: ALICATE PINZA QUITA BANDAS # 34 | G6: PRECIO PERICO $20980 | H6: =19000*0.88*1.19 -> 19896.8 | I6: =25227*0.85*1.19 -> 25517.11 | L6: PERICO | M6: =19000*0.88*1.19 -> 19896.8 | N6: =E6*H6 -> 198968 | P6: =H6*O6 -> 0 | Q6: =R6*O6 -> 0 | R6: 34000 | S6: =(R6/H6)-1 -> 0.7088175
E7: 0 | F7: Aplicador de ligaduras llaves y cadenetas Morelly | R7: 28000 | S7: =(R7/H7)-1 -> #DIV/0!
E8: 5 | F8: APLICADOR DICAL | H8: =3700*0.88*1.19 -> 3874.64 | I8: =3507*0.85*1.19 -> 3547.3305 | K8: =3800*0.85*1.19 -> 3843.7 | L8: AQUILES | M8: =3800*0.85*1.19 -> 3843.7 | N8: =K8*E8 -> 19218.5 | P8: =C8*K8 -> 0 | Q8: =R8*O8 -> 0 | R8: 7000 | S8: =(R8/H8)-1 -> 0.80661945
E9: 0 | F9: arco de Young De ADULTO OJO GRANDE instrumental | H9: =7400*0.88*1.19 -> 7749.28 | I9: N / V | K9: =5000*0.85*1.19 -> 5057.5 | L9: AQUILES | M9: =5000*0.85*1.19 -> 5057.5 | N9: =K9*E9 -> 0 | P9: =C9*K9 -> 0 | Q9: =R9*O9 -> 0 | R9: 14000 | S9: =(R9/H9)-1 -> 0.80661945
E10: 0 | F10: arco de Young pediatrico Pño instrumental | H10: =7400*0.88*1.19 -> 7749.28 | I10: N / V | K10: =5000*0.85*1.19 -> 5057.5 | L10: AQUILES | M10: =5000*0.85*1.19 -> 5057.5 | N10: =K10*E10 -> 0 | P10: =C10*K10 -> 0 | Q10: =R10*O10 -> 0 | R10: 14000 | S10: =(R10/H10)-1 -> 0.80661945
E11: 0 | F11: Asentador de bandas 300 X instrumental (PARECE ELEVADOR) bandpusher | H11: =9000*0.88*1.19 -> 9424.8 | I11: =13740*0.85*1.19 -> 13898.01 | J11: 5000 | L11: CRISTIAN | M11: 5000 | N11: =E11*H11 -> 0 | P11: =O11*H11 -> 0 | Q11: =R11*O11 -> 0 | R11: 30000 | S11: =(R11/H11)-1 -> 2.1830914
E12: 10 | F12: Asentador de bandas color | H12: =5500*0.88*1.19 -> 5759.6 | L12: PERICO | M12: =5500*0.88*1.19 -> 5759.6 | N12: =E12*J12 -> 0 | P12: =H12*O12 -> 0 | Q12: =R12*O12 -> 0 | R12: 24000 | S12: =(R12/H12)-1 -> 3.166956
E13: 0 | F13: Asentador de Bandas MORELI | R13: 32000
E14: 10 | F14: BISTURI DE KIRKLAN INSTRUMENTAL | H14: =5000*0.88*1.19 -> 5236 | L14: PERICO | M14: =5000*0.88*1.19 -> 5236 | N14: =E14*H14 -> 52360 | O14: 8000 | P14: =O14*H14 -> 41888000 | Q14: =R14*O14 -> 80000000 | R14: 10000 | S14: =(R14/H14)-1 -> 0.90985485
E15: 6 | F15: BISTURI DE ORBAN INSTRUMENTAL | H15: =4800*0.88*1.19 -> 5026.56 | I15: =7139*0.85*1.19 -> 7221.0985 | L15: PERICO | M15: =4800*0.88*1.19 -> 5026.56 | N15: =E15*H15 -> 30159.36 | O15: 8000 | P15: =H15*O15 -> 40212480 | Q15: =R15*O15 -> 80000000 | R15: 10000 | S15: =(R15/H15)-1 -> 0.98943214
E16: 0 | F16: Bruñidor 21 B | H16: =5000*0.88*1.19 -> 5236 | K16: =5000*0.85*1.19 -> 5057.5 | L16: AQUILES | M16: =5000*0.85*1.19 -> 5057.5 | N16: =E16*J16 -> 0 | P16: =C16*K16 -> 0 | Q16: =R16*O16 -> 0 | R16: 8000 | S16: =(R16/H16)-1 -> 0.52788388
E17: 0 | F17: Bruñidor de Bola y orqueta | H17: =5000*0.88*1.19 -> 5236 | K17: =5000*0.85*1.19 -> 5057.5 | L17: AQUILES | M17: =5000*0.85*1.19 -> 5057.5 | N17: =E17*J17 -> 0 | P17: =C17*K17 -> 0 | Q17: =R17*O17 -> 0 | R17: 8000 | S17: =(R17/H17)-1 -> 0.52788388
D18: 20 | F18: CADENA PORTA BABERO | J18: 2500 | L18: CRISTIAN | M18: 2500 | P18: =K18*O18 -> 0 | Q18: =R18*O18 -> 0 | R18: 6000 | S18: =(R18/J18)-1 -> 1.4
E19: 0 | F19: Calibrador de cera instrumental | G19: precio crstian $10000 | H19: =10000*1.19*0.88 -> 10472 | I19: =16786*1.19*0.85 -> 16979.039 | J19: 8000 | K19: =10000*0.85*1.19 -> 10115 | L19: CRISTIAN | M19: 8000 | N19: =E19*H19 -> 0 | P19: =C19*K19 -> 0 | Q19: =R19*O19 -> 0 | R19: 24000 | S19: =(R19/H19)-1 -> 1.2918258
E20: 0 | F20: calibrador de metal instrumental | H20: =11000*1.19*0.88 -> 11519.2 | I20: =16786*0.85*1.19 -> 16979.039 | J20: 8000 | K20: =10000*0.85*1.19 -> 10115 | L20: CRISTIAN | M20: 8000 | N20: =E20*H20 -> 0 | P20: =C20*K20 -> 0 | Q20: =R20*O20 -> 0 | R20: 24000 | S20: =(R20/H20)-1 -> 1.083478
E21: 0 | F21: calibrador pie de rey | L21: CRISTIAN | R21: 24000
E22: 0 | F22: Castro Viejo instrumental (OJO PINZA QUE TIENE GANCHO EN EL MEDIO) | H22: =24900*0.88*1.19 -> 26075.28 | I22: =30945*0.85*1.19 -> 31300.868 | L22: CRISTIAN | M22: 26071 | N22: =E22*J22 -> 0 | O22: 35000 | P22: =K22*O22 -> 0 | Q22: =R22*O22 -> 1470000000 | R22: 42000 | S22: =(R22/H22)-1 -> 0.61072096
E23: 0 | F23: Castro Viejo instrumental tijera | H23: =18000*0.88*1.19 -> 18849.6 | I23: 25601 | J23: 19000 | L23: CRISTIAN | M23: 19000 | N23: =E23*J23 -> 0 | O23: 35000 | P23: =K23*O23 -> 0 | Q23: =R23*O23 -> 1470000000 | R23: 42000 | S23: =(R23/H23)-1 -> 1.228164
E24: 0 | F24: CK 4 | H24: =5000*0.88*1.19 -> 5236 | I24: =6267*0.85*1.19 -> 6339.0705 | K24: =5000*0.85*1.19 -> 5057.5 | L24: AQUILES | M24: =5000*0.85*1.19 -> 5057.5 | N24: =K24*E24 -> 0 | O24: 8000 | P24: =C24*K24 -> 0 | Q24: =R24*O24 -> 80000000 | R24: 10000 | S24: =(R24/H24)-1 -> 0.90985485
E25: 0 | F25: CK 6 | H25: =5000*0.88*1.19 -> 5236 | J25: 3000 | K25: =5000*0.85*1.19 -> 5057.5 | L25: CRISTIAN | M25: 3000 | N25: =E25*J25 -> 0 | P25: =C25*K25 -> 0 | Q25: =R25*O25 -> 0 | R25: 10000 | S25: =(R25/H25)-1 -> 0.90985485
E26: 0 | F26: CONDENSADOR DE AMALGAMA | H26: =4800*0.88*1.19 -> 5026.56 | L26: PERICO | M26: =5000*0.88*1.19 -> 5236 | N26: =E26*J26 -> 0 | P26: =O26*H26 -> 0 | Q26: =R26*O26 -> 0 | R26: 10000 | S26: =(R26/H26)-1 -> 0.98943214
E27: 0 | F27: Corte de Ligadura ortodoncia | H27: =22000*0.88*1.19 -> 23038.4 | I27: =25227*0.85*1.19 -> 25517.11 | L27: PERICO | M27: =22000*0.88*1.19 -> 23038.4 | N27: =E27*J27 -> 0 | O27: 35000 | R27: 40000 | S27: =(R27/H27)-1 -> 0.73623168
E28: 0 | F28: Corte de Ligadura ortodoncia angelus | R28: 80000 | S28: =(R28/H28)-1 -> #DIV/0!
E29: 5 | F29: Corte Distal ORTODONCIA | H29: =29700*0.88*1.19 -> 31101.84 | L29: PERICO | M29: =29700*0.88*1.19 -> 31101.84 | N29: =E29*J29 -> 0 | O29: 42000 | R29: 48000 | S29: =(R29/H29)-1 -> 0.54331705
E30: 10 | F30: CUBETAS PARA IMPRESIÓN ADULTOS | H30: =58500*0.88*1.19 -> 61261.2 | I30: 64867 | K30: =58000*0.85*1.19 -> 58667 | L30: AQUILES | M30: =58000*0.85*1.19 -> 58667 | N30: =K30*E30 -> 586670 | O30: 74000 | P30: =C30*K30 -> 0 | R30: 95000 | S30: =(R30/H30)-1 -> 0.55073684
E31: 0 | F31: CUBETAS PARA IMPRESIÓN pediatrico | H31: =58500*0.88*1.19 -> 61261.2 | I31: 64867 | K31: =58000*0.85*1.19 -> 58667 | L31: AQUILES | M31: =58000*0.85*1.19 -> 58667 | N31: =K31*E31 -> 0 | P31: =C31*K31 -> 0 | Q31: =R31*O31 -> 0 | R31: 95000 | S31: =(R31/H31)-1 -> 0.55073684
E32: 20 | F32: Cucharilla #17 Puppies | H32: =4800*0.88*1.19 -> 5026.56 | L32: PERICO | M32: =4800*0.88*1.19 -> 5026.56 | N32: =E32*J32 -> 0 | R32: 9000 | S32: =(R32/H32)-1 -> 0.79048892
E33: 0 | F33: Cucharilla basico instrumental | G33: BASICO | H33: =4800*0.88*1.19 -> 5026.56 | I33: =5494*0.85*1.19 -> 5557.181 | K33: =5000*0.85*1.19 -> 5057.5 | L33: AQUILES | M33: =5000*0.85*1.19 -> 5057.5 | N33: =K33*E33 -> 0 | P33: =C33*K33 -> 0 | Q33: =R33*O33 -> 0 | R33: 9000 | S33: =(R33/H33)-1 -> 0.79048892
E34: 0 | F34: CUCHILLO PROTESIS GRANDE | H34: =7000*0.88*1.19 -> 7330.4 | I34: 3724 | J34: 4000 | K34: =6500*0.85*1.19 -> 6574.75 | L34: CRISTIAN | M34: 4000 | N34: =E34*J34 -> 0 | O34: 10000 | P34: =C34*K34 -> 0 | Q34: =R34*O34 -> 130000000 | R34: 13000 | S34: =(R34/H34)-1 -> 0.77343665
E35: 0 | F35: Cureta 11/12 instrumental Mc Call | G35: precio cristian $4000 | H35: =5000*1.19*0.88 -> 5236 | I35: =6043*0.85*1.19 -> 6112.4945 | L35: PERICO | M35: =5000*1.19*0.88 -> 5236 | N35: =E35*H35 -> 0 | P35: =H35*O35 -> 0 | Q35: =R35*O35 -> 0 | R35: 9000 | S35: =(R35/H35)-1 -> 0.71886937
E36: 5 | F36: Cureta 13/14 instrumental Mc Call | H36: =5000*1.19*0.88 -> 5236 | I36: =6043*0.85*1.19 -> 6112.4945 | K36: =5000*0.85*1.19 -> 5057.5 | L36: AQUILES | M36: =5000*0.85*1.19 -> 5057.5 | N36: =K36*E36 -> 25287.5 | P36: =C36*K36 -> 0 | Q36: =R36*O36 -> 0 | R36: 9000 | S36: =(R36/H36)-1 -> 0.71886937
E37: 0 | F37: Cureta 15/16 instrumental Mc Call | H37: =5000*1.19*0.88 -> 5236 | I37: =6043*0.85*1.19 -> 6112.4945 | L37: PERICO | M37: =5000*1.19*0.88 -> 5236 | N37: =E37*H37 -> 0 | P37: =K37*O37 -> 0 | Q37: =R37*O37 -> 0 | R37: 9000 | S37: =(R37/H37)-1 -> 0.71886937
E38: 0 | F38: Cureta 17/18 instrumental Mc Call | H38: =5000*1.19*0.88 -> 5236 | I38: =6043*0.85*1.19 -> 6112.4945 | K38: =5000*0.85*1.19 -> 5057.5 | L38: AQUILES | M38: =5000*0.85*1.19 -> 5057.5 | N38: =K38*E38 -> 0 | P38: =C38*K38 -> 0 | Q38: =R38*O38 -> 0 | R38: 9000 | S38: =(R38/H38)-1 -> 0.71886937
D39: 12 | E39: 1 | F39: cureta de Lucas #85 | G39: precio cristian 5600 | H39: =4800*1.19*0.88 -> 5026.56 | I39: =6043*0.85*1.19 -> 6112.4945 | J39: 3300 | K39: =5000*0.85*1.19 -> 5057.5 | L39: CRISTIAN | M39: 3300 | N39: =E39*J39 -> 3300 | P39: =C39*K39 -> 0 | Q39: =R39*O39 -> 0 | R39: 9000 | S39: =(R39/H39)-1 -> 0.79048892
D40: 4 | F40: CURETA Gracey 1/2 Instrumental | H40: =5000*1.19*0.88 -> 5236 | I40: =6043*0.85*1.19 -> 6112.4945 | J40: 3700 | L40: CRISTIAN | M40: 3700 | N40: =E40*J40 -> 0 | P40: =K40*O40 -> 0 | Q40: =R40*O40 -> 0 | R40: 9000 | S40: =(R40/H40)-1 -> 0.71886937
E41: 0 | F41: CURETA Gracey 11/12 Instrumental | H41: =5000*1.19*0.88 -> 5236 | I41: =6043*0.85*1.19 -> 6112.4945 | J41: 3700 | K41: =5000*0.85*1.19 -> 5057.5 | L41: CRISTIAN | M41: 3700 | N41: =E41*J41 -> 0 | P41: =C41*K41 -> 0 | Q41: =R41*O41 -> 0 | R41: 9000 | S41: =(R41/H41)-1 -> 0.71886937
E42: 0 | F42: CURETA Gracey 13/14 Instrumental | H42: =5000*1.19*0.88 -> 5236 | I42: =6043*0.85*1.19 -> 6112.4945 | J42: 3700 | K42: =5000*0.85*1.19 -> 5057.5 | L42: CRISTIAN | M42: 3700 | N42: =E42*J42 -> 0 | P42: =C42*K42 -> 0 | Q42: =R42*O42 -> 0 | R42: 9000 | S42: =(R42/H42)-1 -> 0.71886937
E43: 5 | F43: CURETA Gracey 15/16 Instrumental | H43: =5000*1.19*0.88 -> 5236 | I43: =6043*0.85*1.19 -> 6112.4945 | L43: PERICO | M43: =5000*1.19*0.88 -> 5236 | N43: =E43*H43 -> 26180 | P43: =H43*O43 -> 0 | Q43: =R43*O43 -> 0 | R43: 9000 | S43: =(R43/H43)-1 -> 0.71886937
E44: 0 | F44: CURETA Gracey 17/18 Instrumental | H44: =5000*1.19*0.88 -> 5236 | I44: =6043*0.85*1.19 -> 6112.4945 | J44: 3700 | K44: =5000*0.85*1.19 -> 5057.5 | L44: CRISTIAN | M44: 3700 | N44: =E44*J44 -> 0 | P44: =C44*K44 -> 0 | Q44: =R44*O44 -> 0 | R44: 9000 | S44: =(R44/H44)-1 -> 0.71886937
D45: 5 | F45: CURETA Gracey 3/4 Instrumental | H45: =5000*1.19*0.88 -> 5236 | I45: =6043*0.85*1.19 -> 6112.4945 | J45: 3700 | K45: =5000*0.85*1.19 -> 5057.5 | L45: CRISTIAN | M45: 3700 | N45: =E45*J45 -> 0 | P45: =C45*K45 -> 0 | Q45: =R45*O45 -> 0 | R45: 9000 | S45: =(R45/H45)-1 -> 0.71886937
D46: 5 | F46: CURETA Gracey 5/6 Instrumental | H46: =5000*1.19*0.88 -> 5236 | I46: =6043*0.85*1.19 -> 6112.4945 | J46: 3700 | K46: =5000*0.85*1.19 -> 5057.5 | L46: CRISTIAN | M46: 3700 | N46: =E46*J46 -> 0 | P46: =C46*K46 -> 0 | Q46: =R46*O46 -> 0 | R46: 9000 | S46: =(R46/H46)-1 -> 0.71886937
E47: 0 | F47: CURETA Gracey 7/8 Instrumental | H47: =5000*1.19*0.88 -> 5236 | I47: =6043*0.85*1.19 -> 6112.4945 | J47: 3700 | K47: =5000*0.85*1.19 -> 5057.5 | L47: CRISTIAN | M47: 3700 | N47: =E47*J47 -> 0 | P47: =C47*K47 -> 0 | Q47: =R47*O47 -> 0 | R47: 9000 | S47: =(R47/H47)-1 -> 0.71886937
E48: 0 | F48: CURETA Gracey 9/10 Instrumental | H48: =5000*1.19*0.88 -> 5236 | I48: =6043*0.85*1.19 -> 6112.4945 | J48: 3700 | K48: =5000*0.85*1.19 -> 5057.5 | L48: CRISTIAN | M48: 3700 | N48: =E48*J48 -> 0 | P48: =C48*K48 -> 0 | Q48: =R48*O48 -> 0 | R48: 9000 | S48: =(R48/H48)-1 -> 0.71886937
E49: 1 | F49: elevador Apical derecho 303 instrumental | H49: =12500*1.19*0.88 -> 13090 | I49: =13740*0.85*1.19 -> 13898.01 | K49: =13000*0.85*1.19 -> 13149.5 | L49: AQUILES | M49: =13000*0.85*1.19 -> 13149.5 | N49: =K49*E49 -> 13149.5 | O49: 18000 | P49: =C49*K49 -> 0 | Q49: =R49*O49 -> 432000000 | R49: 24000 | S49: =(R49/H49)-1 -> 0.83346066
E50: 1 | F50: elevador Apical Izquierdo 302 instrumental | H50: =12500*1.19*0.88 -> 13090 | I50: =13740*0.85*1.19 -> 13898.01 | K50: =13000*0.85*1.19 -> 13149.5 | L50: AQUILES | M50: =13000*0.85*1.19 -> 13149.5 | N50: =K50*E50 -> 13149.5 | O50: 18000 | P50: =C50*K50 -> 0 | Q50: =R50*O50 -> 432000000 | R50: 24000 | S50: =(R50/H50)-1 -> 0.83346066
D51: 5 | E51: 1 | F51: elevador bandera derecha 1R instrumental | H51: =12500*1.19*0.88 -> 13090 | I51: =13740*0.85*1.19 -> 13898.01 | K51: =13000*0.85*1.19 -> 13149.5 | L51: AQUILES | M51: =13000*0.85*1.19 -> 13149.5 | N51: =K51*E51 -> 13149.5 | O51: 18000 | P51: =C51*K51 -> 0 | Q51: =R51*O51 -> 432000000 | R51: 24000 | S51: =(R51/H51)-1 -> 0.83346066
E52: 1 | F52: elevador bandera izquierdo 1L instrumental | H52: =12500*1.19*0.88 -> 13090 | I52: =13740*0.85*1.19 -> 13898.01 | K52: =13000*0.85*1.19 -> 13149.5 | L52: AQUILES | M52: =13000*0.85*1.19 -> 13149.5 | N52: =K52*E52 -> 13149.5 | O52: 18000 | P52: =C52*K52 -> 0 | Q52: =R52*O52 -> 432000000 | R52: 24000 | S52: =(R52/H52)-1 -> 0.83346066
E53: 1 | F53: elevador recto ancho 304 instrumental | H53: =12500*1.19*0.88 -> 13090 | I53: =13740*0.85*1.19 -> 13898.01 | K53: =13000*0.85*1.19 -> 13149.5 | L53: AQUILES | M53: =13000*0.85*1.19 -> 13149.5 | N53: =K53*E53 -> 13149.5 | O53: 18000 | P53: =C53*K53 -> 0 | Q53: =R53*O53 -> 432000000 | R53: 24000 | S53: =(R53/H53)-1 -> 0.83346066
E54: 1 | F54: elevador recto delgado 301 instrumental | H54: =12500*1.19*0.88 -> 13090 | I54: =13740*0.85*1.19 -> 13898.01 | K54: =13000*0.85*1.19 -> 13149.5 | L54: AQUILES | M54: =13000*0.85*1.19 -> 13149.5 | N54: =K54*E54 -> 13149.5 | O54: 18000 | P54: =C54*K54 -> 0 | Q54: =R54*O54 -> 432000000 | R54: 24000 | S54: =(R54/H54)-1 -> 0.83346066
E55: 0 | F55: elevador recto MAS ancho 34 instrumental | H55: =12500*1.19*0.88 -> 13090 | I55: =13740*0.85*1.19 -> 13898.01 | L55: PERICO | M55: =12500*1.19*0.88 -> 13090 | N55: =E55*J55 -> 0 | O55: 18000 | P55: =H55*O55 -> 235620000 | Q55: =R55*O55 -> 432000000 | R55: 24000 | S55: =(R55/H55)-1 -> 0.83346066
E56: 1 | F56: Elevador seldin 23 instrumental | H56: =11000*0.82*1.19 -> 10733.8 | I56: =13740*0.85*1.19 -> 13898.01 | J56: 5000 | K56: =9000*0.85*1.19 -> 9103.5 | L56: CRISTIAN | M56: 5000 | N56: =E56*J56 -> 5000 | O56: 18000 | P56: =C56*K56 -> 0 | Q56: =R56*O56 -> 432000000 | R56: 24000 | S56: =(R56/H56)-1 -> 1.2359276
E57: 0 | F57: EMPACADOR DE HILO instrumental | H57: N/V | I57: =17921*0.85*1.19 -> 18127.091 | K57: =5000*0.85*1.19 -> 5057.5 | L57: AQUILES | M57: =5000*0.85*1.19 -> 5057.5 | N57: =K57*E57 -> 0 | P57: =C57*K57 -> 0 | Q57: =R57*O57 -> 0 | R57: 28000 | S57: =(R57/I57)-1 -> 0.54464934
D58: 50 | F58: ESPATULA 7A | G58: revisar $4500 cris | H58: =4800*0.88*1.19 -> 5026.56 | I58: =6593*0.85*1.19 -> 6668.8195 | J58: 3000 | K58: =5000*0.85*1.19 -> 5057.5 | L58: CRISTIAN | M58: 3000 | N58: =E58*H58 -> 0 | O58: 7000 | P58: =C58*K58 -> 0 | Q58: =R58*O58 -> 63000000 | R58: 9000 | S58: =(R58/H58)-1 -> 0.79048892
E59: 0 | F59: ESPATULA 7A PLASTICO
E60: 30 | F60: Espatula de cemento metalica CORTA DOBLE instrumental 20/23 | H60: =5000*0.88*1.19 -> 5236 | I60: =6043*0.85*1.19 -> 6112.4945 | J60: 5000 | K60: =5000*0.85*1.19 -> 5057.5 | L60: CRISTIAN AQUILES | M60: 5058 | N60: =K60*E60 -> 151725 | O60: 7000 | R60: 9000 | S60: =(R60/H60)-1 -> 0.71886937
E61: 0 | F61: Espatula de CEMENTO PLASTICA | R61: 4000
D62: 15 | E62: 0 | F62: ESPATULA GRITMAN PARA CERA | H62: =5000*0.88*1.19 -> 5236 | I62: =4696*0.85*1.19 -> 4750.004 | J62: 4800 | K62: =6000*0.85*1.19 -> 6069 | L62: AQUILES | M62: =6000*0.85*1.19 -> 6069 | N62: =K62*E62 -> 0 | P62: =C62*K62 -> 0 | Q62: =R62*O62 -> 0 | R62: 9000 | S62: =(R62/H62)-1 -> 0.71886937
E63: 20 | F63: espatula yeso mango madera ANCHA INSTRUMENTAL | H63: =5900*0.88*1.19 -> 6178.48 | I63: =6593*0.85*1.19 -> 6668.8195 | K63: =5900*0.85*1.19 -> 5967.85 | L63: AQUILES | M63: =5900*0.85*1.19 -> 5967.85 | N63: =K63*E63 -> 119357 | O63: 8000 | P63: =C63*K63 -> 0 | Q63: =R63*O63 -> 80000000 | R63: 10000 | S63: =(R63/H63)-1 -> 0.61852106
E64: 0 | F64: Estrella Poscicionador de Brackts ortodoncia | R64: 12000 | S64: =(R64/H64)-1 -> #DIV/0!
E65: 0 | F65: ESTUCHE DISECCION EN KIT | J65: 30000 | K65: =40000*0.85*1.19 -> 40460 | L65: CRISTIAN | M65: 30000 | P65: =C65*K65 -> 0 | R65: 55000
E66: 0 | F66: Explorador de conducto | H66: =4800*0.88*1.19 -> 5026.56 | I66: =6593*0.85*1.19 -> 6668.8195 | K66: =5000*0.85*1.19 -> 5057.5 | L66: AQUILES | M66: =5000*0.85*1.19 -> 5057.5 | N66: =E66*J66 -> 0 | P66: =C66*K66 -> 0 | Q66: =R66*O66 -> 0 | R66: 9000 | S66: =(R66/H66)-1 -> 0.79048892
E67: 0 | F67: Explorador del Basico instrumental | G67: BASICO | H67: =4800*0.88*1.19 -> 5026.56 | I67: =6043*0.85*1.19 -> 6112.4945 | K67: =4700*0.85*1.19 -> 4754.05 | L67: AQUILES | M67: =4700*0.85*1.19 -> 4754.05 | N67: =K67*E67 -> 0 | P67: =C67*K67 -> 0 | Q67: =R67*O67 -> 0 | R67: 9000 | S67: =(R67/H67)-1 -> 0.79048892
E68: 1 | F68: forceps 150 instrumental | H68: =26400*0.88*1.19 -> 27646.08 | I68: =30884*0.85*1.19 -> 31239.166 | K68: =29000*0.85*1.19 -> 29333.5 | L68: AQUILES | M68: =29000*0.85*1.19 -> 29333.5 | N68: =K68*E68 -> 29333.5 | O68: 35000 | P68: =C68*K68 -> 0 | Q68: =R68*O68 -> 1470000000 | R68: 42000 | S68: =(R68/H68)-1 -> 0.51920272
E69: 1 | F69: forceps 151 instrumental | H69: =26400*0.88*1.19 -> 27646.08 | I69: =30884*0.85*1.19 -> 31239.166 | J69: 20000 | K69: =29000*0.85*1.19 -> 29333.5 | L69: AQUILES | M69: =29000*0.85*1.19 -> 29333.5 | N69: =K69*E69 -> 29333.5 | O69: 35000 | P69: =C69*K69 -> 0 | Q69: =R69*O69 -> 1470000000 | R69: 42000 | S69: =(R69/H69)-1 -> 0.51920272
E70: 1 | F70: forceps 16 instrumental | H70: =30000*0.88*1.19 -> 31416 | I70: =30884*0.85*1.19 -> 31239.166 | K70: =29000*0.85*1.19 -> 29333.5 | L70: AQUILES | M70: =29000*0.85*1.19 -> 29333.5 | N70: =E70*K70 -> 29333.5 | O70: 35000 | P70: =C70*K70 -> 0 | Q70: =R70*O70 -> 1470000000 | R70: 42000 | S70: =(R70/H70)-1 -> 0.3368984
E71: 0 | F71: forceps 17 L (no pedir) | R71: 42000
E72: 0 | F72: forceps 18 L (no pedir) | R72: 42000
E73: 0 | F73: forceps 24 instrumental | H73: =30000*0.88*1.19 -> 31416 | I73: =30884*0.85*1.19 -> 31239.166 | K73: =29000*0.85*1.19 -> 29333.5 | L73: AQUILES | M73: =29000*0.85*1.19 -> 29333.5 | N73: =E73*J73 -> 0 | O73: 35000 | P73: =C73*K73 -> 0 | Q73: =R73*O73 -> 1470000000 | R73: 42000 | S73: =(R73/H73)-1 -> 0.3368984
E74: 1 | F74: forceps 69 instrumental | H74: =30000*0.88*1.19 -> 31416 | I74: =30884*0.85*1.19 -> 31239.166 | K74: =29000*0.85*1.19 -> 29333.5 | L74: AQUILES | M74: =29000*0.85*1.19 -> 29333.5 | N74: =E74*K74 -> 29333.5 | O74: 35000 | P74: =C74*K74 -> 0 | Q74: =R74*O74 -> 1470000000 | R74: 42000 | S74: =(R74/H74)-1 -> 0.3368984
E75: 5 | F75: forceps pediatrico 150 S instrumental | H75: =30000*0.88*1.19 -> 31416 | I75: =30884*0.85*1.19 -> 31239.166 | K75: =29000*0.85*1.19 -> 29333.5 | L75: AQUILES | M75: =29000*0.85*1.19 -> 29333.5 | N75: =K75*E75 -> 146667.5 | O75: 35000 | P75: =C75*K75 -> 0 | Q75: =R75*O75 -> 1470000000 | R75: 42000 | S75: =(R75/H75)-1 -> 0.3368984
E76: 0 | F76: forceps pediatrico 151 S instrumental | H76: =30000*0.88*1.19 -> 31416 | I76: =30884*0.85*1.19 -> 31239.166 | K76: =29000*0.85*1.19 -> 29333.5 | L76: AQUILES | M76: =29000*0.85*1.19 -> 29333.5 | N76: =K76*E76 -> 0 | O76: 35000 | P76: =C76*K76 -> 0 | Q76: =R76*O76 -> 1470000000 | R76: 42000 | S76: =(R76/H76)-1 -> 0.3368984
E77: 20 | F77: FP 3 | H77: =4800*0.88*1.19 -> 5026.56 | I77: =6043*0.85*1.19 -> 6112.4945 | K77: =4600*0.85*1.19 -> 4652.9 | L77: AQUILES | M77: =4600*0.85*1.19 -> 4652.9 | N77: =K77*E77 -> 93058 | O77: 8000 | P77: =C77*K77 -> 0 | Q77: =R77*O77 -> 80000000 | R77: 10000 | S77: =(R77/H77)-1 -> 0.98943214
E78: 0 | F78: FP 3 plastcio | O78: 8000
E79: 0 | F79: HOLLEMBACK | H79: =4800*1.19*0.88 -> 5026.56 | I79: 5223 | L79: PERICO | M79: =4800*1.19*0.88 -> 5026.56 | N79: =E79*H79 -> 0 | P79: =H79*O79 -> 0 | Q79: =R79*O79 -> 0 | R79: 9000 | S79: =(R79/H79)-1 -> 0.79048892
E80: 10 | F80: INSTRUMENTAL DE GLICK DELGADO | H80: =4800*0.88*1.19 -> 5026.56 | I80: 3266 | K80: =4600*0.85*1.19 -> 4652.9 | L80: AQUILES | M80: =4600*0.85*1.19 -> 4652.9 | N80: =I80*E80 -> 32660 | P80: =C80*K80 -> 0 | Q80: =R80*O80 -> 0 | R80: 9000 | S80: =(R80/H80)-1 -> 0.79048892
D81: 10 | F81: INSTRUMENTAL PKT 54-630 | G81: puppies | H81: =4600*1.19*0.88 -> 4817.12 | J81: 3740 | L81: CRISTIAN | M81: 3740 | N81: =E81*J81 -> 0 | P81: =K81*O81 -> 0 | Q81: =R81*O81 -> 0 | R81: 9000 | S81: =(R81/H81)-1 -> 0.86833627
D82: 10 | F82: INSTRUMENTAL PKT 54-631 | G82: puppies | H82: =4600*1.19*0.88 -> 4817.12 | J82: 3740 | L82: CRISTIAN | M82: 3740 | N82: =E82*J82 -> 0 | P82: =K82*O82 -> 0 | Q82: =R82*O82 -> 0 | R82: 9000 | S82: =(R82/H82)-1 -> 0.86833627
E83: 0 | F83: INSTRUMENTAL PKT 54-632 | H83: =4600*1.19*0.88 -> 4817.12 | J83: 3740 | L83: CRISTIAN | M83: 3740 | N83: =E83*J83 -> 0 | P83: =K83*O83 -> 0 | Q83: =R83*O83 -> 0 | R83: 9000 | S83: =(R83/H83)-1 -> 0.86833627
E84: 20 | F84: INSTRUMENTAL PKT Chorriador 54-628 | H84: N/V | I84: N / V | P84: =K84*O84 -> 0 | Q84: =R84*O84 -> 0 | R84: 9000
E85: 20 | F85: INSTRUMENTAL PKT Chorriador 54-629 | H85: N/V | I85: N / V | R85: 9000
E86: 0 | F86: INSTRUMENTAL PKT completo x 5 | H86: =21500*0.88*1.19 -> 22514.8 | I86: =24071*0.85*1.19 -> 24347.817 | K86: =22000*0.85*1.19 -> 22253 | L86: AQUILES | M86: =22000*0.85*1.19 -> 22253 | N86: =K86*E86 -> 0 | P86: =C86*K86 -> 0 | Q86: =R86*O86 -> 0 | R86: 40000 | S86: =(R86/H86)-1 -> 0.77660916
D87: 20 | E87: 1 | F87: Jeringa carpule de rosca CON ALETA INSTRUMENTAL | H87: =21500*0.88*1.19 -> 22514.8 | I87: =26620*0.85*1.19 -> 26926.13 | J87: 17000 | K87: =21000*0.85*1.19 -> 21241.5 | L87: CRISTIAN | M87: 17000 | N87: =E87*H87 -> 22514.8 | O87: 32000 | P87: =C87*K87 -> 0 | Q87: =R87*O87 -> 1152000000 | R87: 36000 | S87: =(R87/H87)-1 -> 0.59894825
E88: 20 | F88: KIT Basico adulto instrumental | G88: BASICO | H88: =17700*1.19*0.88 -> 18535.44 | I88: =22048*1.19*0.85 -> 22301.552 | K88: =20000*0.85*1.19 -> 20230 | L88: AQUILES | M88: =20000*0.85*1.19 -> 20230 | N88: =K88*E88 -> 404600 | O88: 30000 | P88: =C88*K88 -> 0 | Q88: =R88*O88 -> 1020000000 | R88: 34000 | S88: =(R88/H88)-1 -> 0.83432387
E89: 0 | F89: KIT Basico instrumental PEDIATRICO | G89: BASICO P | H89: N/V | I89: =22048*1.19*0.85 -> 22301.552 | L89: NELLY | M89: =22048*1.19*0.85 -> 22301.552 | N89: =E89*I89 -> 0 | P89: =O89*I89 -> 0 | Q89: =R89*O89 -> 0 | R89: 32000 | S89: =(R89/I89)-1 -> 0.43487772
E90: 1 | F90: Lima de Hueso instrumental | H90: =10000*0.88*1.19 -> 10472 | I90: =11527*0.85*1.19 -> 11659.56 | J90: 4000 | K90: =8500*0.85*1.19 -> 8597.75 | L90: CRISTIAN | M90: 4000 | N90: =E90*J90 -> 4000 | P90: =C90*K90 -> 0 | Q90: =R90*O90 -> 0 | R90: 13000 | S90: =(R90/H90)-1 -> 0.24140565
E91: 0 | F91: luna para espejo instrumental basico No. 5 | G91: BASICO | H91: =1900*0.88*1.19 -> 1989.68 | I91: 2223 | K91: =21600*0.85*1.19/12 -> 1820.7 | L91: AQUILES | M91: =21600*0.85*1.19/12 -> 1820.7 | N91: =K91*E91 -> 0 | P91: =C91*K91 -> 0 | Q91: =R91*O91 -> 0 | R91: 5000 | S91: =(R91/H91)-1 -> 1.5129669
E92: 0 | F92: luna para espejo instrumental No. 4 | H92: =1900*0.88*1.19 -> 1989.68 | N92: =E92*J92 -> 0 | P92: =K92*O92 -> 0 | Q92: =R92*O92 -> 0 | R92: 5000 | S92: =(R92/H92)-1 -> 1.5129669
E93: 1 | F93: Mango de bisturi instrumental | H93: =3700*0.88*1.19 -> 3874.64 | I93: =2725*0.85*1.19 -> 2756.3375 | K93: =3500*0.85*1.19 -> 3540.25 | L93: AQUILES | M93: =3500*0.85*1.19 -> 3540.25 | N93: =K93*E93 -> 3540.25 | O93: 5000 | P93: =C93*K93 -> 0 | Q93: =R93*O93 -> 35000000 | R93: 7000 | S93: =(R93/H93)-1 -> 0.80661945
D94: 20 | F94: MANGO SOLO PARA ESPEJO BASICO instrumental | G94: BASICO | H94: =3900*0.88*1.19 -> 4084.08 | I94: =3507*1.19*0.85 -> 3547.3305 | J94: 2500 | K94: =3000*0.85*1.19 -> 3034.5 | L94: CRISTIAN | M94: 2500 | N94: =E94*J94 -> 0 | P94: =C94*K94 -> 0 | Q94: =R94*O94 -> 0 | R94: 7000 | S94: =(R94/H94)-1 -> 0.7139723
E95: 0 | F95: MARTILLO TUMBA PUENTES XTRES PUNTAS | H95: =35000*0.88*1.19 -> 36652 | I95: =30474*0.85*1.19 -> 30824.451 | K95: =32000*0.85*1.19 -> 32368 | L95: AQUILES | M95: =32000*0.85*1.19 -> 32368 | N95: =K95*E95 -> 0 | P95: =C95*K95 -> 0 | Q95: =R95*O95 -> 0 | R95: 48000 | S95: =(R95/H95)-1 -> 0.30961476
E96: 0 | F96: MECHERO METALICO | J96: 4300 | L96: CRISTIAN | M96: 4300 | N96: =E96*J96 -> 0 | P96: =K96*O96 -> 0 | Q96: =R96*O96 -> 0 | R96: 8000 | S96: =(R96/J96)-1 -> 0.86046512
E97: 5 | F97: Perforador de tela instrumental | H97: =32000*0.88*1.19 -> 33510.4 | I97: =37651*0.85*1.19 -> 38083.986 | K97: =34000*0.85*1.19 -> 34391 | L97: AQUILES | M97: =34000*0.85*1.19 -> 34391 | N97: =K97*E97 -> 171955 | O97: 44000 | P97: =C97*K97 -> 0 | Q97: =R97*O97 -> 2376000000 | R97: 54000 | S97: =(R97/H97)-1 -> 0.61144003
E98: 1 | F98: PERIOSTOTOMO (elevador de molt) | H98: =9000*0.88*1.19 -> 9424.8 | I98: =13740*0.85*1.19 -> 13898.01 | K98: =9500*0.85*1.19 -> 9609.25 | L98: AQUILES | M98: =9500*0.85*1.19 -> 9609.25 | N98: =E98*K98 -> 9609.25 | O98: 15000 | P98: =C98*K98 -> 0 | Q98: =R98*O98 -> 300000000 | R98: 20000 | S98: =(R98/H98)-1 -> 1.1220609
D99: 15 | E99: 0 | F99: PINZA ALGODONERA del basico | G99: BASICO | H99: =5000*0.88*1.19 -> 5236 | I99: =5161*0.85*1.19 -> 5220.3515 | J99: 4300 | K99: =4600*0.85*1.19 -> 4652.9 | L99: CRISTIAN | M99: 4300 | N99: =E99*J99 -> 0 | O99: 7000 | P99: =C99*K99 -> 0 | Q99: =R99*O99 -> 63000000 | R99: 9000 | S99: =(R99/H99)-1 -> 0.71886937
E100: 5 | F100: PINZA ALGODONERA PEDIATRICA | G100: BASICO P | H100: =4800*0.88*1.19 -> 5026.56 | I100: =4343*0.85*1.19 -> 4392.9445 | L100: NELLY | M100: =4343*0.85*1.19 -> 4392.9445 | N100: =E100*J100 -> 0 | P100: =H100*O100 -> 0 | Q100: =R100*O100 -> 0 | R100: 9000 | S100: =(R100/H100)-1 -> 0.79048892
...

Sheet TEMPO NORTE PEDIDO EUFAR
B2: pedi junio 28 | C2: referencias | F2: PEDIDO SUR | G2: PEDIDO NORTE | I2: INVENT SUR mar 21 | J2: INVENT NTE | K2: FECHA VCMTO | L2: PRECIO COMPRA | M2: precio venta
B3: acido fluorhidrico 9.6% Jeringa 2 g Eufar | C3: Aquiles $32000 ramon $32000 EUFAR $29354 | G3: 5 | H3: AQUILES RAMON GABRIEL VELASQUEZ Eufar | J3: 3 | L3: =24667*1.19 -> 29353.73 | M3: 45000 | N3: =G3*L3 -> 146768.65
B4: ALVOFAR eufar | G4: 0 | H4: RAMON-eufar | J4: 0 | K4: muy costoso no pedi | L4: 48744 | M4: 62000 | N4: =G4*L4 -> 0
B5: CALCIFAR - P JERINGA 2ML Hidroxido de calcio en pasta | G5: 0 | H5: eufar | J5: 0 | L5: 25935 | M5: 36000
B6: DENTOFAR 5 ML | C6: aquiles $22325 EUFAR 21385 | G6: 0 | H6: EUFAR proquident AQUILES | J6: 3 | L6: 21385 | M6: 28000
B7: desinfectantes ALCOHOL 80% x 240 ml eucida clasicc | G7: 10 | H7: eufar | J7: 11 | L7: 12285 | M7: 17000 | N7: =G7*L7 -> 122850
B8: EDTA 120 ml eufar | C8: aquiles $40000 eufar $36985 | G8: 0 | H8: Gabriel Velasquez - aquiles Eufar | J8: 6 | L8: 36985 | M8: 58000
B9: Eucida Advanced Solución desinfectante de dispositivos médicos superficie 240ML | G9: 0 | H9: RAMON EUFAR | J9: 13 | K9: 46569 | L9: 12285 | M9: 18000
B10: EUGENOL EUFAR 15ml | G10: 0 | H10: eufar | J10: 15 | L10: 10985 | M10: 16000
B11: fluofar chicle x 240 ml | C11: EUFAR 12299 AQUILES 13566 | G11: 0 | H11: AQUILES EUFAR | J11: 4 | L11: =10335*1.19 -> 12298.65 | M11: 18000
B12: fluor fluofar neutro 240 ML | C12: AQULIES $22848 | G12: 0 | H12: ramon-aquiles - eufar - proquident | J12: 1 | L12: =21385*1.19 -> 25448.15 | M12: 35000
B13: fluor neutro 50 ML | C13: EUFAR 11525 proquident 8935 | G13: 5 | H13: ramon-aquiles PROQUIDENT EUFAR | J13: 4 | K13: 1/10/2026 12-2026 4-2028 | L13: =9685*1.19 -> 11525.15 | M13: 15000 | N13: =G13*L13 -> 57625.75
B14: GOTAS REVELADORAS DITONOS | C14: AQUILES $11,400 | G14: 0 | H14: EUFAR | J14: 0 | L14: =10367*1.19 -> 12336.73 | M14: 15000
B15: hemofar sulfato ferrico EUFAR | G15: 0 | H15: Gabriel Velasquez Eufar | J15: 3 | K15: 46447 | L15: =10985 -> 10985 | M15: 18000
B16: HIDROXIDO DE CALCIO X 10 gm prodont | D16: actualizar 4297 | G16: 0 | H16: RAMON-PROQUIDENT-PRODONT Aquiles Eufar | J16: 10 | K16: 46508 | L16: 7961 | M16: 8000
B17: HIDROXIDO DE CALCIO X 7gm proquident | G17: 0 | H17: RAMON-PROQUIDENT-PRODONT Aquiles Eufar | J17: 10 | L17: 5114 | M17: 8000
B18: JABON DE MANOS 500ML bonfar | G18: 5 | H18: EUFAR | J18: 12 | K18: 46539 | L18: =12935*1.19 -> 15392.65 | M18: 18000 | N18: =G18*L18 -> 76963.25
B19: MOMIFAR 7ML MOMIFICANTE PULPAR X 7 ML EUFAR | G19: 10 | H19: RAMON PRODONT EUFAR | J19: 6 | K19: 46388 | L19: 9620 | M19: 13000 | N19: =G19*L19 -> 96200
B20: MOMIFICANTE PULPAR X 7 ML MOMICIDE | G20: 0 | H20: RAMON PRODONT EUFAR | J20: 0 | K20: 46388 | L20: 9243 | M20: 12000
B21: Pasta Profilactica EUFAR TUBO colapsible Detarfar 50gm | C21: =9685*1.19 -> 11525.15 | G21: 10 | H21: EUFAR | J21: 3 | K21: 46844 | L21: =9685*1.19 -> 11525.15 | M21: 14000 | N21: =G21*L21 -> 115251.5
B22: Pasta Profilactica EUFAR TUBO DETARFAR GRANDE 345gm | G22: 1 | H22: EUFAR | J22: 0 | K22: 46843 | L22: =25945*1.19 -> 30874.55 | M22: 44000 | N22: =G22*L22 -> 30874.55
B23: Retracfar Cloruro de aluminio 7ml | G23: 1 | H23: ramon EUFAR PRODONT AQUILES | J23: 0 | L23: 9685 | M23: 15000 | N23: =G23*L23 -> 9685

Sheet TEMPO NORTE PEDIDO PRODONT
B2: pedi junio 28 | C2: referencias | F2: PEDIDO SUR | G2: PEDIDO NORTE | I2: INVENT SUR mar 21 | J2: INVENT NTE
B3: ACIDO FLUORHIDRICO 3ML (JERINGA) prodont | G3: 5 | H3: PRODONT | J3: 4
B4: ACIDO FLUORHIDRICO 7ML (GOTERO) prodont | G4: 0 | H4: PRODONT | J4: 9
B5: Cemento C-Gross | C5: NO PEDIR | G5: 0 | H5: PRODONT | J5: 0
B6: EUGENOL X 7 ML prodont | C6: PRODONT | G6: 10 | H6: PRODONT | J6: 12
B7: GLUTARALDEHIDO BACTIXIDE PRODONT x 500 cc (YA MEZCLADA) | C7: MEDIO LITRO | D7: BORRAR | G7: 0 | H7: PRODONT | J7: 0
B8: Hemostatico Cloruro de aluminio x 7ml hemodent prodont | G8: 5 | H8: RAMON PRODONT | J8: 15
B9: HIDROXIDO DE CALCIO X 10 gm prodont | D9: actualizar 4297 | G9: 0 | H9: RAMON-PROQUIDENT-PRODONT Aquiles Eufar | J9: 10
B10: HIDROXIDO DE CALCIO X 7gm proquident | G10: 0 | H10: RAMON-PROQUIDENT-PRODONT Aquiles Eufar | J10: 10
B11: HIPOCLORITO AL 1% X 120 ML | G11: 1 | H11: RAMON PRODONT | J11: 1
B12: HIPOCLORITO AL 5 % X 120 ML | C12: PROQUID $3370 // PRODONT $5095 | G12: 30 | H12: PRODONT | J12: 15
B13: Jabon Enzimatico x 120 cc prodont | C13: PROQUIDENT $5280 PRODONT $6993 GARHOX $7735 | G13: 10 | H13: PRODONT | J13: 24
B14: Jabon multienzimatico bactixide 500 ml | D14: BORRAR | G14: 0 | H14: PRODONT | J14: 0
B15: LECHADA DE CALCIO SIDCAL X 500 ML prodont | G15: 0 | H15: PRODONT | J15: 5
B16: MOMIFAR 7ML MOMIFICANTE PULPAR X 7 ML EUFAR | G16: 0 | H16: RAMON PRODONT EUFAR | J16: 30
B17: MOMIFICANTE PULPAR X 7 ML MOMICIDE | G17: 0 | H17: RAMON PRODONT EUFAR
B18: Oxido de zinc 10g | G18: 0 | H18: RAMON PROQUIDENT PRODONT | J18: 10
B19: Pasta Profilactica (tutifruti - fresa) TUBO colapsible prodont | C19: prodont 10144 | G19: 0 | H19: PRODONT | J19: 20
B20: perborato de sodio | G20: 0 | H20: PRODONT | J20: 0
B21: Retracfar Cloruro de aluminio 7ml | G21: 2 | H21: ramon EUFAR PRODONT AQUILES | J21: 0
B22: Topsensy desensibilizante dental 5 ml dentofar | G22: 0 | H22: Prodont | J22: 2
B23: Xilol prodont 15ML | G23: 10 | H23: RAMON PROQUIDENT PRODONT | J23: 7

Sheet TEMPO PEDIDO GUANTES NORTE
B2: NORTE | C2: LATEX | D2: NITRILO | K2: TOTAL NORTE Y SUR | L2: LATEX | M2: NITRILO
D3: AZUL | E3: NEGRO | F3: MORADO | G3: ROSADO | M3: AZUL | N3: NEGRO | O3: MORADO | P3: ROSADO
B4: XS | C4: 46 | D4: 39 | E4: 22 | F4: 10 | G4: 10 | K4: XS | L4: =C4+C10 -> 79 | M4: =D4+D10 -> 69 | N4: =E4+E10 -> 33 | O4: =F4+F10 -> 18 | P4: =G4+G10 -> 39
B5: S | C5: 118 | D5: 37 | E5: 11 | F5: 13 | G5: 14 | K5: S | L5: =C5+C11 -> 159 | M5: =D5+D11 -> 76 | N5: =E5+E11 -> 15 | O5: =F5+F11 -> 31 | P5: =G5+G11 -> 36
B6: M | C6: 16 | D6: 12 | E6: 23 | F6: - | G6: - | K6: M | L6: =C6+C12 -> 65 | M6: =D6+D12 -> 37 | N6: =E6+E12 -> 35
B8: SUR | C8: LATEX | D8: NITRILO | K8: TOTAL | L8: LATEX | M8: NITRILO
D9: AZUL | E9: NEGRO | F9: MORADO | G9: ROSADO
B10: XS | C10: 33 | D10: 30 | E10: 11 | F10: 8 | G10: 29 | K10: XS | L10: =L4 -> 79 | M10: =M4+N4+O4+P4 -> 159
B11: S | C11: 41 | D11: 39 | E11: 4 | F11: 18 | G11: 22 | K11: S | L11: =L5 -> 159 | M11: =M5+N5+O5+P5 -> 158
B12: M | C12: 49 | D12: 25 | E12: 12 | F12: - | G12: - | K12: M | L12: =L6 -> 65 | M12: =M6+N6+O6+P6 -> 72

Sheet tempo norte pedido nuria
A1: pedi junio 28 | B1: referencias | E1: PEDIDO SUR | F1: PEDIDO NORTE | H1: INVENT SUR mar 21 | I1: INVENT NTE
A2: anestesia TOPICA GAROCAINA | F2: 0 | G2: nuria | I2: 0
A3: clorhexidina clorexol 180 ML | F3: 15 | G3: nuria | I3: 6
A4: desinfectantes superficies ORGANICA x 500 ml | F4: 0 | G4: nuria | I4: 8
A5: desinfectantes superficies x 100 ml | F5: 0 | G5: nuria | I5: 18
A6: garhox desinfectantes superficies x 3.850 ml GALON | F6: 0 | G6: nuria | I6: 1
A7: GLUTARALDEHIDO glutarbio x 500 ml organica | B7: MEDIO LITRO | F7: 0 | G7: nuria | I7: 15
A8: Glutaraldehido x 3.850 ml galon organica GRANDE | B8: GALON | C8: AGOTADO | F8: 5 | G8: nuria | I8: 0
A9: Hexitec clorhexidinal clorexol | F9: 15 | G9: nuria | I9: 6
A10: Jabon Enzimatico x 120ml DE ORGANICA | B10: PROQUIDENT $5280 PRODONT $6993 GARHOX $8500 | F10: 0 | G10: NURIA | I10: 23
A11: jabon enzimatico x 500 cc organica | F11: 0 | G11: nuria | I11: 16
A12: Jabon Enzimatico x GALON DE ORGANICA | F12: 1 | G12: nuria | I12: 0

Sheet tempo pedido norte soccidentale
A1: pedi junio 28 | B1: referencias | E1: PEDIDO SUR | F1: PEDIDO NORTE | H1: INVENT SUR mar 21 | I1: INVENT NTE
A2: Aceite LUBRICANTE X200 ML Maquira | F2: 0 | G2: SOCCIDENTALES | I2: 0
A3: acido desmineralizante 37% fosforico MAQUIRA 2.5 | B3: ACIDO | C3: PRECIO MAYO 20 | F3: 0 | G3: RAMON CLAUDIA SOCCIDENTALES | I3: 30
A4: acido fluorhidrico 10% Jeringa 2.5 ml Maquira | F4: 6 | G4: SOCCIDENTALES CLAUDIA | I4: 4
A5: Aclaramiento casero Power bleaching bM4 16 % | F5: 0 | G5: SOCCIDENTALES | I5: 10
A6: Aclaramiento casero Power bleaching bM4 22 % | F6: 0 | G6: SOCCIDENTALES | I6: 0
A7: Adhesivo bond 2.1 4ml maquira | B7: SOCCIDEN $22000 | F7: 0 | G7: SOCCIDENTALES CLAUDIA | I7: 6
A8: Adhesivo bond 2.1 5ml maquira | F8: 0 | G8: SOCCIDENTALES CLAUDIA | I8: 0
A9: Adhesivo bond 2.1 6ml maquira | F9: 0 | G9: SOCCIDENTALES CLAUDIA | I9: 0
A10: Apacal Art x2 jeringas | F10: 0 | G10: SOCCIDENTALES | I10: 0
A11: Barrera Gingival Max Dam Jeringa 2 g Maquira | B11: COMPRE 17600 | C11: PRECIO 20 MAYO | F11: 0 | G11: RAMON SOCCIDENTALES CLAUDIA | I11: 7
A12: base it Cemento base intermedia Spident | F12: 3 | G12: SOCCIDENTALES | I12: 2
A13: cemento fostato de zinc | F13: 0 | G13: SOCCIDENTALES CLAUDIA | I13: 0
A14: cemento resinoso Dual Force 5g maquira | B14: compre $0 | F14: 0 | G14: RAMON SOCCIDENTALES CLAUDIA | I14: 0
A15: cemento temporal TEMP IT FLOW eringa X 2 GM | F15: 0 | G15: RAMON SOCCIDENTALES CLAUDIA | I15: 2
A16: cemento temporal TEMP IT jeringa X 3 GM | F16: 0 | G16: RAMON SOCCIDENTALES CLAUDIA | I16: 0
A17: cemento temporal Applic 2g maquira x 2 jeringas | F17: 0 | G17: RAMON SOCCIDENTALES CLAUDIA | I17: 8
A18: Cemento temporal fluor OBTUR 25 gm | F18: 10 | G18: soccidentales | I18: 5
A19: Cemento Temporal Orafil G x 40gr prevest | F19: 0 | G19: soccidentales | I19: 0
A20: Conos de Gutapercha No 15 caja x 6 | B20: ABRA $ //15,500 // DAZA $ 16,700 //SOCCID $14500 | F20: 0 | G20: ABRAHAM DAZA SOCCIDENTALES | I20: 15
A21: Conos de Gutapercha No 20 caja x 6 | B21: ABRA $ //15,500 // DAZA $ 16,700 //SOCCID $14500 | F21: 0 | G21: ABRAHAM DAZA SOCCIDENTALES | I21: 12
A22: Conos de Gutapercha No 25 caja x 6 | B22: ABRA $ //15,500 // DAZA $ 16,700 //SOCCID $14500 | F22: 3 | G22: ABRAHAM DAZA SOCCIDENTALES | I22: 1
A23: Conos de Gutapercha No 30 caja x 6 | B23: ABRA $ //15,500 // DAZA $ 16,700 //SOCCID $14500 | F23: 0 | G23: ABRAHAM DAZA SOCCIDENTALES | I23: 4
A24: Conos de Gutapercha No 35 caja x 6 | B24: ABRA $ //15,500 // DAZA $ 16,700 //SOCCID $14500 | F24: 0 | G24: ABRAHAM DAZA SOCCIDENTALES | I24: 5
A25: Conos de Gutapercha No 40 caja x 6 | B25: ABRA $ //15,500 // DAZA $ 16,700 //SOCCID $14500 | F25: 0 | G25: ABRAHAM DAZA SOCCIDENTALES | I25: 8
A26: Conos de Gutapercha 15-40 1ra serie | B26: ABRA $ //15,500 // DAZA $ 16,700 //SOCCID $14500 | F26: 0 | G26: ABRAHAM DAZA SOCCIDENTALES | I26: 12
A27: Conos de Gutapercha 45-80 2da serie | B27: ABRA $ //15,500 // DAZA $ 16,700 //SOCCID $14500 | F27: 0 | G27: ABRAHAM DAZA SOCCIDENTALES | I27: 9
A28: Endo ice spray 200ML | F28: 0 | G28: RAMON SOCCIDENTALES ultradental | I28: 7
A29: ESTEMP NE spident tembond 2jeringas x 10gr | F29: 0 | G29: SOCCIDENTALES | I29: 0
A30: fix RESINA ortodoncia 2.5ml | B30: ortho $35000 | F30: 0 | G30: SOCCIDENTALES CLAUDIA ortho prof | I30: 12
A31: GELATAM HEMOSPON CAJA X 40U | F31: 0 | G31: soccidentales | I31: 4
A32: GELATAM HEMOSPON tira X 10 | F32: 0 | G32: soccidentales | I32: 0
A33: GELATAM HEMOSPON unidad | F33: 0 | G33: soccidentales | I33: 0
A34: hidroxcal hidroxido de calcio FOTOCURADO 2gm | F34: 0 | G34: SOCCIDENTALES CLAUDIA | I34: 0
A35: Hilo retractor 00 no impregnado maquira | F35: 0 | G35: SOCCIDENTALES CLAUDIA | I35: 0
A36: Hilo retractor 000 no impregnado maquira | F36: 0 | G36: SOCCIDENTALES CLAUDIA | I36: 0
A37: hydcal hidcal dycal cemento hidroxido calcio pasta pasta | F37: 0 | G37: SOCCIDENTALES | I37: 4
A38: ionomero cementante IONGLASS C | B38: COMPRE 49900 | F38: 0 | G38: SOCCIDENTALES | I38: 0
A39: Marcador plastico caucho instrumental autoclavable | B39: IMPORT $7122 BRASIL SOCCI | F39: 0 | G39: SOCCIDENTALES CLAUDIA | I39: 0
A40: matriz universal kit x 25 unidades | F40: 0 | G40: soccidentales abraham importado | I40: 0
A41: matriz universal kit x 50 unidades | F41: 0 | G41: soccidentales abraham importado | I41: 0
A42: ORATEMP Resina Bisacrilica X67GR A1 | F42: 1 | G42: SOCCIDENTALES | I42: 0
A43: ORATEMP Resina Bisacrilica X67GR BLEACH | F43: 1 | G43: SOCCIDENTALES | I43: 0
A44: PASTA DIAMANTADA UNIVERSAL MAQUIRA | F44: 0 | G44: SOCCIDENTALES CLAUDIA | I44: 6
A45: Pasta profilactica shine 90g tutty maquira | F45: 0 | G45: SOCCIDENTALES | I45: 0
A46: PISTOLA LUXATEM - VYSALIS | B46: soccidentales | F46: 0 | G46: ABRAHAM - IMPORTADO - julvident soccidentales | I46: 2
A47: Pistola para dispensar silicona | F47: 0 | G47: importada soccidentales
A48: Puntas de Papel 1ra SERIE | B48: DAZA $19278 RAMON $18903 abraham $14530 SOCCID #13800 | F48: 4 | G48: ABRAHAM RAMON Daza SOCCIDENTALES | I48: 9
A49: Puntas de Papel 2da SERIE | B49: DAZA $19278 RAMON $18903 abraham $14530 SOCCID #13800 | F49: 0 | G49: ABRAHAM RAMON Daza SOCCIDENTALES | I49: 12
A50: Resina Applic Dentina A1 | G50: SOCCIDENTALES | I50: 0
A51: Resina Applic Dentina A2 | G51: SOCCIDENTALES | I51: 0
A52: Resina Applic Dentina A3 | G52: SOCCIDENTALES | I52: 0
A53: Resina Applic Dentina A3.5 | G53: SOCCIDENTALES | I53: 0
A54: Resina Applic Esmalte A1 | G54: SOCCIDENTALES | I54: 0
A55: Resina Applic Esmalte A2 | G55: SOCCIDENTALES | I55: 0
A56: Resina Applic Esmalte A3 | G56: SOCCIDENTALES | I56: 0
A57: Resina Applic Esmalte A3.5 | G57: SOCCIDENTALES | I57: 0
A58: Resina fluida Applic FLow Maquira 2 Gr A3 | B58: ramon $29.000 COMPRE socci 22880 ORTHO PROF $20.000 | F58: 0 | G58: RAMON SOCCIDENTALES CLAUDIA | I58: 3
A59: Resina fluida applic FLow Maquira 2 Gr A1 | B59: ramon $29.000 COMPRE socci 22880 ORTHO PROF $20.000 | F59: 0 | G59: RAMON SOCCIDENTALES CLAUDIA | I59: 25
A60: Resina fluida applic FLow Maquira 2 Gr A2 | B60: ramon $29.000 COMPRE socci 22880 ORTHO PROF $20.000 | C60: PRECIO 20 MAYO | F60: 5 | G60: RAMON SOCCIDENTALES CLAUDIA | I60: 2
A61: Resina Opallis Flow Fluida A1 FGM | B61: antioq $30000 soccid $ 28700 plus $28800 | F61: 0 | G61: FGM SOCCIDENTAL
A62: Resina Opallis Flow Fluida A2 FGM | B62: antioq $30000 soccid $ 28700 plus $28800 | G62: FGM SOCCIDENTAL
A63: Resina Opus Flow APS BULK FILL A1 | B63: compre promo $59500 | G63: FGM masdental soccidentales
A64: Resina Opus Flow APS BULK FILL A2 | B64: compre promo $59501 | C64: PRECIO 20 MAYO | G64: FGM masdental soccidentales
A65: sellante de fosas y fisuras Maxseal Maquira | G65: SOCCIDENTALES CLAUDIA | I65: 0
A66: Silano Maquira 5 ML | F66: 8 | G66: RAMON SOCCIDENTALES CLAUDIA | I66: 0
A67: VIOSEAL SPIDENT ADSEAL | F67: 1 | G67: SOCCIDENTALES | I67: 0

Sheet PAGO RECIBOS 2025
A1: PAGAR ANTES DE: | B1: Clase de Servicio | C1: de que casa | D1: Valor Aprox | E1: Referencia de pago | F1: Agt - 2024 | G1: Sep - 2024 | H1: 45566 | I1: 45597 | J1: 45627 | K1: 45658 | L1: 45690 | M1: 45719 | N1: 45751 | O1: 45782 | P1: 45814 | Q1: 45845 | R1: 45877 | S1: 45909 | T1: 45940 | U1: 45962 | V1: 45993
A2: 1 | B2: ARRENDO UNIDENTAL SUR | C2: UNIDENTAL SUR | D2: 2000000 | G2: SEP 4 $2.000.000 | H2: OCT 04 $2,000,000 | I2: NOV 07 $2,000,000 | J2: DIC 06 $2,000,000 | K2: ENE 10 $2,000,000 | L2: FEB 03 $2,000,000 | M2: MARZO 04 $2,000,000 | N2: ABRIL 04 $2,000,000 | O2: MAYO 05 $2,000,000 | P2: JUNIO 06 $2,167,000
A3: 1 | B3: BANCOOMEVA ASOCIADO | C3: BANCOOMEVA | D3: 4000000 | F3: AGOSTO 1 $2.348.713 | G3: SEP 05 $2,536,275 | H3: OCT 04 $4,700,470 | I3: NOV 05 $2,504,652 | J3: DIC 5 $2,592,022 | K3: ENE 08 $5,401,000 | L3: FEB 05 $1,719,970 | M3: MARZO 05 $4,842,704 | N3: ABRIL 10 $3,290,000 | O3: MAYO 03 $3,252,764 | P3: JUNIO 06 $5,770,000 pago jose
A4: 2 | B4: JOSE DAVID | D4: 600000 | F4: 300000 | G4: 800000 | H4: 700
A5: 2 | B5: GABRIELA | D5: 250000 | F5: 200000 | G5: 400000 | H5: 500
A6: 3 | B6: CELULAR RAUL | C6: MOVISTAR | D6: 45000 | F6: Agt 09 $37579 | G6: sept 6 $37,674 | H6: OCT 07 $37,580 | I6: NOV 05 $36,550 | J6: DIC 5 $36,489 | K6: ENE 08 $36,489 | L6: FEB 05 $37,628 | M6: MARZO 04 $36,489 | N6: ABRIL 02 $36,489 | O6: MAYO 03 $36,489 | P6: JUNIO 06 $36,489
A7: 4 | B7: EMCALI | C7: MORICHAL | D7: 300000 | E7: 1610503 | F7: AGT 10 $679.012 | G7: sept 10 $656.025 | H7: OCT 07 $701,032 | I7: Nov 06 $621,873 | J7: DIC 09 $760,562 | K7: ENE 13 $610,037 | L7: FEB 05 $763,799 | M7: MARZO 07 $638,699 | N7: ABRIL 07 $524,481 | O7: MAYO 08 $533,268 | P7: JUNIO 09 $389,320
A8: 4 | B8: MOVISTAR | C8: GRANADA | D8: 90000 | E8: 605 705 10081 | F8: AGT 10 $56.703 | G8: SEPT 9 $86.000 | H8: OCT 07 $80,395 | I8: NOV 06 $52,121 | J8: DIC 09 $53,093 | K8: ENE 13 $82,457 | L8: FEB 05 $119,965 | M8: MARZO 07 $97,985 | N8: ABRIL 07 $131,636 | O8: MAYO 08 $99,375 | P8: JUNIO 09 $128,849
A9: 5 | B9: EPS JENNIFER MADRID | C9: Mariana gestores 077-000264-71 | D9: 401300 | F9: - | G9: - | H9: - | I9: - | J9: DIC 14 $367,800 | K9: ENE 13 $367,800 | L9: FEB 07 $367,800 | M9: MARZO 08 $401,300 | N9: ABRIL 07 $401,300 | O9: MAYO 08 $401300 | P9: JUNIO 09 $401,300
A10: 6 | B10: RAFA EPS | C10: Mariana gestores 077-000264-71 | D10: 381300 | E10: 8833 68 1550 | F10: AGT 10 $348.000 | G10: sep 10 $348,000 | H10: OCT 08 $348,000 | I10: NOV 07 $348,000 | J10: DIC 14 $348,000 | K10: ENE 13 $348,000 | L10: FEB 07 $348,000 | M10: MARZO 08 $381,300 | N10: ABRIL 07 $381,300 | O10: MAYO 08 $381300 | P10: JUNIO 09 $381,300
A11: 7 | B11: ADMINISTRACION LA CEIBA - Av villas | C11: VALLE LILI 3202 cll 54 #83c2 38 | D11: 172000 | E11: 213002942 | F11: Agt 10 $151.800 | G11: Sep 10 $151,800 | H11: OCT 07 $151,800 | I11: NOV 08 $151,800 | J11: DIC 09 $151,800 | K11: ENE 09 $151,800 | L11: FEB 10 $151,800 | M11: MARZO 08 $151,800 | N11: ABRIL 07 $232,600 | O11: MAYO 09 $172,000 | P11: JUNIO 09 $172,000
A12: 7 | B12: ADMINISTRACION AV Villas | C12: URBANIZ CERROS Cll 1 #56-70 | D12: 530100 | F12: pago 10 Agt 2024 $460750 | G12: Sep 10 $460,750 | H12: OCT 08 $460,750 | I12: NOV 08 $460,750 | J12: DIC 09 $460,750 | K12: ENE 09 $460,750 | L12: FEB 10 $460,750 | M12: MARZO 08 $460,750 | N12: ABRIL 08 $740,100 | O12: MAYO 09 $530,100 | P12: JUNIO 06 $530,100
A13: 10 | B13: EPS - Simple | C13: RAUL | D13: 405800 | E13: 883 368 1550 | F13: Agoto 12 $370.500 | G13: Sep 10 $370,500 | H13: OCT 08 $370,500 | I13: NOV 26 $371,900 | J13: DIC 16 $370,500 | K13: ENE 14 $370,500 | L13: ENE 16 $405,800 | M13: MARZO 11 $405,800 | N13: ABRIL 08 $405,800 | O13: MAYO 12 $405,800 | P13: JUNIO 09 $405,800
A14: 15 | B14: GASES DE OCCIDENTE | C14: VALLE LILI | D14: 25000 | E14: 1719297 | F14: - | G14: - | H14: - | I14: - | J14: - | K14: - | L14: - | M14: - | N14: - | O14: - | P14: - | Q14: - | R14: - | S14: - | T14: - | U14: - | V14: -
A15: 15 | B15: GASES DE OCCIDENTE | C15: CERROS | D15: 30000 | E15: 641483 | F15: agosto 20 $42.667 | G15: Sep 19 $45,035 | H15: OCT 11 $51,814 | I15: NOV 14 $60,672 | J15: DIC 16 $69,307 | K15: ENE 14 $57,431 | L15: FEB 17 $62,329 | M15: MAR 18 $56,134 | N15: ABRIL 16 $44,317 | O15: MAYO 20 $49,951 | P15: JUNIO 17 $45,171
A16: 17 | B16: CLARO HOGAR | C16: CERROS | D16: 120000 | E16: 7328582 | F16: agosto 20 $92.139 | G16: Sep 19 $99,619 | H16: OCT 11 $99,619 | I16: NOV 14 $106,499 | J16: DIC 17 $106,499 | K16: ENE 16 $106,499 | L16: FEB 20 $106,499 | M16: MARZO 18 $109,499 | N16: ABRIL 23 $106,499 | O16: MAYO 20 $129,198 | P16: junio 17 dice que ya esta cancelada
A17: 17 | B17: MOVISTAR | C17: UNIDENTAL SUR | D17: 100000 | E17: 6074357576 | F17: AGT $50,000 | G17: Sep 19 $156,024 | H17: OCT 17 $137,177 | I17: NOV 14 $137,238 | J17: DIC 17 $89,205 | K17: ENE 16 $89,205 | L17: FEB 20 $88,456 | M17: MARZO 18 $90,539 | N17: ABRIL 16 $89,205 | O17: MAYO 20 $89,205 | P17: JUNIO 17 $150,519
A18: 18 | B18: CREDITO CONSUMO COLPATRIA | C18: RAUL CREDITO | D18: $16,860,000 | E18: 407419259669 | F18: - | G18: - | H18: - | I18: NOV 25 $1,491,000 | J18: DIC 18 $1,589,200 | K18: ENE 16 $1,585,000 | L18: FEB 20 $7,085,000 | M18: MARZO 15 $1,569,183
A19: 20 | B19: EMCALI | C19: GRANADA | D19: 400000 | E19: 121686 | F19: agosto 20 $681.934 | G19: Sep 19 $660,131 | H19: OCT 11 $698,265 | I19: NOV 26 $694,042 | J19: DIC 19 $685,338 | K19: ENE 20 $737,809 | L19: FEB 20 $671,716 | M19: MAR 22 $723,661 | N19: ABRIL 16 $1,078,336 | O19: MAYO 20 $882,890 | P19: JUNIO 17 $804,005
A20: 24 | B20: EMCALI | C20: CERROS | D20: 350000 | E20: 920903 | F20: 20/8/2024 $523.071 | G20: Sep 19 $463,478 | H20: OCT 23 $484,659 | I20: NOV 26 $474,695 | J20: DIC 19 $565,182 | K20: ENE 29 $551,351 | L20: FEB 28 $523,068 | M20: MAR 25 $437,904 | N20: ABRIL 26 $443,214 | O20: MAYO 23 $450,792 | P20: JUNIO 27 $362,547
A21: 24 | B21: EMCALI | C21: UNIDENTAL SUR | D21: 178000 | E21: 913397 | F21: AGT 28 $200,012 | G21: Sep 19 $437,971 | H21: OCT 23 $524,655 | I21: NOV 26 $422,377 | J21: DIC 19 $414,937 | K21: ENE 24 $376,195 | L21: FEB 25 $390,530 | M21: MAR 25 $479,891 | N21: ABRIL 30 $527,345 | O21: MAYO 23 $457,607 | P21: JUNIO 27 $425,119
A22: 25 | B22: GASES DE OCCIDENTE | C22: MORICHAL | D22: 25000 | E22: 280280 | F22: agosto 20 $42.931 | G22: Sep 19 $42,909 | H22: OCT 11 $48,722 | I22: NOV 14 $55,098 | J22: DIC 16 $42,854 | K22: Se pago x medio de un concurso q gano en ENERO el recibo se pago por valor x $29,985 | L22: FEB 28 $24,098 | M22: MAR 25 $26,359 | N22: ABRIL 26 $38,954 | O22: MAYO 23 $22,669 | P22: JUNIO 27 $31,117
A23: 25 | B23: EMCALI | C23: VALLE LILI | D23: 400000 | E23: 46729024 | F23: - | G23: - | H23: - | I23: - | J23: - | K23: - | L23: - | M23: - | N23: - | O23: - | P23: - | Q23: - | R23: - | S23: - | T23: - | U23: - | V23: -
A24: 30 | B24: GASES DE OCCIDENTE | C24: GRANADA | D24: 50000 | E24: 2024805 | G24: Sep 19 pago 2 meses $24,925 | H24: OCT 11 $6,108 | I24: NOV 14 $9,200 | J24: DIC 16 $12,069 | K24: ENE 25 $9,229 | L24: FEB 28 $12,489 | M24: MAR 25 $12,374 | N24: ABRIL 26 $12,064 | O24: MAYO 23 $15,634 | P24: JUNIO 27 $15,738
E26: Total | K26: 13341552 | L26: 15339697 | M26: 12922371 | N26: 10483640 | O26: =SUM(O2:O24) -> 0 | P26: =SUM(P2:P24) -> 0

Sheet HOJA DE PAGOS NTE Y SUR
A1: PROVEDOR | B1: Valor | C1: Vence | D1: factura | F1: observaciones | I1: espacio para raul | J1: PAGADA
A2: BIOSALUD | B2: 992800 | C2: 45764 | D2: RM | E2: NORTE | G2: GABRIELA PAGAR EN EFECTIVO
A3: BIODENTALES | B3: 1540857 | C3: 45793 | D3: 29904 | E3: NORTE | F3: ok pague mayo 13 | G3: PAGUE 2 VECES
A4: NURIA | B4: =2736649-1766700 -> 969949 | C4: 45799 | D4: Varios | E4: SUR | F4: se abono $1,766,700 saldo $935 | G4: SE ABONO MAYO 26
A5: PLUSS DENT | B5: 1708280 | C5: 45862 | D5: 44673 | E5: SUR | I5: OK CORROBORADA
A6: IMPORQUIRURGICA | B6: 2085000 | C6: 45802 | D6: 5273 | E6: NORTE | G6: YA LA PAGUE
A7: PREMIUM | B7: =866300-16000 -> 850300 | C7: 45807 | D7: RM | E7: NORTE | F7: REVISAR VALOR ANTES DE PAGAR | G7: GABRIELA PAGAR EN EFECTIVO | I7: ok corroborada
A8: PERICO | B8: 2845986 | C8: 45811 | D8: 141992 | E8: NORTE | G8: YA PAGUE TRANSFER JN 25
A9: PREMIUM | B9: 1067000 | C9: 45813 | D9: RM | E9: SUR | G9: JEN PAGAR | I9: ok corroborada
A10: ESTERIPAC | B10: 2125340 | C10: 45814 | D10: 4108 | E10: NORTE | G10: YA PAGUE TRANSFER JN 25
A11: PERICO | B11: 4981230 | C11: 45817 | D11: 142063 | E11: SUR | F11: Jun 25 abono $1,581,300 saldo $3,400 | G11: JEN PAGAR O ABONAR
A12: PERICO REMI JERINGAS | B12: 517200 | C12: 45817 | D12: RM | E12: SUR | G12: JENIFER DEJELA PENDIENTE PRIMERO PAGUE LA OTRA
A13: AQUILES | B13: 758381 | C13: 45819 | D13: 2953 | E13: NORTE | G13: Gabriela pago efectivo junio 26
A14: DAZA | B14: 3950000 | C14: 45821 | D14: 110960 | E14: NORTE | G14: GABRIELA PAGAR CON TDC | I14: OK CORROBORADA
A15: DAZA | B15: 199920 | C15: 45822 | D15: 110970 | E15: NORTE | I15: OK CORROBORADA
A16: PRODONT | B16: 1172169 | C16: 45824 | D16: 7166 | E16: NORTE | G16: YA PAGUE TRANSFER JN 25
A17: PLUSS DENT | B17: 578000 | C17: 45827 | D17: 43721 | E17: NORTE | G17: GABRIELA PAGAR CON TDC
A18: PLUSS DENT | B18: 1985941 | C18: 45827 | D18: 43733 | E18: NORTE | G18: GABRIELA PAGAR CON TDC
A19: DORA | B19: 1200000 | C19: 45828 | E19: NORTE | G19: YA SE PAGO
A20: PREMIUM | B20: 375000 | C20: 45828 | D20: RM | E20: SUR
A21: NURIA | B21: 720392 | C21: 45830 | D21: RM | E21: NORTE | G21: GABRIELA REVISAR Y PAGAR EN EFECTIVO
A22: LA MUELA | B22: 519374 | C22: 45834 | D22: 88363 | E22: NORTE
A23: BIOSALUD | B23: 494900 | C23: 45835 | D23: RM | E23: NORTE
A24: ORTHO PROFESSIONAL | B24: 2579977 | C24: 45835 | D24: 798471 | E24: NORTE
A25: PLUSS DENT | B25: 1333000 | C25: 45835 | D25: 43991 | E25: NORTE
A26: LA MUELA | B26: 529275 | C26: 45835 | D26: 88426 | E26: SUR
A27: ORTHO PROFESSIONAL | B27: 77969 | C27: 45837 | D27: 198570 | E27: SUR
A28: ORTHO PROFESSIONAL | B28: 540689 | C28: 45838 | D28: 198605 | E28: NORTE
A29: PLUSS DENT | B29: 5000000 | C29: 45838 | D29: 44091 | E29: NORTE
A30: RAMON | B30: 955454 | C30: 45838 | D30: 3961 | E30: NORTE
A31: LA MUELA | B31: 760200 | C31: 45841 | D31: 88700 | E31: NORTE
A32: LA MUELA | B32: 380100 | C32: 45841 | D32: 88712 | E32: NORTE
A33: LA MUELA | B33: 380100 | C33: 45841 | D33: 88713 | E33: NORTE
A34: BIOSALUD | B34: 270000 | C34: 45842 | D34: RM | E34: NORTE
A35: PLUSS DENT | B35: 169200 | C35: 45842 | D35: 44171 | E35: NORTE
A36: PLUSS DENT | B36: 169200 | C36: 45842 | D36: 44168 | E36: NORTE
A37: PLUSS DENT | B37: 169200 | C37: 45842 | D37: 44161 | E37: NORTE
A38: PLUSS DENT | B38: 376040 | C38: 45844 | D38: 44259 | E38: NORTE
A39: RAMON | B39: 609200 | C39: 45845 | D39: 4087 | E39: NORTE
A40: PLUSS DENT | B40: 5271600 | C40: 45847 | D40: 44297 | E40: NORTE
A41: DAZA | B41: 487480 | C41: 45854 | D41: 111264 | E41: NORTE
A42: ORTHO PROFESSIONAL | B42: 134004 | C42: 45856 | D42: 199408 | E42: NORTE
A43: PLUSS DENT | B43: 1393219 | C43: 45856 | D43: 44547 | E43: NORTE
A44: LA MUELA | B44: 7939471 | C44: 45857 | D44: 90053 | E44: NORTE
A45: BIODENTALES | B45: -1540857 | C45: JULIO | F45: TENGO ESTE VALOR A MI FAVOR | G45: PAGUE 2 VECES

Sheet AGOTADO UNIDENTAL 
B1: referencias | C1: PROVEEDOR | D1: PRECIO COMPRA | F1: SEDE
A2: abre bocas Umbrella | C2: Pluss Dent GAB VEL | D2: =9288*1.19 -> 11052.72
A3: Abreboca manual gancho DOBLE EXTREMO NEGRO | C3: IMPORTADA | D3: 8746
A4: Abreboca manual gancho DOBLE EXTREMO TRANSPARENTE | C4: IMPORTADA | D4: =1962*2 -> 3924
A5: ANESTESIA TOPICA ROXICAINA SPRAY | C5: AQUILES RAMON | D5: 68000
A6: ANESTESIA TOPICA ROXICAINA JALEA | C6: AQUILES RAMON | D6: 23000
A7: Abreboca manual gancho PEQUEÑO | C7: IMPORTADA | D7: 1712
A8: Abreboca AZUL Y ROJO AMARILLO | C8: ELVER LOZANO BOGOTA | D8: 4500
A9: abreboca Con retractor adulto | C9: UPEGUI | D9: 16900
A10: abreboca Con retractor PEDIATRICO | C10: UPEGUI | D10: 16900
A11: Abreboca manual gancho GRANDE | C11: IMPORTADA | D11: 1426.9789
A12: Abreboca sencillo adulto | B12: OXXI $ 11067 NISSI $7556 | C12: OXXI NISSI | D12: =9300*1.19/5 -> 2213.4
A13: Abreboca sencillo niño | B13: OXXI $ 11067 NISSI $7557 | C13: OXXI NISSI | D13: =9300*1.19/5 -> 2213.4
A14: abreboca sin retractor | C14: UPEGUI | D14: 16900
A15: abrebocas aclaramiento tipo optragate | C15: IMPORTADA | D15: 4602
A16: Accufilm Papel de articular aqua film x 280 tiras | C16: La muela miguel | D16: =65000/200 -> 325
A17: Accufilm Papel de articular CIRENE aqua film x 280 tiras | C17: La muela miguel | D17: 65000
A18: Aceite 3 en 1 | C18: CENTRO HOYOSTOOL | D18: =3200*1.19 -> 3808
A19: aceite lubricante - pieza de mano Dental handpiece 300ml | C19: dentmark | D19: 28000
A20: aceite lubricante - pieza de mano Dental handpiece 550ml | C20: dentmark | D20: 35000
A21: aceite lubricante - pieza de mano PANASPRAY PLUS NSK 480ML | B21: NSK | C21: LA MUELA | D21: =121849*1.19 -> 145000.31
A22: aceite lubricante - pieza de mano WYH 400ML | B22: euro $96250 | C22: MASDENTAL EURODENT | D22: 116000
A23: Aceite lubricante Bendechk 300ml | C23: makrodent dentmart | D23: 35000
A24: aceite lubricante de piezas digixpray 240ml | C24: muela | D24: 24850
A25: Aceite lubricante en Spray 200 ml- KAVO | C25: Pluss Dent GAB VEL | D25: 49504
A26: aceite lubricante pequeño - pieza de mano 50 ml | C26: RAMON | D26: 7400
A27: Aceite lubricante Quiruspray 200 cc - pieza de mano | B27: ramon $29.500 aquiles $24.871 | C27: RAMON AQUILES | D27: =24789.92*1.19 -> 29500.005
A28: Aceite lubricante Universal en Spray 250 ml- Adensys | C28: Pluss Dent GAB VEL | D28: =50500*1.19 -> 60095
A29: Aceite LUBRICANTE X200 ML Maquira | C29: SOCCIDENTALES | D29: =26000*1.19 -> 30940
A30: Aceite super lubry 50ml | C30: AQUILES | D30: 7500
A31: acetato lamina rosada 0.6 | C31: RAMON | D31: 1800
A32: acetato rigido ACE | C32: RAMON | D32: 6400
A33: acido clorhidrico removedor de manchas opalustre FGM whiteness RM 6% | B33: antioq $95200 soccid $ 80,206 plus $79968 | C33: FGM soccident | D33: =100000*0.8*1.19 -> 95200
A34: acido desmineralizante fosforico MAQUIRA 2.5 | B34: ACIDO | C34: RAMON CLAUDIA SOCCIDENTALES | D34: =(11654*1.19)/3 -> 4622.7533
A35: Acido desmineralizante 2.5 coltene | B35: ACIDO | C35: Ultradental | D35: 10868
A36: acido desmineralizante 2.5 Densell 12g 35% | B36: ACIDO | C36: La muela - ramon | D36: 12000
A37: Acido desmineralizante 35% ultradent 1.2ml | B37: ACIDO | C37: Gabriel Vel pluss | D37: 13272
A38: acido desmineralizante angelus 3 grs | B38: ACIDO | C38: CLAUDIA | D38: 2000
A39: Acido desmineralizante FGM condac 12.5 ML | B39: ACIDO promo antoq $24375 SOCCIDEN 20825 plus20000 | C39: FGM soccident | D39: =32500*0.8 -> 26000
A40: Acido Desmineralizante proquident 10ML jumbo | B40: ACIDO | C40: PROQUIDENT | D40: 14173
A41: Acido Desmineralizante Select H V ETCH 5ML Bisco | B41: promo $32400 | C41: JULVIDENT bisco | D41: 54000
A42: Acido desmineralizante SUPER ETCH SDI 12 gm | B42: ACIDO | C42: ABRAHAM | D42: 33800
A43: Acido desmineralizante ultra ETCH 30ml ultradent | B43: ACIDO | C43: Gabriel Vel pluss | D43: 150579
A44: Acido Desmineralizante Zafira 10 ml | B44: ACIDO | C44: New Stetic | D44: 12400
A45: acido fluorhidrico 10% Jeringa 2.5 ml Angelus | C45: CLAUDIA | D45: 37140
A46: acido fluorhidrico 10% Jeringa 2.5 ml Maquira | C46: SOCCIDENTALES CLAUDIA | D46: =21315*1.19 -> 25364.85
A47: ACIDO FLUORHIDRICO 3ML (JERINGA) prodont | C47: PRODONT | D47: =23294*1.19 -> 27719.86
A48: acido fluorhidrico 5% 3 g BM4 | C48: CLAUDIA | D48: 10320
A49: acido fluorhidrico 5% porcelana jeringa 2.5 ml FGM | B49: SOCCID $24514 plus $25600 | C49: FGM soccident | D49: =40000*0.8*1.19 -> 38080
A50: ACIDO FLUORHIDRICO 7ML (GOTERO) prodont | C50: PRODONT | D50: =25757*1.19 -> 30650.83
A51: acido fluorhidrico 9.6% Jeringa 2 g Eufar | B51: Aquiles $32000 ramon $32000 EUFAR $29354 | C51: AQUILES RAMON GABRIEL VELASQUEZ Eufar | D51: =24667*1.19 -> 29353.73
A52: Acido fluorhidrico grabador para porcelana ultradent | B52: pluss $24804 | C52: Gabriel Vel pluss | D52: 30257
A53: Acido Fluorhidrico porcelain etch 9,5% Bisco | B53: promo $70800 | C53: JULVIDENT bisco | D53: 118000
A54: aclaramiento casero Clariant 16% Angelus | C54: ABRAHAM | D54: 19710
A55: Aclaramiento casero OPALECENSE x 2 JERINGAS | C55: CLAUDIA pluss dent | D55: 45031
A56: Aclaramiento casero Opalecense Go caja x 10 | B56: pluss $211.000 promo 2x 159 gabriel velasq promo x 2 155 | C56: CLAUDIA pluss dent | D56: 211194
A57: Aclaramiento casero Opalecense Go x unidad | C57: CLAUDIA pluss dent | D57: 25000
A58: Aclaramiento casero Polanight | C58: CLAUDIA abraham | D58: 26900
A59: Aclaramiento casero Potenza 16% | C59: New Stetic | D59: 13953
A60: Aclaramiento casero Potenza 22% | C60: New Stetic | D60: 15153
A61: Aclaramiento casero Power bleaching bM4 16 % | C61: SOCCIDENTALES | D61: =8070*1.19 -> 9603.3
A62: Aclaramiento casero Power bleaching bM4 22 % | C62: SOCCIDENTALES | D62: =8070*1.19 -> 9603.3
A63: Aclaramiento casero Whiteness perfect FGM 16% | B63: antioq $16800 promo $15000 soccid $14500 plus $15232 | C63: FGM soccident | D63: 16800
A64: Aclaramiento casero Whiteness perfect FGM 22% | B64: antioq $16800 promo $15000 soccid $14500 plus $15232 | C64: FGM soccident | D64: 16800
A65: Aclaramiento casero withegold | C65: DORA ramon | D65: 11700
A66: Aclaramiento consultorio AZUL HP BLUE FGM 35% JERINGA | B66: SOCCID 38714 plus $37334 | C66: FGM soccident | D66: =245000*0.8*1.19/6 -> 38873.333
A67: Aclaramiento consultorio AZUL HP BLUE FGM 35% MINI KIT | B67: antioq $76160 soccid $66800 | C67: FGM soccident | D67: =80000*0.8*1.19 -> 76160
A68: aclaramiento consultorio Clariant 35% Angelus | C68: ABRAHAM | D68: 36130
A69: Aclaramiento consultorio FGM 35% ROJO HP | B69: antioq $200000 promo $196350 soccid $202.300 | C69: FGM soccident | D69: =250000*0.8 -> 200000
A70: Aclaramiento consultorio FGM 35% ROJO HP Mini kit | C70: FGM soccident | D70: 89000
A71: Aclaramiento consultorio FGM 35% VERDE HP AUTOMIX JERINGA CONSULTORIO | C71: FGM soccident | D71: 190000
A72: Aclaramiento consultorio FGM 35% VERDE HP MAXX | B72: antioq $233240 soccid $180000 plus $208012 | C72: FGM soccident | D72: 200000
A73: Aclaramiento consultorio FGM 35% VERDE MINI KIT HP MAXX | B73: antioq $117096 soccid $66800 | C73: FGM soccident | D73: =123000*0.8*1.19 -> 117096
A74: Aclaramiento consultorio OPALECENSE BOOTS + barrera gingival OPALDAM | C74: CLAUDIA pluss dent | D74: 115250
A75: Aclaramiento consultorio OPALECENSE BOOTS 40% | B75: compre $90200 | C75: CLAUDIA pluss dent | D75: 97429
A76: Aclaramiento consultorio Pola Office + LISTO 1PCTE | C76: abraham | D76: 141000
A77: Aclaramiento consultorio Pola Office 3 PCTE S POLVO Y LIQUIDO | C77: abraham | D77: 292000
A78: Aclaramiento consultorio pola office bulk kit | C78: abraham | D78: 287900
A79: Aclaramiento consultorio Potenza 38% (1,3+0,4) | C79: New stetic | D79: 42000
A80: Aclaramiento consultorio Potenza 38% 1 jeringa+ Barrera 1g+ 1 frasco Neutralizador | C80: New stetic | D80: 65450
A81: aclaramiento HP BLUE 6 JERINGAS
A82: ACONDICIONADOR DE TEJIDOS COE CONFORT LIQUIDO | B82: GC | C82: LA MUELA - DORA - RAMON - masdental | D82: 80808
A83: ACONDICIONADOR DE TEJIDOS COE CONFORT POLVO | B83: GC | C83: LA MUELA - DORA - RAMON - masdental | D83: 97275
A84: ACONDICIONADOR DE TEJIDOS COE CONFORT Y COE SOFT X PORCION | B84: GC | C84: La Muela | D84: =130000/15 -> 8666.6667
A85: ACONDICIONADOR DE TEJIDOS COE SOFT LIQUIDO | B85: GC | C85: LA MUELA - DORA - RAMON - masdental | D85: 80808
A86: ACONDICIONADOR DE TEJIDOS COE SOFT POLVO | B86: GC | C86: LA MUELA - DORA - RAMON - masdental | D86: 87241
A87: ACOPLE CORDEN PARA PIEZAS UNIDAD | C87: larry alfredo | D87: 25000
A88: Acrilico auto 125 g JB | C88: New Stetic | D88: 18683
A89: Acrilico auto 125 g TRANSPARENTE | C89: New Stetic | D89: 18683
A90: Acrilico auto 125 g VR1 | C90: New Stetic | D90: 18683
A91: Acrilico auto 60 g A 3.5 | C91: New Stetic | D91: 18683
A92: Acrilico auto 60 g A0 | C92: New Stetic | D92: 18683
A93: Acrilico Auto 60 g A1 | C93: New Stetic | D93: 18683
A94: Acrilico auto 60 g A2 | C94: New Stetic | D94: 18683 | E94: AGOTADO | F94: NORTE
A95: Acrilico auto 60 g A3 | C95: New Stetic | D95: 18683
A96: Acrilico Auto 60 g B2 | C96: New Stetic | D96: 18683
A97: Acrilico auto 60 g JB | C97: New Stetic | D97: 9639
A98: Acrilico auto 60 g Transparente | C98: New Stetic | D98: 9639
A99: Acrilico auto 60 g VR1 | C99: New Stetic | D99: 9639
A100: Acrilico auto 60 g VRX | C100: New Stetic | D100: 9639
...

Sheet TEMPO Pedido prodont sur 
A1: SUR PRODONT MAYO 19 | B1: PEDIDO SUR | C1: INVTAR SUR
A2: ACIDO FLUORHIDRICO 3ML (JERINGA) prodont | B2: 2 | C2: 5
A3: ACIDO FLUORHIDRICO 7ML (GOTERO) prodont | B3: 4 | C3: 1
A4: Cemento C-Gross | B4: 0 | C4: 0
A5: EUGENOL X 7 ML prodont | B5: 0 | C5: 9
A6: GLUTARALDEHIDO BACTIXIDE PRODONT x 500 cc (YA MEZCLADA) | B6: 0 | C6: 0
A7: Hemostatico Cloruro de aluminio x 7ml hemodent prodont | B7: 10 | C7: 7
A8: HIDROXIDO DE CALCIO X 10 gm prodont | B8: 0 | C8: 22
A9: HIDROXIDO DE CALCIO X 7gm proquident | B9: 0 | C9: 9
A10: HIPOCLORITO AL 1% X 120 ML | B10: 6 | C10: 1
A11: HIPOCLORITO AL 5 % X 120 ML | B11: 20 | C11: 6
A12: Jabon Enzimatico x 120 cc prodont | B12: 15 | C12: 5
A13: Jabon multienzimatico bactixide 500 ml | B13: 0 | C13: 15
... A22: Xilol prodont 15ML | B22: 10 | C22: 7

Sheet PEDIDO FGM nte y sur
A1: estoy cotizando con socciden fgm y plus | B1: PEDIDO SUR | C1: PEDIDO NORTE | D1: INVENT SUR | E1: INVENT NTE | F1: PRECIO COMPRA | H1: PLUS | I1: SOCCIDENTAL | J1: NORTE SOCCID | K1: NORTE PLUSS
A2: acido clorhidrico removedor de manchas opalustre FGM whiteness RM 6% | B2: 0 | C2: 0 | D2: 1 | E2: 1 | F2: =100000*0.8*1.19 -> 95200 | G2: =B2+C2 -> 0
A3: Acido desmineralizante FGM condac 12.5 ML | B3: 0 | C3: 0 | D3: 21 | E3: 9 | F3: =32500*0.8 -> 26000 | G3: =B3+C3 -> 0
A4: acido fluorhidrico 5% porcelana jeringa 2.5 ml FGM | B4: 0 | C4: 0 | D4: 2 | E4: 13 | F4: =40000*0.8*1.19 -> 38080 | G4: =B4+C4 -> 0
A5: Aclaramiento casero Whiteness perfect FGM 16% | B5: 0 | C5: 0 | D5: 15 | E5: 20 | F5: 16800 | G5: =B5+C5 -> 0
A6: Aclaramiento casero Whiteness perfect FGM 22% | B6: 0 | C6: 0 | D6: 59 | E6: 18 | F6: 16800 | G6: =B6+C6 -> 0
A7: Aclaramiento consultorio AZUL HP BLUE FGM 35% JERINGA | B7: 0 | C7: 1 | D7: 5 | E7: 1 | F7: =245000*0.8*1.19/6 -> 38873.333 | G7: =B7+C7 -> 1 | J7: OK
A8: Aclaramiento consultorio AZUL HP BLUE FGM 35% MINI KIT | B8: 0 | C8: 0 | D8: 0 | E8: 0 | F8: =80000*0.8*1.19 -> 76160 | G8: =B8+C8 -> 0
A9: Aclaramiento consultorio FGM 35% ROJO HP | B9: 0 | C9: 0 | D9: 5 | E9: 18 | F9: =250000*0.8 -> 200000 | G9: =B9+C9 -> 0
A10: Aclaramiento consultorio FGM 35% ROJO HP Mini kit | B10: 0 | C10: 0 | D10: 0 | E10: 1 | F10: 89000 | G10: =B10+C10 -> 0
A11: Aclaramiento consultorio FGM 35% VERDE HP AUTOMIX JERINGA CONSULTORIO | B11: 0 | C11: 0 | D11: 0 | E11: 0 | F11: 190000 | G11: =B11+C11 -> 0
A12: Aclaramiento consultorio FGM 35% VERDE HP MAXX | B12: 0 | C12: 0 | D12: 4 | E12: 9 | F12: 200000 | G12: =B12+C12 -> 0
A13: Aclaramiento consultorio FGM 35% VERDE MINI KIT HP MAXX | B13: 0 | C13: 0 | D13: 2 | E13: 0 | F13: =123000*0.8*1.19 -> 117096 | G13: =B13+C13 -> 0
A14: Adhesivo AMBAR FGM 4 ML naranja | B14: 0 | C14: 0 | D14: 0 | E14: 0 | F14: 58000 | G14: =B14+C14 -> 0
A15: Adhesivo AMBAR MORADO FGM 6ML APS | B15: 0 | C15: 0 | D15: 4 | E15: 14 | F15: =95000*0.8 -> 76000 | G15: =B15+C15 -> 0
A16: Adhesivo AMBAR ROJO FGM 5 ML APS Universal | B16: 5 | C16: 5 | D16: 0 | E16: 0 | F16: =125000*0.8 -> 100000 | G16: =B16+C16 -> 10 | J16: OK | K16: -
A17: ALLCEM CORE A1 PEAR CORPO DUPLO FGM | B17: 5 | C17: 5 | D17: 0 | E17: 1 | F17: =100000 -> 100000 | G17: =B17+C17 -> 10 | J17: LLEGARON 4 | K17: -
A18: ALLCEM CORE A2 PEAR CORPO DUPLO FGM | B18: 5 | C18: 5 | D18: 0 | E18: 2 | F18: =100000 -> 100000 | G18: =B18+C18 -> 10 | J18: LLEGARON 4 | K18: -
A19: ALLCEM CORE VENEER APS OW FGM | B19: 0 | C19: 0 | D19: 0 | E19: 0 | F19: =200000*0.8 -> 160000 | G19: =B19+C19 -> 0
A20: ALLCEM CORE VENEER APS TRANS FGM | B20: 0 | C20: 0 | D20: 0 | E20: 0 | F20: =200000*0.8 -> 160000 | G20: =B20+C20 -> 0
A21: Barrera Gingival Top Dam 2 g FGM | B21: 0 | C21: 0 | D21: 4 | E21: 22 | F21: 19200 | G21: =B21+C21 -> 0
A22: DESENSIBILIZANTE KF 2% JGA X 2.5 ML FGM | B22: 0 | C22: 0 | D22: 2 | E22: 2 | F22: =29000*0.8*1.19 -> 27608 | G22: =B22+C22 -> 0
A23: Disco diamond flex fieltro x 24 undidades | B23: 0 | C23: 0 | D23: 1 | E23: 1 | F23: =65000*0.8*1.19 -> 61880 | G23: =B23+C23 -> 0
A24: LAMPARA CURINGPEN CAJA BLANCA eighteeth | B24: 1 | C24: 1 | D24: 0 | E24: 0 | F24: 743000 | G24: =B24+C24 -> 2 | J24: NO LLEGO | K24: -
A25: LAMPARA CURINGPEN-E CAJA AZUL eighteeth | B25: 0 | C25: 0 | D25: 1 | E25: 1 | F25: 384000 | G25: =B25+C25 -> 0
A26: orthocem resina ortodoncia FGM | B26: 0 | C26: 0 | D26: 2 | E26: 5 | F26: =85000*0.8 -> 68000 | G26: =B26+C26 -> 0
A27: Pasta Diamantada FGM diamond excel | B27: 0 | C27: 0 | D27: 3 | E27: 5 | F27: =32000*0.8*1.19 -> 30464 | G27: =B27+C27 -> 0
A28: Primma art 7 gr FGM - visacril - visalis Color A1 | B28: 2 | C28: 3 | D28: 2 | E28: 2 | F28: =90000*0.8 -> 72000 | G28: =B28+C28 -> 5 | J28: OK | K28: LLEGARON 3
A29: Primma art 7 gr FGM - visacril - visalis Color A2 | B29: 2 | C29: 5 | D29: 0 | E29: 0 | F29: =90000*0.8 -> 72000 | G29: =B29+C29 -> 7 | J29: LLEGARON 3 | K29: LLEGARON 3
A30: Primma art 7 gr FGM - visacril - visalis Color-Bleach | B30: 3 | C30: 5 | D30: 0 | E30: 0 | F30: 72000 | G30: =B30+C30 -> 8 | J30: LLEGARON 4 | K30: LLEGARON 4
A31: Primma art 75gr FGM - visacril - visalis Color-Bleach | B31: 1 | C31: 1 | D31: 0 | E31: 0 | F31: =229500*0.8 -> 183600 | G31: =B31+C31 -> 2 | J31: LLEGARON 2
A32: PUNTAS PARA PRIMMA ART AZULES CORTAS INDIVIDUAL | B32: 0 | C32: 0 | D32: 0 | E32: 0 | F32: 3000 | G32: =B32+C32 -> 0
A33: PUNTAS PARA PRIMMA ART AZULES CORTAS PAQUETE X 20 | C33: 0 | D33: 0 | E33: 0 | F33: 47600 | G33: =B33+C33 -> 0
A34: Resina LLIS FGM D - A1 dentina | B34: 0 | C34: 0 | D34: 0 | F34: 28800 | G34: =B34+C34 -> 0
A35: Resina LLIS FGM D - A2 dentina | B35: 0 | C35: 0 | D35: 3 | F35: 28800 | G35: =B35+C35 -> 0
A36: Resina LLIS FGM D - A3 dentina | B36: 0 | C36: 0 | D36: 2 | F36: 28800 | G36: =B36+C36 -> 0
A37: Resina LLIS FGM D - A3.5 dentina | B37: 0 | C37: 0 | D37: 3 | F37: 28800 | G37: =B37+C37 -> 0
A38: Resina LLIS FGM E - A1 esmalte | B38: 0 | C38: 0 | D38: 2 | F38: 28800 | G38: =B38+C38 -> 0
A39: Resina LLIS FGM E - A2 esmalte | B39: 0 | C39: 0 | D39: 3 | F39: 28800 | G39: =B39+C39 -> 0
A40: Resina LLIS FGM E - A3 esmalte | B40: 0 | C40: 0 | D40: 2 | F40: 28800 | G40: =B40+C40 -> 0
A41: Resina LLIS FGM E - A3.5 esmalte | B41: 0 | C41: 0 | D41: 0 | F41: 28800 | G41: =B41+C41 -> 0
A42: Resina Opallis Flow Fluida A1 FGM | B42: 0 | C42: 0 | D42: 5 | E42: 5 | F42: =38000*0.8 -> 30400 | G42: =B42+C42 -> 0
A43: Resina Opallis Flow Fluida A2 FGM | B43: 0 | C43: 0 | D43: 1 | E43: 6 | F43: =38000*0.8 -> 30400 | G43: =B43+C43 -> 0
A44: Resina Opus Flow APS BULK FILL A1 | B44: 0 | C44: 0 | D44: 1 | E44: 1 | F44: =90000*0.8 -> 72000 | G44: =B44+C44 -> 0
A45: Resina Opus Flow APS BULK FILL A2 | B45: 0 | C45: 1 | D45: 1 | E45: 0 | F45: =90000*0.8 -> 72000 | G45: =B45+C45 -> 1 | J45: OK
A46: Resina Vitra UNIQUE APS 2gm | B46: 2 | C46: 3 | D46: 2 | E46: 1 | F46: =90000*0.8 -> 72000 | G46: =B46+C46 -> 5 | J46: OK
A47: Resina Vitra UNIQUE APS 4gm | B47: 0 | C47: 0 | D47: 1 | E47: 1 | F47: 116000 | G47: =B47+C47 -> 0
A48: Silano Prosil FGM | B48: 0 | C48: 6 | D48: 0 | E48: 0 | F48: =40000*0.8 -> 32000 | G48: =B48+C48 -> 6 | J48: OK
A49: whiteness super endo FGM diente no vital jeringa x 3ml | B49: 0 | C49: 0 | D49: 1 | E49: 1 | F49: =100000*0.8*1.19 -> 95200 | G49: =B49+C49 -> 0

Sheet INSTRUMENTAL
A1: Perico | B1: nelly | C1: FERCHO | D1: CRIST | E1: PEDIDO SUR | F1: PEDIDO NORTE | H1: ubicacion | J1: QX / 23 | K1: INVENT SUR Abril 30 | L1: INVENT NORTE ABRIL 23 | M1: PERICO dcto 12% + iva | N1: NELLY dcto 15% + iva | O1: CRISTIAN | P1: AQUILES FERCHO | Q1: a quien pedir) | S1: PRECIO DEL PEDIDO | T1: MALETERO | U1: costo | V1: VR TOTAL | W1: PRECIO DE VENTA | X1: %
E2: 0 | F2: 0 | G2: ABREBOCA MOLT ADULTO | H2: 1 | K2: 0 | L2: 0 | M2: =24000*0.88*1.19 -> 25132.8 | Q2: PERICO | R2: =24000*0.88*1.19 -> 25132.8 | S2: =F2*O2 -> 0 | U2: =M2*T2 -> 0 | V2: =W2*T2 -> 0 | W2: 45000 | X2: =(W2/M2)-1 -> 0.79048892
E3: 0 | F3: 0 | G3: ABREBOCA MOLT PEDIATRICO | H3: 1 | K3: 0 | L3: 0 | M3: =24000*0.88*1.19 -> 25132.8 | Q3: PERICO | R3: =24000*0.88*1.19 -> 25132.8 | S3: =F3*O3 -> 0 | U3: =M3*T3 -> 0 | V3: =W3*T3 -> 0 | W3: 45000 | X3: =(W3/M3)-1 -> 0.79048892
E4: 6 | F4: 0 | G4: ALICATE 2 PICOS # 139 | H4: 33 | K4: 8 | L4: 35 | M4: =18700*0.88*1.19 -> 19582.64 | N4: =+25227*0.85*1.19 -> 25517.11 | P4: =18000*0.85*1.19 -> 18207 | Q4: AQUILES | R4: =18000*0.85*1.19 -> 18207 | S4: =P4*F4 -> 0 | T4: 30000 | U4: =C4*P4 -> 0 | V4: =W4*T4 -> 1020000000 | W4: 34000 | X4: =(W4/M4)-1 -> 0.73623168
E5: 0 | F5: 0 | G5: ALICATE 3 PICOS # 200 | H5: 33 | K5: 11 | L5: 19 | M5: =18700*0.88*1.19 -> 19582.64 | N5: =+25227*0.85*1.19 -> 25517.11 | P5: =18000*0.85*1.19 -> 18207 | Q5: AQUILES | R5: =18000*0.85*1.19 -> 18207 | S5: =P5*F5 -> 0 | U5: =C5*P5 -> 0 | V5: =W5*T5 -> 0 | W5: 34000 | X5: =(W5/M5)-1 -> 0.73623168
E6: 6 | F6: 10 | G6: ALICATE PINZA QUITA BANDAS # 34 | H6: 32 | I6: PRECIO PERICO $20980 | K6: 9 | L6: 16 | M6: =19000*0.88*1.19 -> 19896.8 | N6: =25227*0.85*1.19 -> 25517.11 | Q6: PERICO | R6: =19000*0.88*1.19 -> 19896.8 | S6: =F6*M6 -> 198968 | U6: =M6*T6 -> 0 | V6: =W6*T6 -> 0 | W6: 34000 | X6: =(W6/M6)-1 -> 0.7088175
E7: 0 | F7: 0 | G7: Aplicador de ligaduras llaves y cadenetas Morelly | H7: 49 | K7: 0 | L7: 4 | W7: 28000 | X7: =(W7/M7)-1 -> #DIV/0!
E8: 10 | F8: 5 | G8: APLICADOR DICAL | H8: 1 | K8: 3 | L8: 4 | M8: =3700*0.88*1.19 -> 3874.64 | N8: =3507*0.85*1.19 -> 3547.3305 | P8: =3800*0.85*1.19 -> 3843.7 | Q8: AQUILES | R8: =3800*0.85*1.19 -> 3843.7 | S8: =P8*F8 -> 19218.5 | U8: =C8*P8 -> 0 | V8: =W8*T8 -> 0 | W8: 7000 | X8: =(W8/M8)-1 -> 0.80661945
E9: 0 | F9: 0 | G9: arco de Young De ADULTO OJO GRANDE instrumental | H9: 2 | K9: 17 | L9: 32 | M9: =7400*0.88*1.19 -> 7749.28 | N9: N / V | P9: =5000*0.85*1.19 -> 5057.5 | Q9: AQUILES | R9: =5000*0.85*1.19 -> 5057.5 | S9: =P9*F9 -> 0 | U9: =C9*P9 -> 0 | V9: =W9*T9 -> 0 | W9: 14000 | X9: =(W9/M9)-1 -> 0.80661945
E10: 0 | F10: 0 | G10: arco de Young pediatrico Pño instrumental | H10: 2 | K10: 16 | L10: 17 | M10: =7400*0.88*1.19 -> 7749.28 | N10: N / V | P10: =5000*0.85*1.19 -> 5057.5 | Q10: AQUILES | R10: =5000*0.85*1.19 -> 5057.5 | S10: =P10*F10 -> 0 | U10: =C10*P10 -> 0 | V10: =W10*T10 -> 0 | W10: 14000 | X10: =(W10/M10)-1 -> 0.80661945
E11: 0 | F11: 0 | G11: Asentador de bandas 300 X instrumental (PARECE ELEVADOR) bandpusher | H11: 3 | K11: 31 | L11: 36 | M11: =9000*0.88*1.19 -> 9424.8 | N11: =13740*0.85*1.19 -> 13898.01 | O11: 5000 | Q11: CRISTIAN | R11: 5000 | S11: =F11*M11 -> 0 | U11: =T11*M11 -> 0 | V11: =W11*T11 -> 0 | W11: 30000 | X11: =(W11/M11)-1 -> 2.1830914
E12: 0 | F12: 10 | G12: Asentador de bandas color | H12: 3 | K12: 18 | L12: 27 | M12: =5500*0.88*1.19 -> 5759.6 | Q12: PERICO | R12: =5500*0.88*1.19 -> 5759.6 | S12: =F12*O12 -> 0 | U12: =M12*T12 -> 0 | V12: =W12*T12 -> 0 | W12: 24000 | X12: =(W12/M12)-1 -> 3.166956
E13: 0 | F13: 0 | G13: Asentador de Bandas MORELI | H13: 3 | K13: 1 | L13: 2 | W13: 32000
E14: 0 | F14: 10 | G14: BISTURI DE KIRKLAN INSTRUMENTAL | H14: 4 | K14: 7 | L14: 12 | M14: =5000*0.88*1.19 -> 5236 | Q14: PERICO | R14: =5000*0.88*1.19 -> 5236 | S14: =F14*M14 -> 52360 | T14: 8000 | U14: =T14*M14 -> 41888000 | V14: =W14*T14 -> 80000000 | W14: 10000 | X14: =(W14/M14)-1 -> 0.90985485
E15: 0 | F15: 6 | G15: BISTURI DE ORBAN INSTRUMENTAL | H15: 4 | K15: 8 | L15: 14 | M15: =4800*0.88*1.19 -> 5026.56 | N15: =7139*0.85*1.19 -> 7221.0985 | Q15: PERICO | R15: =4800*0.88*1.19 -> 5026.56 | S15: =F15*M15 -> 30159.36 | T15: 8000 | U15: =M15*T15 -> 40212480 | V15: =W15*T15 -> 80000000 | W15: 10000 | X15: =(W15/M15)-1 -> 0.98943214
E16: 7 | F16: 0 | G16: Bruñidor 21 B | H16: 44 | K16: 7 | L16: 29 | M16: =5000*0.88*1.19 -> 5236 | P16: =5000*0.85*1.19 -> 5057.5 | Q16: AQUILES | R16: =5000*0.85*1.19 -> 5057.5 | S16: =F16*O16 -> 0 | U16: =C16*P16 -> 0 | V16: =W16*T16 -> 0 | W16: 8000 | X16: =(W16/M16)-1 -> 0.52788388
E17: 0 | F17: 0 | G17: Bruñidor de Bola y orqueta | H17: 44 | K17: 10 | L17: 15 | M17: =5000*0.88*1.19 -> 5236 | P17: =5000*0.85*1.19 -> 5057.5 | Q17: AQUILES | R17: =5000*0.85*1.19 -> 5057.5 | S17: =F17*O17 -> 0 | U17: =C17*P17 -> 0 | V17: =W17*T17 -> 0 | W17: 8000 | X17: =(W17/M17)-1 -> 0.52788388
D18: 20 | E18: 0 | G18: CADENA PORTA BABERO | H18: - | K18: 6 | O18: 2500 | Q18: CRISTIAN | R18: 2500 | U18: =P18*T18 -> 0 | V18: =W18*T18 -> 0 | W18: 6000 | X18: =(W18/O18)-1 -> 1.4
E19: 15 | F19: 0 | G19: Calibrador de cera instrumental | H19: 5 | I19: precio crstian $10000 | K19: 7 | L19: 22 | M19: =10000*1.19*0.88 -> 10472 | N19: =16786*1.19*0.85 -> 16979.039 | O19: 8000 | P19: =10000*0.85*1.19 -> 10115 | Q19: CRISTIAN | R19: 8000 | S19: =F19*M19 -> 0 | U19: =C19*P19 -> 0 | V19: =W19*T19 -> 0 | W19: 24000 | X19: =(W19/M19)-1 -> 1.2918258
E20: 0 | F20: 0 | G20: calibrador de metal instrumental | H20: 5 | K20: 25 | L20: 31 | M20: =11000*1.19*0.88 -> 11519.2 | N20: =16786*0.85*1.19 -> 16979.039 | O20: 8000 | P20: =10000*0.85*1.19 -> 10115 | Q20: CRISTIAN | R20: 8000 | S20: =F20*M20 -> 0 | U20: =C20*P20 -> 0 | V20: =W20*T20 -> 0 | W20: 24000 | X20: =(W20/M20)-1 -> 1.083478
E21: 0 | F21: 0 | G21: calibrador pie de rey | H21: 5 | K21: 3 | L21: 8 | Q21: CRISTIAN | W21: 24000
E22: 20 | F22: 0 | G22: Castro Viejo instrumental (OJO PINZA QUE TIENE GANCHO EN EL MEDIO) | H22: 6 | K22: 0 | L22: 10 | M22: =24900*0.88*1.19 -> 26075.28 | N22: =30945*0.85*1.19 -> 31300.868 | Q22: CRISTIAN | R22: 26071 | S22: =F22*O22 -> 0 | T22: 35000 | U22: =P22*T22 -> 0 | V22: =W22*T22 -> 1470000000 | W22: 42000 | X22: =(W22/M22)-1 -> 0.61072096
E23: 0 | F23: 0 | G23: Castro Viejo instrumental tijera | H23: 6 | K23: 3 | L23: 4 | M23: =18000*0.88*1.19 -> 18849.6 | N23: 25601 | O23: 19000 | Q23: CRISTIAN | R23: 19000 | S23: =F23*O23 -> 0 | T23: 35000 | U23: =P23*T23 -> 0 | V23: =W23*T23 -> 1470000000 | W23: 42000 | X23: =(W23/M23)-1 -> 1.228164
E24: 0 | F24: 0 | G24: CK 4 | H24: 6 | K24: 11 | L24: 22 | M24: =5000*0.88*1.19 -> 5236 | N24: =6267*0.85*1.19 -> 6339.0705 | P24: =5000*0.85*1.19 -> 5057.5 | Q24: AQUILES | R24: =5000*0.85*1.19 -> 5057.5 | S24: =P24*F24 -> 0 | T24: 8000 | U24: =C24*P24 -> 0 | V24: =W24*T24 -> 80000000 | W24: 10000 | X24: =(W24/M24)-1 -> 0.90985485
E25: 0 | F25: 0 | G25: CK 6 | H25: 6 | K25: 10 | L25: 11 | M25: =5000*0.88*1.19 -> 5236 | O25: 3000 | P25: =5000*0.85*1.19 -> 5057.5 | Q25: CRISTIAN | R25: 3000 | S25: =F25*O25 -> 0 | U25: =C25*P25 -> 0 | V25: =W25*T25 -> 0 | W25: 10000 | X25: =(W25/M25)-1 -> 0.90985485
E26: 0 | F26: 0 | G26: CONDENSADOR DE AMALGAMA | H26: 45 | K26: 13 | L26: 20 | M26: =4800*0.88*1.19 -> 5026.56 | Q26: PERICO | R26: =5000*0.88*1.19 -> 5236 | S26: =F26*O26 -> 0 | U26: =T26*M26 -> 0 | V26: =W26*T26 -> 0 | W26: 10000 | X26: =(W26/M26)-1 -> 0.98943214
E27: 4 | F27: 0 | G27: Corte de Ligadura ortodoncia | H27: 47 | K27: 2 | L27: 39 | M27: =22000*0.88*1.19 -> 23038.4 | N27: =25227*0.85*1.19 -> 25517.11 | Q27: PERICO | R27: =22000*0.88*1.19 -> 23038.4 | S27: =F27*O27 -> 0 | T27: 35000 | W27: 40000 | X27: =(W27/M27)-1 -> 0.73623168
E28: 0 | F28: 0 | G28: Corte de Ligadura ortodoncia angelus | H28: 47 | K28: 8 | L28: 7 | W28: 80000 | X28: =(W28/M28)-1 -> #DIV/0!
E29: 4 | F29: 5 | G29: Corte Distal ORTODONCIA | H29: 47 | K29: 3 | L29: 10 | M29: =29700*0.88*1.19 -> 31101.84 | Q29: PERICO | R29: =29700*0.88*1.19 -> 31101.84 | S29: =F29*O29 -> 0 | T29: 42000 | W29: 48000 | X29: =(W29/M29)-1 -> 0.54331705
E30: 10 | F30: 10 | G30: CUBETAS PARA IMPRESIÓN ADULTOS | H30: - | K30: 7 | L30: 12 | M30: =58500*0.88*1.19 -> 61261.2 | N30: 64867 | P30: =58000*0.85*1.19 -> 58667 | Q30: AQUILES | R30: =58000*0.85*1.19 -> 58667 | S30: =P30*F30 -> 586670 | T30: 74000 | U30: =C30*P30 -> 0 | W30: 95000 | X30: =(W30/M30)-1 -> 0.55073684
E31: 0 | F31: 0 | G31: CUBETAS PARA IMPRESIÓN pediatrico | H31: - | K31: 17 | L31: 20 | M31: =58500*0.88*1.19 -> 61261.2 | N31: 64867 | P31: =58000*0.85*1.19 -> 58667 | Q31: AQUILES | R31: =58000*0.85*1.19 -> 58667 | S31: =P31*F31 -> 0 | U31: =C31*P31 -> 0 | V31: =W31*T31 -> 0 | W31: 95000 | X31: =(W31/M31)-1 -> 0.55073684
E32: 0 | F32: 20 | G32: Cucharilla #17 Puppies | H32: 7 | K32: 21 | L32: 2 | M32: =4800*0.88*1.19 -> 5026.56 | Q32: PERICO | R32: =4800*0.88*1.19 -> 5026.56 | S32: =F32*O32 -> 0 | W32: 9000 | X32: =(W32/M32)-1 -> 0.79048892
E33: 0 | F33: 0 | G33: Cucharilla basico instrumental | H33: 26 | I33: BASICO | J33: 98 | K33: 22 | L33: 98 | M33: =4800*0.88*1.19 -> 5026.56 | N33: =5494*0.85*1.19 -> 5557.181 | P33: =5000*0.85*1.19 -> 5057.5 | Q33: AQUILES | R33: =5000*0.85*1.19 -> 5057.5 | S33: =P33*F33 -> 0 | U33: =C33*P33 -> 0 | V33: =W33*T33 -> 0 | W33: 9000 | X33: =(W33/M33)-1 -> 0.79048892
E34: 0 | F34: 0 | G34: CUCHILLO PROTESIS GRANDE | H34: 7 | K34: 20 | L34: 98 | M34: =7000*0.88*1.19 -> 7330.4 | N34: 3724 | O34: 4000 | P34: =6500*0.85*1.19 -> 6574.75 | Q34: CRISTIAN | R34: 4000 | S34: =F34*O34 -> 0 | T34: 10000 | U34: =C34*P34 -> 0 | V34: =W34*T34 -> 130000000 | W34: 13000 | X34: =(W34/M34)-1 -> 0.77343665
E35: 0 | F35: 0 | G35: Cureta 11/12 instrumental Mc Call | H35: 9 | I35: precio cristian $4000 | K35: 0 | L35: 0 | M35: =5000*1.19*0.88 -> 5236 | N35: =6043*0.85*1.19 -> 6112.4945 | Q35: PERICO | R35: =5000*1.19*0.88 -> 5236 | S35: =F35*M35 -> 0 | U35: =M35*T35 -> 0 | V35: =W35*T35 -> 0 | W35: 9000 | X35: =(W35/M35)-1 -> 0.71886937
E36: 2 | F36: 5 | G36: Cureta 13/14 instrumental Mc Call | H36: 9 | K36: 3 | L36: 0 | M36: =5000*1.19*0.88 -> 5236 | N36: =6043*0.85*1.19 -> 6112.4945 | P36: =5000*0.85*1.19 -> 5057.5 | Q36: AQUILES | R36: =5000*0.85*1.19 -> 5057.5 | S36: =P36*F36 -> 25287.5 | U36: =C36*P36 -> 0 | V36: =W36*T36 -> 0 | W36: 9000 | X36: =(W36/M36)-1 -> 0.71886937
E37: 0 | F37: 0 | G37: Cureta 15/16 instrumental Mc Call | H37: 9 | K37: 2 | L37: 5 | M37: =5000*1.19*0.88 -> 5236 | N37: =6043*0.85*1.19 -> 6112.4945 | Q37: PERICO | R37: =5000*1.19*0.88 -> 5236 | S37: =F37*M37 -> 0 | U37: =P37*T37 -> 0 | V37: =W37*T37 -> 0 | W37: 9000 | X37: =(W37/M37)-1 -> 0.71886937
E38: 2 | F38: 0 | G38: Cureta 17/18 instrumental Mc Call | H38: 9 | K38: 3 | L38: 11 | M38: =5000*1.19*0.88 -> 5236 | N38: =6043*0.85*1.19 -> 6112.4945 | P38: =5000*0.85*1.19 -> 5057.5 | Q38: AQUILES | R38: =5000*0.85*1.19 -> 5057.5 | S38: =P38*F38 -> 0 | U38: =C38*P38 -> 0 | V38: =W38*T38 -> 0 | W38: 9000 | X38: =(W38/M38)-1 -> 0.71886937
D39: 12 | E39: 12 | G39: cureta de Lucas #85 | H39: 7 | I39: precio cristian 5600 | J39: Q | K39: 13 | L39: 10 | M39: =4800*1.19*0.88 -> 5026.56 | N39: =6043*0.85*1.19 -> 6112.4945 | O39: 3300 | P39: =5000*0.85*1.19 -> 5057.5 | Q39: CRISTIAN | R39: 3300 | S39: =F39*O39 -> 0 | U39: =C39*P39 -> 0 | V39: =W39*T39 -> 0 | W39: 9000 | X39: =(W39/M39)-1 -> 0.79048892
D40: 4 | E40: 0 | G40: CURETA Gracey 1/2 Instrumental | H40: 8 | K40: 4 | L40: 4 | M40: =5000*1.19*0.88 -> 5236 | N40: =6043*0.85*1.19 -> 6112.4945 | O40: 3700 | Q40: CRISTIAN | R40: 3700 | S40: =F40*O40 -> 0 | U40: =P40*T40 -> 0 | V40: =W40*T40 -> 0 | W40: 9000 | X40: =(W40/M40)-1 -> 0.71886937
E41: 2 | F41: 0 | G41: CURETA Gracey 11/12 Instrumental | H41: 8 | K41: 3 | L41: 49 | M41: =5000*1.19*0.88 -> 5236 | N41: =6043*0.85*1.19 -> 6112.4945 | O41: 3700 | P41: =5000*0.85*1.19 -> 5057.5 | Q41: CRISTIAN | R41: 3700 | S41: =F41*O41 -> 0 | U41: =C41*P41 -> 0 | V41: =W41*T41 -> 0 | W41: 9000 | X41: =(W41/M41)-1 -> 0.71886937
E42: 0 | F42: 0 | G42: CURETA Gracey 13/14 Instrumental | H42: 8 | K42: 4 | L42: 7 | M42: =5000*1.19*0.88 -> 5236 | N42: =6043*0.85*1.19 -> 6112.4945 | O42: 3700 | P42: =5000*0.85*1.19 -> 5057.5 | Q42: CRISTIAN | R42: 3700 | S42: =F42*O42 -> 0 | U42: =C42*P42 -> 0 | V42: =W42*T42 -> 0 | W42: 9000 | X42: =(W42/M42)-1 -> 0.71886937
E43: 0 | F43: 5 | G43: CURETA Gracey 15/16 Instrumental | H43: 8 | K43: 0 | L43: 0 | M43: =5000*1.19*0.88 -> 5236 | N43: =6043*0.85*1.19 -> 6112.4945 | Q43: PERICO | R43: =5000*1.19*0.88 -> 5236 | S43: =F43*M43 -> 26180 | U43: =M43*T43 -> 0 | V43: =W43*T43 -> 0 | W43: 9000 | X43: =(W43/M43)-1 -> 0.71886937
E44: 0 | F44: 0 | G44: CURETA Gracey 17/18 Instrumental | H44: 8 | K44: 2 | L44: 6 | M44: =5000*1.19*0.88 -> 5236 | N44: =6043*0.85*1.19 -> 6112.4945 | O44: 3700 | P44: =5000*0.85*1.19 -> 5057.5 | Q44: CRISTIAN | R44: 3700 | S44: =F44*O44 -> 0 | U44: =C44*P44 -> 0 | V44: =W44*T44 -> 0 | W44: 9000 | X44: =(W44/M44)-1 -> 0.71886937
D45: 5 | E45: 0 | G45: CURETA Gracey 3/4 Instrumental | H45: 8 | K45: 4 | L45: 0 | M45: =5000*1.19*0.88 -> 5236 | N45: =6043*0.85*1.19 -> 6112.4945 | O45: 3700 | P45: =5000*0.85*1.19 -> 5057.5 | Q45: CRISTIAN | R45: 3700 | S45: =F45*O45 -> 0 | U45: =C45*P45 -> 0 | V45: =W45*T45 -> 0 | W45: 9000 | X45: =(W45/M45)-1 -> 0.71886937
D46: 5 | E46: 0 | G46: CURETA Gracey 5/6 Instrumental | H46: 8 | K46: 5 | L46: 0 | M46: =5000*1.19*0.88 -> 5236 | N46: =6043*0.85*1.19 -> 6112.4945 | O46: 3700 | P46: =5000*0.85*1.19 -> 5057.5 | Q46: CRISTIAN | R46: 3700 | S46: =F46*O46 -> 0 | U46: =C46*P46 -> 0 | V46: =W46*T46 -> 0 | W46: 9000 | X46: =(W46/M46)-1 -> 0.71886937
E47: 2 | F47: 0 | G47: CURETA Gracey 7/8 Instrumental | H47: 8 | K47: 3 | L47: 10 | M47: =5000*1.19*0.88 -> 5236 | N47: =6043*0.85*1.19 -> 6112.4945 | O47: 3700 | P47: =5000*0.85*1.19 -> 5057.5 | Q47: CRISTIAN | R47: 3700 | S47: =F47*O47 -> 0 | U47: =C47*P47 -> 0 | V47: =W47*T47 -> 0 | W47: 9000 | X47: =(W47/M47)-1 -> 0.71886937
E48: 0 | F48: 0 | G48: CURETA Gracey 9/10 Instrumental | H48: 8 | K48: 5 | L48: 8 | M48: =5000*1.19*0.88 -> 5236 | N48: =6043*0.85*1.19 -> 6112.4945 | O48: 3700 | P48: =5000*0.85*1.19 -> 5057.5 | Q48: CRISTIAN | R48: 3700 | S48: =F48*O48 -> 0 | U48: =C48*P48 -> 0 | V48: =W48*T48 -> 0 | W48: 9000 | X48: =(W48/M48)-1 -> 0.71886937
E49: 0 | F49: 0 | G49: elevador Apical derecho 303 instrumental | H49: 11 | J49: Q | K49: 24 | L49: 55 | M49: =12500*1.19*0.88 -> 13090 | N49: =13740*0.85*1.19 -> 13898.01 | P49: =13000*0.85*1.19 -> 13149.5 | Q49: AQUILES | R49: =13000*0.85*1.19 -> 13149.5 | S49: =P49*F49 -> 0 | T49: 18000 | U49: =C49*P49 -> 0 | V49: =W49*T49 -> 432000000 | W49: 24000 | X49: =(W49/M49)-1 -> 0.83346066
E50: 6 | F50: 0 | G50: elevador Apical Izquierdo 302 instrumental | H50: 11 | J50: Q | K50: 18 | L50: 25 | M50: =12500*1.19*0.88 -> 13090 | N50: =13740*0.85*1.19 -> 13898.01 | P50: =13000*0.85*1.19 -> 13149.5 | Q50: AQUILES | R50: =13000*0.85*1.19 -> 13149.5 | S50: =P50*F50 -> 0 | T50: 18000 | U50: =C50*P50 -> 0 | V50: =W50*T50 -> 432000000 | W50: 24000 | X50: =(W50/M50)-1 -> 0.83346066
D51: 5 | E51: 5 | F51: 0 | G51: elevador bandera derecha 1R instrumental | H51: 10 | J51: Q | K51: 16 | L51: 26 | M51: =12500*1.19*0.88 -> 13090 | N51: =13740*0.85*1.19 -> 13898.01 | P51: =13000*0.85*1.19 -> 13149.5 | Q51: AQUILES | R51: =13000*0.85*1.19 -> 13149.5 | S51: =F51*O51 -> 0 | T51: 18000 | U51: =C51*P51 -> 0 | V51: =W51*T51 -> 432000000 | W51: 24000 | X51: =(W51/M51)-1 -> 0.83346066
E52: 0 | F52: 0 | G52: elevador bandera izquierdo 1L instrumental | H52: 10 | J52: Q | K52: 22 | L52: 35 | M52: =12500*1.19*0.88 -> 13090 | N52: =13740*0.85*1.19 -> 13898.01 | P52: =13000*0.85*1.19 -> 13149.5 | Q52: AQUILES | R52: =13000*0.85*1.19 -> 13149.5 | S52: =F52*O52 -> 0 | T52: 18000 | U52: =C52*P52 -> 0 | V52: =W52*T52 -> 432000000 | W52: 24000 | X52: =(W52/M52)-1 -> 0.83346066
E53: 0 | F53: 5 | G53: elevador recto ancho 304 instrumental | H53: 12 | J53: Q | K53: 22 | L53: 14 | M53: =12500*1.19*0.88 -> 13090 | N53: =13740*0.85*1.19 -> 13898.01 | P53: =13000*0.85*1.19 -> 13149.5 | Q53: AQUILES | R53: =13000*0.85*1.19 -> 13149.5 | S53: =P53*F53 -> 65747.5 | T53: 18000 | U53: =C53*P53 -> 0 | V53: =W53*T53 -> 432000000 | W53: 24000 | X53: =(W53/M53)-1 -> 0.83346066
E54: 10 | F54: 0 | G54: elevador recto delgado 301 instrumental | H54: 12 | J54: Q | K54: 10 | L54: 19 | M54: =12500*1.19*0.88 -> 13090 | N54: =13740*0.85*1.19 -> 13898.01 | P54: =13000*0.85*1.19 -> 13149.5 | Q54: AQUILES | R54: =13000*0.85*1.19 -> 13149.5 | S54: =P54*F54 -> 0 | T54: 18000 | U54: =C54*P54 -> 0 | V54: =W54*T54 -> 432000000 | W54: 24000 | X54: =(W54/M54)-1 -> 0.83346066
E55: 0 | F55: 0 | G55: elevador recto MAS ancho 34 instrumental | H55: 12 | K55: 5 | L55: 0 | M55: =12500*1.19*0.88 -> 13090 | N55: =13740*0.85*1.19 -> 13898.01 | Q55: PERICO | R55: =12500*1.19*0.88 -> 13090 | S55: =F55*O55 -> 0 | T55: 18000 | U55: =M55*T55 -> 235620000 | V55: =W55*T55 -> 432000000 | W55: 24000 | X55: =(W55/M55)-1 -> 0.83346066
E56: 0 | F56: 0 | G56: Elevador seldin 23 instrumental | H56: 13 | J56: Q | K56: 9 | L56: 33 | M56: =11000*0.82*1.19 -> 10733.8 | N56: =13740*0.85*1.19 -> 13898.01 | O56: 5000 | P56: =9000*0.85*1.19 -> 9103.5 | Q56: CRISTIAN | R56: 5000 | S56: =F56*O56 -> 0 | T56: 18000 | U56: =C56*P56 -> 0 | V56: =W56*T56 -> 432000000 | W56: 24000 | X56: =(W56/M56)-1 -> 1.2359276
E57: 0 | F57: 0 | G57: EMPACADOR DE HILO instrumental | H57: 14 | K57: 24 | L57: 49 | M57: N/V | N57: =17921*0.85*1.19 -> 18127.091 | P57: =5000*0.85*1.19 -> 5057.5 | Q57: AQUILES | R57: =5000*0.85*1.19 -> 5057.5 | S57: =P57*F57 -> 0 | U57: =C57*P57 -> 0 | V57: =W57*T57 -> 0 | W57: 28000 | X57: =(W57/N57)-1 -> 0.54464934
D58: 50 | E58: 0 | G58: ESPATULA 7A | H58: 15 | I58: revisar $4500 cris | K58: 69 | L58: 6 | M58: =4800*0.88*1.19 -> 5026.56 | N58: =6593*0.85*1.19 -> 6668.8195 | O58: 3000 | P58: =5000*0.85*1.19 -> 5057.5 | Q58: CRISTIAN | R58: 3000 | S58: =F58*M58 -> 0 | T58: 7000 | U58: =C58*P58 -> 0 | V58: =W58*T58 -> 63000000 | W58: 9000 | X58: =(W58/M58)-1 -> 0.79048892
E59: 0 | F59: 0 | G59: ESPATULA 7A PLASTICO | H59: 15 | K59: 0 | L59: 50
E60: 0 | F60: 30 | G60: Espatula de cemento metalica CORTA DOBLE instrumental 20/23 | H60: 16 | K60: 49 | L60: 18 | M60: =5000*0.88*1.19 -> 5236 | N60: =6043*0.85*1.19 -> 6112.4945 | O60: 5000 | P60: =5000*0.85*1.19 -> 5057.5 | Q60: CRISTIAN AQUILES | R60: 5058 | S60: =P60*F60 -> 151725 | T60: 7000 | W60: 9000 | X60: =(W60/M60)-1 -> 0.71886937
E61: 0 | F61: 0 | G61: Espatula de CEMENTO PLASTICA | H61: 16 | K61: 50 | L61: 50 | W61: 4000
D62: 15 | E62: 15 | F62: 0 | G62: ESPATULA GRITMAN PARA CERA | H62: 16 | K62: 12 | L62: 24 | M62: =5000*0.88*1.19 -> 5236 | N62: =4696*0.85*1.19 -> 4750.004 | O62: 4800 | P62: =6000*0.85*1.19 -> 6069 | Q62: AQUILES | R62: =6000*0.85*1.19 -> 6069 | S62: =P62*F62 -> 0 | U62: =C62*P62 -> 0 | V62: =W62*T62 -> 0 | W62: 9000 | X62: =(W62/M62)-1 -> 0.71886937
E63: 20 | F63: 20 | G63: espatula yeso mango madera ANCHA INSTRUMENTAL | H63: - | K63: 20 | L63: 25 | M63: =5900*0.88*1.19 -> 6178.48 | N63: =6593*0.85*1.19 -> 6668.8195 | P63: =5900*0.85*1.19 -> 5967.85 | Q63: AQUILES | R63: =5900*0.85*1.19 -> 5967.85 | S63: =P63*F63 -> 119357 | T63: 8000 | U63: =C63*P63 -> 0 | V63: =W63*T63 -> 80000000 | W63: 10000 | X63: =(W63/M63)-1 -> 0.61852106
E64: 0 | F64: 0 | G64: Estrella Poscicionador de Brackts ortodoncia | H64: 48 | K64: 0 | W64: 12000 | X64: =(W64/M64)-1 -> #DIV/0!
E65: 0 | F65: 0 | G65: ESTUCHE DISECCION EN KIT | H65: - | K65: 9 | L65: 0 | O65: 30000 | P65: =40000*0.85*1.19 -> 40460 | Q65: CRISTIAN | R65: 30000 | U65: =C65*P65 -> 0 | W65: 55000
E66: 15 | F66: 0 | G66: Explorador de conducto | H66: 14 | K66: 6 | L66: 10 | M66: =4800*0.88*1.19 -> 5026.56 | N66: =6593*0.85*1.19 -> 6668.8195 | P66: =5000*0.85*1.19 -> 5057.5 | Q66: AQUILES | R66: =5000*0.85*1.19 -> 5057.5 | S66: =F66*O66 -> 0 | U66: =C66*P66 -> 0 | V66: =W66*T66 -> 0 | W66: 9000 | X66: =(W66/M66)-1 -> 0.79048892
E67: 0 | F67: 0 | G67: Explorador del Basico instrumental | H67: 26 | I67: BASICO | J67: 86 | K67: 36 | L67: =69+17 -> 86 | M67: =4800*0.88*1.19 -> 5026.56 | N67: =6043*0.85*1.19 -> 6112.4945 | P67: =4700*0.85*1.19 -> 4754.05 | Q67: AQUILES | R67: =4700*0.85*1.19 -> 4754.05 | S67: =P67*F67 -> 0 | U67: =C67*P67 -> 0 | V67: =W67*T67 -> 0 | W67: 9000 | X67: =(W67/M67)-1 -> 0.79048892
E68: 5 | F68: 0 | G68: forceps 150 instrumental | H68: 17 | J68: Q | K68: 16 | L68: 24 | M68: =26400*0.88*1.19 -> 27646.08 | N68: =30884*0.85*1.19 -> 31239.166 | P68: =29000*0.85*1.19 -> 29333.5 | Q68: AQUILES | R68: =29000*0.85*1.19 -> 29333.5 | S68: =P68*F68 -> 0 | T68: 35000 | U68: =C68*P68 -> 0 | V68: =W68*T68 -> 1470000000 | W68: 42000 | X68: =(W68/M68)-1 -> 0.51920272
E69: 0 | F69: 0 | G69: forceps 151 instrumental | H69: 18 | J69: Q | K69: 21 | L69: 33 | M69: =26400*0.88*1.19 -> 27646.08 | N69: =30884*0.85*1.19 -> 31239.166 | O69: 20000 | P69: =29000*0.85*1.19 -> 29333.5 | Q69: AQUILES | R69: =29000*0.85*1.19 -> 29333.5 | S69: =P69*F69 -> 0 | T69: 35000 | U69: =C69*P69 -> 0 | V69: =W69*T69 -> 1470000000 | W69: 42000 | X69: =(W69/M69)-1 -> 0.51920272
E70: 0 | F70: 0 | G70: forceps 16 instrumental | H70: 21 | J70: Q | K70: 16 | L70: 28 | M70: =30000*0.88*1.19 -> 31416 | N70: =30884*0.85*1.19 -> 31239.166 | P70: =29000*0.85*1.19 -> 29333.5 | Q70: AQUILES | R70: =29000*0.85*1.19 -> 29333.5 | S70: =F70*O70 -> 0 | T70: 35000 | U70: =C70*P70 -> 0 | V70: =W70*T70 -> 1470000000 | W70: 42000 | X70: =(W70/M70)-1 -> 0.3368984
E71: 0 | F71: 0 | G71: forceps 17 L (no pedir) | H71: 22 | K71: 0 | L71: 1 | W71: 42000
E72: 0 | F72: 0 | G72: forceps 18 L (no pedir) | H72: 22 | K72: 0 | L72: 1 | W72: 42000
E73: 0 | F73: 0 | G73: forceps 24 instrumental | H73: 21 | K73: 18 | L73: 19 | M73: =30000*0.88*1.19 -> 31416 | N73: =30884*0.85*1.19 -> 31239.166 | P73: =29000*0.85*1.19 -> 29333.5 | Q73: AQUILES | R73: =29000*0.85*1.19 -> 29333.5 | S73: =F73*O73 -> 0 | T73: 35000 | U73: =C73*P73 -> 0 | V73: =W73*T73 -> 1470000000 | W73: 42000 | X73: =(W73/M73)-1 -> 0.3368984
E74: 0 | F74: 0 | G74: forceps 69 instrumental | H74: 19 | J74: Q | K74: 10 | L74: 19 | M74: =30000*0.88*1.19 -> 31416 | N74: =30884*0.85*1.19 -> 31239.166 | P74: =29000*0.85*1.19 -> 29333.5 | Q74: AQUILES | R74: =29000*0.85*1.19 -> 29333.5 | S74: =F74*O74 -> 0 | T74: 35000 | U74: =C74*P74 -> 0 | V74: =W74*T74 -> 1470000000 | W74: 42000 | X74: =(W74/M74)-1 -> 0.3368984
E75: 20 | F75: 5 | G75: forceps pediatrico 150 S instrumental | H75: 20 | K75: 3 | L75: 7 | M75: =30000*0.88*1.19 -> 31416 | N75: =30884*0.85*1.19 -> 31239.166 | P75: =29000*0.85*1.19 -> 29333.5 | Q75: AQUILES | R75: =29000*0.85*1.19 -> 29333.5 | S75: =P75*F75 -> 146667.5 | T75: 35000 | U75: =C75*P75 -> 0 | V75: =W75*T75 -> 1470000000 | W75: 42000 | X75: =(W75/M75)-1 -> 0.3368984
E76: 6 | F76: 0 | G76: forceps pediatrico 151 S instrumental | H76: 20 | K76: 7 | L76: 10 | M76: =30000*0.88*1.19 -> 31416 | N76: =30884*0.85*1.19 -> 31239.166 | P76: =29000*0.85*1.19 -> 29333.5 | Q76: AQUILES | R76: =29000*0.85*1.19 -> 29333.5 | S76: =P76*F76 -> 0 | T76: 35000 | U76: =C76*P76 -> 0 | V76: =W76*T76 -> 1470000000 | W76: 42000 | X76: =(W76/M76)-1 -> 0.3368984
E77: 0 | F77: 20 | G77: FP 3 | H77: 53 | K77: 30 | L77: 60 | M77: =4800*0.88*1.19 -> 5026.56 | N77: =6043*0.85*1.19 -> 6112.4945 | P77: =4600*0.85*1.19 -> 4652.9 | Q77: AQUILES | R77: =4600*0.85*1.19 -> 4652.9 | S77: =P77*F77 -> 93058 | T77: 8000 | U77: =C77*P77 -> 0 | V77: =W77*T77 -> 80000000 | W77: 10000 | X77: =(W77/M77)-1 -> 0.98943214
E78: 0 | F78: 0 | G78: FP 3 plastcio | H78: 53 | K78: 42 | L78: 100 | T78: 8000
E79: 6 | F79: 0 | G79: HOLLEMBACK | H79: 45 | K79: 6 | L79: 13 | M79: =4800*1.19*0.88 -> 5026.56 | N79: 5223 | Q79: PERICO | R79: =4800*1.19*0.88 -> 5026.56 | S79: =F79*M79 -> 0 | U79: =M79*T79 -> 0 | V79: =W79*T79 -> 0 | W79: 9000 | X79: =(W79/M79)-1 -> 0.79048892
E80: 0 | F80: 10 | G80: INSTRUMENTAL DE GLICK DELGADO | H80: 52 | K80: 16 | L80: 10 | M80: =4800*0.88*1.19 -> 5026.56 | N80: 3266 | P80: =4600*0.85*1.19 -> 4652.9 | Q80: AQUILES | R80: =4600*0.85*1.19 -> 4652.9 | S80: =N80*F80 -> 32660 | U80: =C80*P80 -> 0 | V80: =W80*T80 -> 0 | W80: 9000 | X80: =(W80/M80)-1 -> 0.79048892
D81: 10 | E81: 10 | G81: INSTRUMENTAL PKT 54-630 | H81: 24 | I81: puppies | K81: 5 | L81: 7 | M81: =4600*1.19*0.88 -> 4817.12 | O81: 3740 | Q81: CRISTIAN | R81: 3740 | S81: =F81*O81 -> 0 | U81: =P81*T81 -> 0 | V81: =W81*T81 -> 0 | W81: 9000 | X81: =(W81/M81)-1 -> 0.86833627
D82: 10 | E82: 10 | G82: INSTRUMENTAL PKT 54-631 | H82: 24 | I82: puppies | K82: 0 | L82: 4 | M82: =4600*1.19*0.88 -> 4817.12 | O82: 3740 | Q82: CRISTIAN | R82: 3740 | S82: =F82*O82 -> 0 | U82: =P82*T82 -> 0 | V82: =W82*T82 -> 0 | W82: 9000 | X82: =(W82/M82)-1 -> 0.86833627
E83: 0 | F83: 0 | G83: INSTRUMENTAL PKT 54-632 | H83: 24 | K83: 8 | L83: 38 | M83: =4600*1.19*0.88 -> 4817.12 | O83: 3740 | Q83: CRISTIAN | R83: 3740 | S83: =F83*O83 -> 0 | U83: =P83*T83 -> 0 | V83: =W83*T83 -> 0 | W83: 9000 | X83: =(W83/M83)-1 -> 0.86833627
E84: 10 | F84: 20 | G84: INSTRUMENTAL PKT Chorriador 54-628 | H84: 24 | K84: 0 | L84: 0 | M84: N/V | N84: N / V | U84: =P84*T84 -> 0 | V84: =W84*T84 -> 0 | W84: 9000
E85: 8 | F85: 20 | G85: INSTRUMENTAL PKT Chorriador 54-629 | H85: 24 | K85: 2 | L85: 0 | M85: N/V | N85: N / V | W85: 9000
E86: 6 | F86: 0 | G86: INSTRUMENTAL PKT completo x 5 | H86: 23 | K86: 14 | L86: 29 | M86: =21500*0.88*1.19 -> 22514.8 | N86: =24071*0.85*1.19 -> 24347.817 | P86: =22000*0.85*1.19 -> 22253 | Q86: AQUILES | R86: =22000*0.85*1.19 -> 22253 | S86: =P86*F86 -> 0 | U86: =C86*P86 -> 0 | V86: =W86*T86 -> 0 | W86: 40000 | X86: =(W86/M86)-1 -> 0.77660916
D87: 20 | E87: 20 | F87: 0 | G87: Jeringa carpule de rosca CON ALETA INSTRUMENTAL | H87: 30 | J87: Q | K87: 19 | L87: 48 | M87: =21500*0.88*1.19 -> 22514.8 | N87: =26620*0.85*1.19 -> 26926.13 | O87: 17000 | P87: =21000*0.85*1.19 -> 21241.5 | Q87: CRISTIAN | R87: 17000 | S87: =F87*M87 -> 0 | T87: 32000 | U87: =C87*P87 -> 0 | V87: =W87*T87 -> 1152000000 | W87: 36000 | X87: =(W87/M87)-1 -> 0.59894825
E88: 0 | F88: 20 | G88: KIT Basico adulto instrumental | H88: 25 | I88: BASICO | K88: 58 | L88: 21 | M88: =17700*1.19*0.88 -> 18535.44 | N88: =22048*1.19*0.85 -> 22301.552 | P88: =20000*0.85*1.19 -> 20230 | Q88: AQUILES | R88: =20000*0.85*1.19 -> 20230 | S88: =P88*F88 -> 404600 | T88: 30000 | U88: =C88*P88 -> 0 | V88: =W88*T88 -> 1020000000 | W88: 34000 | X88: =(W88/M88)-1 -> 0.83432387
E89: 0 | F89: 0 | G89: KIT Basico instrumental PEDIATRICO | H89: - | I89: BASICO P | K89: 15 | L89: 13 | M89: N/V | N89: =22048*1.19*0.85 -> 22301.552 | Q89: NELLY | R89: =22048*1.19*0.85 -> 22301.552 | S89: =F89*N89 -> 0 | U89: =T89*N89 -> 0 | V89: =W89*T89 -> 0 | W89: 32000 | X89: =(W89/N89)-1 -> 0.43487772
E90: 0 | F90: 0 | G90: Lima de Hueso instrumental | H90: 15 | J90: Q | K90: 16 | L90: 50 | M90: =10000*0.88*1.19 -> 10472 | N90: =11527*0.85*1.19 -> 11659.56 | O90: 4000 | P90: =8500*0.85*1.19 -> 8597.75 | Q90: CRISTIAN | R90: 4000 | S90: =F90*O90 -> 0 | U90: =C90*P90 -> 0 | V90: =W90*T90 -> 0 | W90: 13000 | X90: =(W90/M90)-1 -> 0.24140565
E91: 0 | F91: 0 | G91: luna para espejo instrumental basico No. 5 | H91: 28 | I91: BASICO | J91: 360 | K91: 12 | L91: =12*30 -> 360 | M91: =1900*0.88*1.19 -> 1989.68 | N91: 2223 | P91: =21600*0.85*1.19/12 -> 1820.7 | Q91: AQUILES | R91: =21600*0.85*1.19/12 -> 1820.7 | S91: =P91*F91 -> 0 | U91: =C91*P91 -> 0 | V91: =W91*T91 -> 0 | W91: 5000 | X91: =(W91/M91)-1 -> 1.5129669
E92: 0 | F92: 0 | G92: luna para espejo instrumental No. 4 | H92: 28 | K92: 0 | L92: 12 | M92: =1900*0.88*1.19 -> 1989.68 | S92: =F92*O92 -> 0 | U92: =P92*T92 -> 0 | V92: =W92*T92 -> 0 | W92: 5000 | X92: =(W92/M92)-1 -> 1.5129669
E93: 0 | F93: 10 | G93: Mango de bisturi instrumental | H93: 4 | J93: Q | K93: 59 | L93: 27 | M93: =3700*0.88*1.19 -> 3874.64 | N93: =2725*0.85*1.19 -> 2756.3375 | P93: =3500*0.85*1.19 -> 3540.25 | Q93: AQUILES | R93: =3500*0.85*1.19 -> 3540.25 | S93: =P93*F93 -> 35402.5 | T93: 5000 | U93: =C93*P93 -> 0 | V93: =W93*T93 -> 35000000 | W93: 7000 | X93: =(W93/M93)-1 -> 0.80661945
D94: 20 | E94: 20 | G94: MANGO SOLO PARA ESPEJO BASICO instrumental | H94: 28 | I94: BASICO | J94: 39 | K94: 9 | L94: 39 | M94: =3900*0.88*1.19 -> 4084.08 | N94: =3507*1.19*0.85 -> 3547.3305 | O94: 2500 | P94: =3000*0.85*1.19 -> 3034.5 | Q94: CRISTIAN | R94: 2500 | S94: =F94*O94 -> 0 | U94: =C94*P94 -> 0 | V94: =W94*T94 -> 0 | W94: 7000 | X94: =(W94/M94)-1 -> 0.7139723
E95: 0 | F95: 0 | G95: MARTILLO TUMBA PUENTES XTRES PUNTAS | H95: 29 | K95: 2 | L95: 7 | M95: =35000*0.88*1.19 -> 36652 | N95: =30474*0.85*1.19 -> 30824.451 | P95: =32000*0.85*1.19 -> 32368 | Q95: AQUILES | R95: =32000*0.85*1.19 -> 32368 | S95: =P95*F95 -> 0 | T95: 44000 | U95: =C95*P95 -> 0 | V95: =W95*T95 -> 2112000000 | W95: 48000 | X95: =(W95/M95)-1 -> 0.30961476
E96: 0 | F96: 0 | G96: MECHERO METALICO | H96: - | K96: 36 | O96: 4300 | Q96: CRISTIAN | R96: 4300 | S96: =F96*O96 -> 0 | U96: =P96*T96 -> 0 | V96: =W96*T96 -> 0 | W96: 8000 | X96: =(W96/O96)-1 -> 0.86046512
E97: 0 | F97: 5 | G97: Perforador de tela instrumental | H97: 51 | K97: 20 | L97: 15 | M97: =32000*0.88*1.19 -> 33510.4 | N97: =37651*0.85*1.19 -> 38083.986 | P97: =34000*0.85*1.19 -> 34391 | Q97: AQUILES | R97: =34000*0.85*1.19 -> 34391 | S97: =P97*F97 -> 171955 | T97: 44000 | U97: =C97*P97 -> 0 | V97: =W97*T97 -> 2376000000 | W97: 54000 | X97: =(W97/M97)-1 -> 0.61144003
E98: 15 | F98: 0 | G98: PERIOSTOTOMO (elevador de molt) | H98: 52 | J98: Q | K98: 13 | L98: 49 | M98: =9000*0.88*1.19 -> 9424.8 | N98: =13740*0.85*1.19 -> 13898.01 | P98: =9500*0.85*1.19 -> 9609.25 | Q98: AQUILES | R98: =9500*0.85*1.19 -> 9609.25 | S98: =F98*O98 -> 0 | T98: 15000 | U98: =C98*P98 -> 0 | V98: =W98*T98 -> 300000000 | W98: 20000 | X98: =(W98/M98)-1 -> 1.1220609
D99: 15 | E99: 15 | F99: 0 | G99: PINZA ALGODONERA del basico | H99: 27 | I99: BASICO | J99: 110 | K99: 11 | L99: 118 | M99: =5000*0.88*1.19 -> 5236 | N99: =5161*0.85*1.19 -> 5220.3515 | O99: 4300 | P99: =4600*0.85*1.19 -> 4652.9 | Q99: CRISTIAN | R99: 4300 | S99: =F99*O99 -> 0 | T99: 7000 | U99: =C99*P99 -> 0 | V99: =W99*T99 -> 63000000 | W99: 9000 | X99: =(W99/M99)-1 -> 0.71886937
E100: 6 | F100: 5 | G100: PINZA ALGODONERA PEDIATRICA | H100: 27 | I100: BASICO P | K100: 3 | L100: 2 | M100: =4800*0.88*1.19 -> 5026.56 | N100: =4343*0.85*1.19 -> 4392.9445 | Q100: NELLY | R100: =4343*0.85*1.19 -> 4392.9445 | S100: =F100*O100 -> 0 | U100: =M100*T100 -> 0 | V100: =W100*T100 -> 0 | W100: 9000 | X100: =(W100/M100)-1 -> 0.79048892
...

Sheet imporq
B1: pedido | C1: sur | D1: norte | F1: PEDI A
A2: bolsa para esterilizar # 2 = 9 Cm x 13 Cm GRAPAS | B2: 30 | C2: 10 | D2: 20 | F2: IMPORQUIR
A3: Bolsa para esterilizar # 3 = 9 x 26 cm BASICO | B3: 60 | C3: 10 | D3: 50 | F3: IMPORQUIR
A4: Cinta Esterilizar clase 5 caja roja indicador imporquirurgica | B4: 20 | C4: 15 | D4: 3 | F4: IMPORQUIR
A5: Hojas de bisturi # 15 x Caja | B5: 5 | C5: 0 | D5: 3 | F5: IMPORQUIR
A6: bolsa para esterilizar # 1 = 6 Cm x 13 Cm LIMAS | B6: =C6+D6 -> 40 | C6: 20 | D6: 20 | E6: dentmar $6.500 imporq $6.000 | F6: DENMART
A7: Bolsa para esterilizar # 5 = 19 x 33 cm GRANDE | B7: =C7+D7 -> 2 | C7: 0 | D7: 2 | E7: denmart $45.000 | F7: DENMART
A8: MICROBRUSH micro aplicadores X 100 | B8: 20 AZUL 16 fuscia 20 AMAR 8 BLAN 12 VERD | C8: 20 AZUL 16 ROSA 20 AMAR 8 BLAN 12 VERD | D8: 0 | F8: DENMART
A9: Sutura SEDA 3/0 | B9: =C9+D9 -> 20 | C9: 0 | D9: 20 | E9: denmart $12.500 | F9: DENMART
A10: Sutura SEDA 4/0 | B10: =C10+D10 -> 20 | C10: 0 | D10: 20 | E10: denmart $12.500 | F10: DENMART
A11: Sutura VICRYL - Poliglicolico 4/0 | B11: =C11+D11 -> 5 | C11: 0 | D11: 5 | F11: DENMART
A12: CINTA TESTIGO | B12: 20 | C12: 30 | D12: 2 | E12: denmart $10.000 imporq $10.000 | F12: FALTA CONSEGUIR ESTO | G12: 12000 | H12: JOSE CARDENAS
A13: Sutura POLYPROPYLENE 3/0 nylon | B13: =C13+D13 -> 20 | C13: 10 | D13: 10 | E13: dentmar $15.000 imporq $12.000 | F13: FALTA CONSEGUIR ESTO | G13: 13000 | H13: JOSE CARDENAS
A14: Sutura POLYPROPYLENE 4/0 nylon | B14: =C14+D14 -> 20 | C14: 10 | D14: 10 | E14: dentmar $15.000 imporq $12.000 | F14: FALTA CONSEGUIR ESTO | G14: 13000 | H14: JOSE CARDENAS
A15: Sutura POLYPROPYLENE 5/0 nylon | B15: =C15+D15 -> 20 | C15: 0 | D15: 20 | E15: dentmar $15.000 imporq $12.000 | F15: FALTA CONSEGUIR ESTO | G15: 13000 | H15: JOSE CARDENAS
A16: Sutura SEDA 5/0 | B16: =C16+D16 -> 15 | C16: 0 | D16: 15 | F16: FALTA CONSEGUIR ESTO | G16: 13000 | H16: JOSE CARDENAS

Sheet HOJA CUADRE NORTE
A1: FECHA | B1: INICIO | C1: FINAL | D1: VENTA EFECTIV | E1: DATAFONO | F1: TRANSFERENCIA | G1: VENTA DEL DIA | I1: PAGOS | J1: A quien se pago
A2: 45554 | B2: 0 | C2: =289800+1200000+344000+1800000+1270000+682000 -> 5585800 | D2: =C2-B2 -> 5585800 | E2: =858000+12000+105000+20000+258000+24000+240000+24000+858000 -> 2399000 | F2: 1083000 | G2: =D2+E2+F2 -> 9067800 | I2: =600000+82000 -> 682000 | J2: facturas | K2: 700000
A3: 45555 | B3: =440000+35300 -> 475300 | C3: =517000+120000+1450000+33200+20000 -> 2140200 | D3: =C3-B3 -> 1664900 | E3: =34000+10000+135000+581000 -> 760000 | F3: 472000 | G3: =D3+E3+F3 -> 2896900 | I3: 4000 | J3: raul
A4: 45556 | B4: =350000+33200 -> 383200 | C4: =20400+298000+600000+7000+1832000 -> 2757400 | D4: =C4-B4 -> 2374200 | E4: =32000+116000+50000+45000+60000+136000 -> 439000 | F4: 1301100 | G4: =D4+E4+F4 -> 4114300 | I4: =20000+12000+150000+1650000 -> 1832000 | J4: DON JUAN + DORA + RAUL
A5: 45557 | B5: =20400+298000+7000+600000 -> 925400 | C5: =18000+380000+120000+50000+300000+1000000 -> 1868000 | D5: =C5-B5 -> 942600 | E5: 0 | F5: 45000 | G5: =D5+E5+F5 -> 987600 | I5: =300000+1000000 -> 1300000 | J5: larry + raul
A6: 45558 | B6: =18000+380000+120000+50000 -> 568000 | C6: =11500+450000+456000+1317000 -> 2234500 | D6: =C6-B6 -> 1666500 | E6: =83700+20000+66000+226000 -> 395700 | F6: 3181100 | G6: =D6+E6+F6 -> 5243300 | I6: =6000+5000+1000000+306000 -> 1317000 | J6: estefani + aguacate + plussdent + visores
A7: 45559 | B7: 917500 | C7: =2450000+610000+119000 -> 3179000 | D7: =C7-B7 -> 2261500 | E7: =132000+400000+42000+34000 -> 608000 | F7: 2463800 | G7: =D7+E7+F7 -> 5333300 | I7: =550000+100000+500000 -> 1150000 | J7: d1 + guantes + raul
A8: 45560 | B8: 371000 | C8: =32200+313000+1600000+432100 -> 2377300 | D8: =C8-B8 -> 2006300 | E8: =210000+164000+28000 -> 402000 | F8: 1314700 | G8: =D8+E8+F8 -> 3723000 | I8: =50000+32500+254100+90500+5000 -> 432100 | J8: monedas + raul + scott + abraham + aguacate
A9: 45561 | B9: 345200 | C9: =10000+469000+1400000+45000 -> 1924000 | D9: =C9-B9 -> 1578800 | E9: 1466000 | F9: 3710000 | G9: =D9+E9+F9 -> 6754800 | I9: =30000+15000 -> 45000 | J9: flete bogota + alfredo
A10: 45562 | B10: 479000 | C10: =371300+1600000+170000+98200 -> 2239500 | D10: =C10-B10 -> 1760500 | E10: 244000 | F10: 719000 | G10: =D10+E10+F10 -> 2723500 | I10: =20500+77700 -> 98200 | J10: cardenas + perico | N10: millones
A11: 45563 | B11: =336000+35300 -> 371300 | C11: =31100+278000+400000+307200 -> 1016300 | D11: =C11-B11 -> 645000 | E11: 162000 | F11: 585000 | G11: =D11+E11+F11 -> 1392000 | I11: =300000+7200 -> 307200 | J11: LARRY + DOMICILIO | N11: 3.2
A12: 45565 | B12: =309100+400000 -> 709100 | C12: =19500+238000+250000+2230400 -> 2737900 | D12: =C12-B12 -> 2028800 | E12: 637000 | F12: 1788800 | G12: =D12+E12+F12 -> 4454600 | I12: =540000+500000+950000+40400+200000 -> 2230400 | J12: PAGOS CORRESPONSAL + MARICELA + NOMINA+ AGUA + PLAFIQUE | N12: 3.2
D13: =C13-B13 -> 0 | G13: =SUM(G2:G12) -> 46691100 | I13: =SUM(I2:I12) -> 9397900 | N13: 2.5
A14: 45566 | B14: 507500 | C14: =371000+6500+1850000+1063900 -> 3291400 | D14: =C14-B14 -> 2783900 | E14: 165000 | F14: 2126500 | G14: =D14+E14+F14 -> 5075400 | I14: =874000+139900+50000 -> 1063900 | J14: aquiles + abraham + vigilante | N14: 0.8
A15: 45567 | B15: 326500 | C15: =256000+1450000+10400+140400 -> 1856800 | D15: =C15-B15 -> 1530300 | E15: 1270000 | F15: 1843500 | G15: =D14+E15+F15 -> 5897400 | I15: =6500+4200+99700+30000 -> 140400 | J15: mufla + sello + dulces + boligrafo | K15: mufla | N15: =SUM(N11:N14) -> 9.7
A16: 45568 | B16: =256000+50000+10400 -> 316400 | C16: =228000+107000+19100+2250000+450600 -> 3054700 | D16: =C16-B16 -> 2738300 | E16: 91200 | F16: 4693900 | G16: =D16+E16+F16 -> 7523400 | I16: =425500+25100 -> 450600 | J16: salento + flete marleny
A17: 45569 | B17: =228000+19100 -> 247100 | C17: =205000+1500000+192500+16600 -> 1914100 | D17: =C17-B17 -> 1667000 | E17: 119000 | F17: 1816600 | G17: =D17+E17+F17 -> 3602600 | I17: =28500+164000 -> 192500 | J17: aquiles + flete eurodent | K17: hidrogum
A18: 45570 | B18: =205000+16600 -> 221600 | C18: =292000+1100000+8600+20000+370000 -> 1790600 | D18: =C18-B18 -> 1569000 | E18: =119600+175000+16000 -> 310600 | F18: 864000 | G18: =D18+E18+F18 -> 2743600 | I18: =20000+350000 -> 370000 | J18: alfredo + angela | K18: larry + yeso
A19: 45572 | B19: =250000+8600 -> 258600 | C19: =3800+311000+2450000+30000+20000 -> 2814800 | D19: =C19-B19 -> 2556200 | E19: 1001500 | F19: 1295600 | G19: =D19+E19+F19 -> 4853300 | I19: 20000 | J19: alfredo | K19: new stetic + loggro + ramon
A20: 45573 | B20: =314800+50000+30000 -> 394800 | C20: =392000+47100+800000+279000 -> 1518100 | D20: =C20-B20 -> 1123300 | E20: 1517000 | F20: 1525000 | G20: =D20+E20+F20 -> 4165300 | I20: 279000 | J20: fercho
A21: 45574 | B21: =292000+47100 -> 339100 | C21: =29800+419000+900000+555000 -> 1903800 | D21: =C21-B21 -> 1564700 | E21: 918900 | F21: 1431600 | G21: =D21+E21+F21 -> 3915200 | I21: =15000+340000+200000 -> 555000 | J21: alfredo + gabriel velasques + eucaris
A22: 45575 | B22: 448800 | C22: =312000+21300+1750000+50000 -> 2133300 | D22: =C22-B22 -> 1684500 | E22: 634000 | F22: 641500 | G22: =D22+E22+F22 -> 2960000 | I22: 50000 | J22: D1
A23: 45576 | B23: =212000+21300 -> 233300 | C23: =2400+400000+2200000+1634600 -> 4237000 | D23: =C23-B23 -> 4003700 | E23: 602000 | F23: 1909000 | G23: =D23+E23+F23 -> 6514700 | I23: =1449600+185000 -> 1634600 | J23: hidrogum + aquiles
A24: 45577 | B24: =400000+2400+400000 -> 802400 | C24: =6000+287000+1300000+650000 -> 2243000 | D24: =C24-B24 -> 1440600 | E24: 0 | F24: 437100 | G24: =D24+E24+F24 -> 1877700 | I24: =350000+300000 -> 650000 | J24: angela + larry
A25: 45580 | B25: 293000 | C25: =394000+46900+830000+1786500 -> 3057400 | D25: =C25-B25 -> 2764400 | E25: 1843500 | F25: 1984000 | G25: =D25+E25+F25 -> 6591900 | I25: =200000 + 670000+16500 + 900000 -> 1786500 | J25: miguel bogota + valentina + flete prodont + gabriela
A26: 45581 | B26: =394000+46900 -> 440900 | C26: =29000+420000+1550000+325800 -> 2324800 | D26: =C26-B26 -> 1883900 | E26: =9000+84000+20000+76000+82500+700000 -> 971500 | F26: 4939200 | G26: =D26+E26+F26 -> 7794600 | I26: =300000+25800 -> 325800
A27: 45582 | B27: 449000 | C27: =596000+880000+23900+697700 -> 2197600 | D27: =C27-B27 -> 1748600 | E27: 200000 | F27: 3742300 | G27: =D27+E27+F27 -> 5690900 | I27: =100000+597700 -> 697700 | J27: upegui + allers
A28: 45583 | B28: =300000+23900 -> 323900 | C28: =+6700+184000+320000+2203000+5000 -> 2718700 | D28: =C28-B28 -> 2394800 | E28: 427400 | F28: 3119000 | G28: =D28+E28+F28 -> 5941200 | I28: 5000
A29: 45584 | B29: =+670+340000+350000+40000 -> 730670 | C29: =28700+567000+630000+350000+621000 -> 2196700 | D29: =C29-B29 -> 1466030 | E29: 163000 | F29: 595000 | G29: =D29+E29+F29 -> 2224030 | I29: =121000+200000+300000 -> 621000 | J29: flete biodentales + hugo tarjeta + larry
A30: 45586 | B30: =28700+305000 -> 333700 | C30: =485000+950000+22800 -> 1457800 | D30: =C30-B30 -> 1124100 | E30: 886000 | F30: 1791800 | G30: =D30+E30+F30 -> 3801900 | I30: 0
A31: 45587 | B31: =345000+22800 -> 367800 | C31: =252000+800000+2000000+115000+12700+490000 -> 3669700 | D31: =C31-B31 -> 3301900 | E31: 239000 | F31: 1680100 | G31: =D31+E31+F31 -> 5221000 | I31: 490000 | J31: 40mil novedades
A32: 45588 | B32: =305000+12700 -> 317700 | C32: =615900+1500000+581500 -> 2697400 | D32: =C32-B32 -> 2379700 | E32: 65000 | F32: 2803800 | G32: =D32+E32+F32 -> 5248500 | I32: =490000+91500 -> 581500 | J32: aquiles + alcohol
A33: 45589 | B33: 615900 | C33: =63500+598000+1100000+977600 -> 2739100 | D33: =C33-B33 -> 2123200 | E33: 146000 | F33: 822900 | G33: =D33+E33+F33 -> 3092100 | I33: =900000+77600+21700 -> 999300 | J33: raul + abraham + flete bond
A34: 45590 | B34: 361500 | C34: =41400+190000+1550000 -> 1781400 | D34: =C34-B34 -> 1419900 | E34: 177500 | F34: 1354900 | G34: =D34+E34+F34 -> 2952300 | I34: =45600+70000+36700+80000+100000 -> 332300 | J34: flete dentmark + alfredo + pizza
A35: 45591 | B35: =231400+400000 -> 631400 | C35: =22400+142000+1000000+350000 -> 1514400 | D35: =C35-B35 -> 883000 | E35: 0 | F35: 880000 | G35: =D35+E35+F35 -> 1763000 | I35: =300000+50000 -> 350000 | J35: LARRY + POSICIONADOR
A36: 45593 | B36: 164000 | C36: =72500+681000+700000 -> 1453500 | D36: =C36-B36 -> 1289500 | E36: 1529000 | F36: 2301100 | G36: =D36+E36+F36 -> 5119600 | I36: 0
A37: 45594 | B37: 231000 | C37: =59600+356000+700000+55820 -> 1171420 | D37: =C37-B37 -> 940420 | E37: 579900 | F37: 3493100 | G37: =D37+E37+F37 -> 5013420 | I37: =38820+520000 -> 558820 | J37: ABRAHAM + LUPAS AZULES
A38: 45595 | B38: 415600 | C38: =50700+409000+1200000+16000 -> 1675700 | D38: =C38-B38 -> 1260100 | E38: 326000 | F38: 1015000 | G38: =D38+E38+F38 -> 2601100 | I38: =6000+10000+900000 -> 916000 | J38: recarga + raul + gabriela
A39: 45596 | B39: =459700+300000 -> 759700 | C39: =51700+557000+1450000+4860000 -> 6918700 | D39: =C39-B39 -> 6159000 | E39: 1118000 | F39: 1028000 | G39: =D39+E39+F39 -> 8305000 | I39: =1270000+660000+2930000 -> 4860000 | J39: krika + valentina + carolina la portada
D40: =SUM(D14:D39) -> 53800050 | E40: =SUM(E14:E39) -> 15301000 | F40: =SUM(F14:F39) -> 50134500 | G40: =SUM(G14:G39) -> 120489150 | I40: =SUM(I14:I39) -> 17929920
A41: 45597 | B41: 608700 | C41: =36700+944000+750000+390000 -> 2120700 | D41: =C41-B41 -> 1512000 | E41: 486600 | F41: 5738200 | G41: =D41+E41+F41 -> 7736800 | I41: 390000 | J41: tropical | K41: 1500000
A42: 45598 | B42: =36700+324000 -> 360700 | C42: =33100+165000+171000+550000 -> 919100 | D42: =C42-B42 -> 558400 | E42: 66000 | F42: 337000 | G42: =D42+E42+F42 -> 961400 | I42: 280000 | J42: larry | K42: 500000
A43: 45601 | B43: 369100 | C43: =182500+78000+1350000+103000 -> 1713500 | D43: =C43-B43 -> 1344400 | E43: 430000 | F43: 908400 | G43: =D43+E43+F43 -> 2682800 | I43: =36000+17000+50000 -> 103000 | J43: flete dentmarck + domicilio bocas + vigilante | K43: 1100000
A44: 45602 | B44: 360500 | C44: =170400+351000+2400000 -> 2921400 | D44: =C44-B44 -> 2560900 | E44: 289000 | F44: 2080900 | G44: =D44+E44+F44 -> 4930800 | I44: =21500+200000+88000 -> 309500 | J44: flete prodont + raul + regular | K44: 2400000
A45: 45603 | B45: 521400 | C45: =158300+414000+2350000+60000 -> 2982300 | D45: =C45-B45 -> 2460900 | E45: 545000 | F45: 2231900 | G45: =D45+E45+F45 -> 5237800 | I45: =19000+6000 -> 25000 | J45: D1 + raul | K45: 2350000
A46: 45604 | B46: =572300+60000 -> 632300 | C46: =132600+364000+1450000 -> 1946600 | D46: =C46-B46 -> 1314300 | E46: 72000 | F46: 1325300 | G46: =D46+E46+F46 -> 2711600 | I46: =49500+4700+600000+170000 -> 824200 | J46: llaves + aquiles + raul + glicerina | K46: 1450000
A47: 45605 | B47: 496000 | C47: =135500+410000+1100000+36000 -> 1681500 | D47: =C47-B47 -> 1185500 | E47: 0 | F47: 202000 | G47: =D47+E47+F47 -> 1387500 | I47: 200000 | J47: larry | K47: 1100000
A48: 45608 | B48: =545500+36000 -> 581500 | C48: =170300+629000+100000+1311000 -> 2210300 | D48: =C48-B48 -> 1628800 | E48: 20000 | F48: 1712500 | G48: =D48+E48+F48 -> 3361300 | I48: =150000+1150000+11000 -> 1311000 | J48: vidrios + eurodent+ don juan | K48: 300000
A49: 45609 | B49: 599300 | C49: =151600+157000+900000+1500000+316716 -> 3025316 | D49: =C49-B49 -> 2426016 | E49: 44000 | F49: 3849500 | G49: =D49+E49+F49 -> 6319516 | I49: =203213+113500 -> 316713 | J49: scott + bolsas fercho | K49: 2400000
A50: 45610 | B50: =2708300-2400000 -> 308300 | C50: =153000+84000+2500000+90000 -> 2827000 | D50: =C50-B50 -> 2518700 | E50: 361000 | F50: 3099000 | G50: =D50+E50+F50 -> 5978700 | I50: 90000 | J50: alfredo | K50: 2000000
A51: 45611 | B51: =237000+50000 -> 287000 | C51: =78000+350000+139200+1870700 -> 2437900 | D51: =C51-B51 -> 2150900 | E51: 283000 | F51: 2743900 | G51: =D51+E51+F51 -> 5177800 | I51: =286000+30000+1500000+54700 -> 1870700 | J51: espejos + eurodent+ raul +dyma | K51: 0
A52: 45612 | B52: 567000 | C52: =179000+550000+300000 -> 1029000 | D52: =C52-B52 -> 462000 | E52: 0 | F52: 2340000 | G52: =D52+E52+F52 -> 2802000 | I52: 300000 | J52: larry | K52: 550000
A53: 45614 | B53: 179000 | C53: =384000+126500+450000+478000 -> 1438500 | D53: =C53-B53 -> 1259500 | E53: 41500 | F53: 2747900 | G53: =D53+E53+F53 -> 4048900 | I53: =15000+82000+331000+50000 -> 478000 | J53: alfredo + dolarcity + emma + vigilante | K53: 450000
A54: 45615 | B54: 510500 | C54: =157900+490000+1950000+20000+157000 -> 2774900 | D54: =C54-B54 -> 2264400 | E54: 183000 | F54: 1720900 | G54: =D54+E54+F54 -> 4168300 | I54: 157000 | J54: aquiles | K54: =1950000+170000 -> 2120000
A55: 45616 | B55: 340000 | C55: =156350+537000+4022000+300000+447000 -> 5462350 | D55: =C55-B55 -> 5122350 | E55: 85000 | F55: 2021800 | G55: =D55+E55+F55 -> 7229150 | I55: =10000+310000+5000+122000 -> 447000 | J55: dolarcity + soat + aguacate+alcohol | K55: 4000000
A56: 45617 | B56: 715350 | C56: =155750+308000+2100000+450000 -> 3013750 | D56: =C56-B56 -> 2298400 | E56: 1061000 | F56: 1795000 | G56: =D56+E56+F56 -> 5154400 | I56: =15000+20000+10000 -> 45000 | J56: leonela + alfredo + angela | K56: 2100000
A57: 45618 | B57: =155500+308000 -> 463500 | C57: =143650+238000+650000+322900 -> 1354550 | D57: =C57-B57 -> 891050 | E57: 120000 | F57: 4008000 | G57: =D57+E57+F57 -> 5019050 | I57: =25000+4900+28000+265000 -> 322900 | J57: alfredo azucar + flete ultradental + allers | K57: 650000
A58: 45619 | B58: 381650 | C58: =146400+169000+150000 -> 465400 | D58: =C58-B58 -> 83750 | E58: 165000 | F58: 679700 | G58: =D58+E58+F58 -> 928450 | I58: 0
A59: 45621 | B59: 465400 | C59: =115450+256000+1049000 -> 1420450 | D59: =C59-B59 -> 955050 | E59: 264000 | F59: 6096000 | G59: =D59+E59+F59 -> 7315050 | I59: =22900+426000+2000 -> 450900 | J59: flete soccidentales + emma+ cafe | K59: =800000+200000 -> 1000000
A60: 45622 | B60: =371450+49000 -> 420450 | C60: =246000+147050+5100000+140000 -> 5633050 | D60: =C60-B60 -> 5212600 | E60: 292000 | F60: 2222100 | G60: =D60+E60+F60 -> 7726700 | I60: 0 | K60: 5200000
A61: 45623 | B61: =393050+50 -> 393100 | C61: =163550+276000+200000+1400000 -> 2039550 | D61: =C61-B61 -> 1646450 | E61: 206000 | F61: 4286700 | G61: =D61+E61+F61 -> 6139150 | I61: 700000 | J61: padilla | K61: 1400000
A62: 45624 | B62: =+163550+276000+200000 -> 639550 | C62: =148450+416000+600000+1880000+20000 -> 3064450 | D62: =C62-B62 -> 2424900 | E62: 86000 | F62: 5958200 | G62: =D62+E62+F62 -> 8469100 | I62: 0 | J62: alfredo | K62: 1850000
A63: 45625 | B63: =564000+30000 -> 594000 | C63: =613000+2400000+234200+230000 -> 3477200 | D63: =C63-B63 -> 2883200 | E63: 302000 | F63: 6540700 | G63: =D63+E63+F63 -> 9725900 | I63: =234000+230000 -> 464000 | J63: 234 aquiles + 230 alfredo | K63: =2400000+293000 -> 2693000
A64: 45626 | B64: 320000 | C64: =113850+362000+150000 -> 625850 | D64: =C64-B64 -> 305850 | E64: 85000 | F64: 1378700 | G64: =D64+E64+F64 -> 1769550 | I64: 400000 | J64: larry | K64: 400000
D65: =SUM(D41:D64) -> 45470316 | E65: =SUM(E41:E64) -> 5487100 | F65: =SUM(F41:F64) -> 66024300 | G65: =SUM(D65:F65) -> 116981716 | I65: =SUM(I41:I64) -> 9484913
A66: 45628 | B66: 625850 | C66: =108400+319000+500000+6250000 -> 7177400 | D66: =C66-B66 -> 6551550 | E66: 124500 | F66: 6139000 | G66: =D66+E66+F66 -> 12815050 | I66: 0 | K66: 6250000
A67: 45629 | B67: 427400 | C67: =76200+301000+2850000+204000+4000 -> 3435200 | D67: =C67-B67 -> 3007800 | E67: 0 | F67: 9500400 | G67: =D67+E67+F67 -> 12508200 | I67: 0 | K67: 2850000
A68: 45630 | B68: 377200 | C68: =86700+143000+2200000+101000 -> 2530700 | D68: =C68-B68 -> 2153500 | E68: 300000 | F68: 4062600 | G68: =D68+E68+F68 -> 6516100 | I68: =30000+6000+40000+25000+1015000 -> 1116000 | J68: alfredo + didi+posicionador+biosalud
A69: 45631 | B69: 229700 | C69: =88650+19300+1950000+5000+55000 -> 2117950 | D69: =C69-B69 -> 1888250 | E69: 0 | F69: 6693300 | G69: =D69+E69+F69 -> 8581550 | I69: =5000+55000 -> 60000 | J69: aguacate + alfredo
A70: 45632 | B70: 107950 | C70: =304000+1860000+15000+1200+408000+216000+8000 -> 2812200 | D70: =C70-B70 -> 2704250 | E70: 145000 | F70: 3959800 | G70: =D70+E70+F70 -> 6809050 | I70: =15000+321200+408000+216000+8000 -> 968200 | J70: alfredo + aquiles + emma+ gabriel velazque + didi + raul
A71: 45633 | B71: 304000 | C71: 603500 | D71: =C71-B71 -> 299500 | E71: 0 | F71: 659000 | G71: =D71+E71+F71 -> 958500 | I71: 0
A72: 45635 | B72: 603500 | C72: =74350+850000+849000 -> 1773350 | D72: =C72-B72 -> 1169850 | E72: 652000 | F72: 6255300 | G72: =D72+E72+F72 -> 8077150 | I72: =4500+125500+33000+210000+100000+150000+226000 -> 849000 | J72: cafe raul + stiker +anchetas+articulador+ raul +emma
A73: 45636 | B73: 924350 | C73: =60300+61000+1438000+2350000 -> 3909300 | D73: =C73-B73 -> 2984950 | E73: 158000 | F73: 4240150 | G73: =D73+E73+F73 -> 7383100 | I73: =30000+43000+30000+1335000 -> 1438000 | J73: alfredo+abraham + maicol + biosalud | K73: 2300000
A74: 45637 | B74: =121300+50000 -> 171300 | C74: =48450+138000+1050000 -> 1236450 | D74: =C74-B74 -> 1065150 | E74: 0 | F74: 4428500 | G74: =D74+E74+F74 -> 5493650 | K74: 1050000
A75: 45638 | B75: 186450 | C75: =38100+334000+750000 -> 1122100 | D75: =C75-B75 -> 935650 | E75: 40000 | F75: 4459000 | G75: =D75+E75+F75 -> 5434650 | I75: 600000 | J75: raul
A76: 45639 | B76: =1122100-600000 -> 522100 | C76: =265000+200000+762400 -> 1227400 | D76: =C76-B76 -> 705300 | E76: 0 | F76: 3498300 | G76: =D76+E76+F76 -> 4203600 | I76: =196400+200000+6000+10000+350000 -> 762400 | J76: abraham + ESCOMBROS +DOMICILIO SUR +MATERIALES+RAUL
A77: 45640 | B77: =265000+200000 -> 465000 | C77: =1450000+111900 -> 1561900 | D77: =C77-B77 -> 1096900 | E77: 0 | F77: 1032800 | G77: =D77+E77+F77 -> 2129700 | I77: 1450000 | J77: raul
A78: 45642 | B78: 111900 | C78: =239700+362650 -> 602350 | D78: =C78-B78 -> 490450 | E78: 367200 | F78: 5169200 | G78: =D78+E78+F78 -> 6026850 | I78: =40400+198000+61400+62850 -> 362650 | J78: agua+abraham+gabriel velasquez + flete perico
A79: 45643 | B79: 239700 | C79: =51900+9450000+13000 -> 9514900 | D79: =C79-B79 -> 9275200 | E79: 2215200 | F79: 1148000 | G79: =D79+E79+F79 -> 12638400 | I79: 75600 | J79: aquiles | K79: 9450000
A80: 45644 | B80: =51900+13000 -> 64900 | C80: =710700+1326200 -> 2036900 | D80: =C80-B80 -> 1972000 | E80: 0 | F80: 1632200 | G80: =D80+E80+F80 -> 3604200 | I80: =700000+600000+26200 -> 1326200 | J80: raul + cristian
A81: 45645 | B81: 710700 | C81: 2777400 | D81: =C81-B81 -> 2066700 | E81: 0 | G81: =D81+E81+F81 -> 2066700 | I81: =67300+27000+8000+215000 -> 317300 | J81: empress+ flete dyma+flete dentmark + cocacola
A82: 45646 | B82: 379500 | C82: =574000+170000+2850000 -> 3594000 | D82: =C82-B82 -> 3214500 | E82: 0 | G82: =D82+E82+F82 -> 3214500 | I82: =150000+2000000+700000 -> 2850000 | J82: z350 sur+raul
A83: 45647 | B83: 744000 | C83: =417050+270000 -> 687050 | D83: =C83-B83 -> -56950 | E83: 96000 | F83: 2167000 | G83: =D83+E83+F83 -> 2206050 | I83: 270000 | J83: larry
A84: 45649 | B84: 417050 | C84: =123000+1500000+250000+16000 -> 1889000 | D84: =C84-B84 -> 1471950 | E84: 968000 | F84: 754400 | G84: =D84+E84+F84 -> 3194350 | I84: =25000+16000 -> 41000 | J84: maicol + domiclio
A85: 45650 | B85: =123000 -> 123000 | D85: =SUM(D66:D84) -> 42996500 | E85: =SUM(E66:E84) -> 5065900 | F85: =SUM(F66:F84) -> 65798950 | G85: =D85+E85+F85 -> 113861350 | I85: =SUM(I66:I84) -> 12486350
A87: 45665 | B87: 100000 | C87: =D87+B87 -> 605900 | D87: 505900 | E87: 0 | F87: 328000 | G87: =D87+E87+F87 -> 833900 | I87: 10000 | J87: didi
A88: 45666 | B88: 205000 | C88: =D88+B88 -> 601000 | D88: 396000 | E88: 370000 | F88: 875000 | G88: =D88+E88+F88 -> 1641000
A89: 45667 | B89: 200000 | C89: 973650 | D89: 396000 | E89: =900000+120000 -> 1020000 | F89: =50000+90000+600000+125000+72000+50000 -> 987000 | G89: =D89+E89+F89 -> 2403000
A90: 45668 | B90: =973650+71000 -> 1044650 | C90: =1627850+220000 -> 1847850 | D90: =C90-B90 -> 803200 | E90: 0 | F90: 480000 | G90: =D90+E90+F90 -> 1283200 | I90: =20000+200000 -> 220000 | J90: platos + larry
A91: 45670 | B91: 1847850 | C91: 3263050 | D91: =C91-B91 -> 1415200 | E91: 0 | F91: 3162000 | G91: =D91+E91+F91 -> 4577200
A92: 45671 | B92: 3263050 | C92: =1343950+134000 -> 1477950 | D92: =C92-B92 -> -1785100 | E92: 0 | F92: 3019000 | G92: =D92+E92+F92 -> 1233900 | I92: =109000+15000+10000 -> 134000 | J92: abraham + alfredo+ raul | K92: 2800000
A93: 45672 | B93: 1343950 | C93: =1528200+1000000+253300 -> 2781500 | D93: =C93-B93 -> 1437550 | E93: 0 | F93: 4091900 | G93: =D93+E93+F93 -> 5529450 | I93: =40000+31000+167300+15000 -> 253300 | J93: construccion + raul + abraham+ alfredo | K93: 1000000
A94: 45673 | B94: 1528200 | C94: =1154900+2050000 -> 3204900 | D94: =C94-B94 -> 1676700 | E94: 0 | F94: 1004400 | G94: =D94+E94+F94 -> 2681100 | I94: 17000 | J94: domicilio | K94: =1200000+850000 -> 2050000
A95: 45674 | B95: 1154900 | C95: 888000 | D95: =C95-B95 -> -266900 | E95: 0 | F95: 3810500 | G95: =D95+E95+F95 -> 3543600
A96: 45675 | B96: 888000 | C96: =2450000+418450+200000 -> 3068450 | D96: =C96-B96 -> 2180450 | E96: 0 | F96: 300000 | G96: =D96+E96+F96 -> 2480450 | I96: 200000 | J96: larry | K96: 2450000
A97: 45677 | B97: 418450 | C97: =1847100+1150000 -> 2997100 | D97: =C97-B97 -> 2578650 | E97: 0 | F97: 1319000 | G97: =D97+E97+F97 -> 3897650 | I97: =12000+5000 -> 17000 | J97: dolarcity pan | K97: =1300000+1150000 -> 2450000
A98: 45678 | B98: 547100 | C98: =1306100+2650000+119100 -> 4075200 | D98: =C98-B98 -> 3528100 | E98: =350000+98000 -> 448000 | F98: =1303300 -> 1303300 | G98: =D98+E98+F98 -> 5279400 | I98: =18600+90000+10500 -> 119100 | J98: d1+raul+don juan | K98: =1350000+1300000 -> 2650000
A99: 45679 | B99: 1306100 | C99: =589000+130000+1250000+74000 -> 2043000 | D99: =C99-B99 -> 736900 | E99: 811000 | F99: 1833000 | G99: =D99+E99+F99 -> 3380900 | I99: =15000+10000+43000+6000 -> 74000 | J99: puerta + almuerzo+resina + domicilio | K99: =1250000 -> 1250000
A100: 45680 | B100: 2043000 | C100: =2750000+380000+400900 -> 3530900 | D100: =C100-B100 -> 1487900 | E100: 67000 | F100: 952000 | G100: =D100+E100+F100 -> 2506900 | I100: =3000 -> 3000 | J100: domicilio | K100: 3000000
A101: 45681 | B101: 530900 | C101: 651200 | D101: =C101-B101 -> 120300 | E101: =42000+755000 -> 797000 | F101: 2458600 | G101: =D101+E101+F101 -> 3375900
...

Sheet NOMINA FERNANDO
E1: 46006 | F1: 1200000
E2: 46012 | F2: 1500000
E3: 46019 | F3: 1100000
E4: 45662 | F4: 1000000
E5: 45669 | F5: 1200000
E6: 45675 | F6: 1100000
E7: 45682 | F7: 1100000
E8: 45689 | F8: 1200000
E9: 45696 | F9: 1050000
E10: 45703 | F10: 1050000
E11: 45709 | F11: 1050000
E12: 45716 | F12: 1050000
... E19: 45766 | F19: 350000
F21: =SUM(F1:F20) -> 20250000

Sheet SILICONAS
B2: COSTO | D2: PESADA | E2: KIT 1 LIVIANA + 1 PESADA | F2: KIT CON 2 LIVIANAS + 1 PESADA | G2: LIVIANA | H2: REGULAR | I2: REGISTRO DE MORDIDA | J2: TRANSPARENTE
B3: PANASIL | D3: 174240 | E3: 261360 | F3: 348500 | G3: 87120 | H3: 87120 | I3: 87120 | J3: 87120
B4: PRESIDENT COLTENE | D4: 144500 | E4: 226900 | F4: 309300 | G4: 82400 | H4: 82400
B5: DMG SILAGUM | D5: 202373 | E5: 253470 | F5: =C5+C5+D5 -> 202373 | G5: 78750 | H5: 87900 | I5: 91630
B6: ZHERMACK | D6: 60000 | E6: =165000 -> 165000 | F6: - | G6: 105000 | H6: 109000 | J6: 101000
B8: PANASIL 900 ML | C8: 348480
B9: KIT ZHERMACK 1 LIV + 2 PESADAS | C9: 223027
B10: KIT ZHERMACK YUMBO 900 + 2 LIVIANAS | C10: 584900
B11: SPEEDEX | C11: 121879
B15: VENTA | D15: PESADA | E15: KIT 1 LIVIANA + 1 PESADA | F15: KIT CON 2 LIVIANAS + 1 PESADA | G15: LIVIANA | H15: REGULAR | I15: REGISTRO DE MORDIDA | J15: TRANSPARENTE | L15: utilidad | M15: LIVIANA | N15: PESADA | O15: KIT 1 LIVIANA + 1 PESADA | P15: KIT CON 2 LIVIANAS + 1 PESADA | Q15: REGULAR | R15: REGISTRO DE MORDIDA | S15: TRANSPARENTE
B16: PANASIL | D16: 160000 | E16: 280000 | F16: 380000 | G16: 120000 | H16: 120000 | I16: 120000 | J16: 120000 | L16: PANASIL
B17: PRESIDENT COLTENE | D17: 210000 | E17: 290000 | F17: 390000 | G17: 120000 | H17: 120000 | I17: - | J17: - | L17: PRESIDENT COLTENE
B18: DMG SILAGUM | D18: 266000 | E18: 352000 | G18: 110000 | H18: 115000 | I18: 120000 | J18: - | L18: DMG SILAGUM
B19: ZHERMACK | D19: 120000 | E19: 250000 | F19: - | G19: 160000 | H19: 160000 | I19: - | J19: 160000 | L19: ZHERMACK
B21: PANASIL 900 ML | C21: 450000
B22: KIT PANASIL 900 ML + 2 LIV | C22: 650000
B23: KIT ZHERMACK 1 LIV + 2 PESADAS | C23: 350000
B24: KIT ZHERMACK YUMBO 900 + 2 LIVIANAS | C24: 750000
B25: SPEEDEX | C25: 160000
B35: kit silicona pesada 400 y Liviana Panasil | C35: =75000+87120 -> 162120 | D35: 270000
B36: kit silicona pesada 900 + 2 Livianas Panasil | C36: =348480+87120+87120 -> 522720 | D36: 630000
B37: registro mordida futar clear TRANSPARENTE X unidad silicona | C37: 87120 | D37: 120000
B38: registro mordida futar D silicona | C38: 87120 | D38: 120000
B39: REGULAR PANASIL Silicona | C39: 87120 | D39: 120000
B40: silicona panasil initial contac light liviana | C40: 87120 | D40: 120000
B41: silicona panasil putty soft pesada 400ml | C41: 75000 | D41: 160000
B42: silicona panasil putty soft pesada 900 ml | C42: 348480 | D42: 450000

Sheet DIENTES IVORINA
A1: IVORINA | B1: INVENTARIO | C1: PEDIDO SUR | D1: NTE feb 25 | E1: PEDIDO SUR ABR/25 | F1: PEDIDO NORTE ABR/25 | G1: TOTAL PEDIDO
A2: 11 | B2: 12 | C2: 0 | D2: 15 | F2: 10 | G2: =SUM(C2:F2) -> 25
A3: 12 | B3: 14 | C3: 10 | F3: 10 | G3: =SUM(C3:F3) -> 20
A4: 13 | B4: 11 | C4: 10 | F4: 10 | G4: =SUM(C4:F4) -> 20
A5: 14 | B5: 16 | C5: 5 | G5: =SUM(C5:F5) -> 5
A6: 15 | B6: 11 | C6: 5 | G6: =SUM(C6:F6) -> 5
A7: 16 | B7: 10 | C7: 5 | F7: 10 | G7: =SUM(C7:F7) -> 15
A8: 17 | B8: 13 | C8: 5 | G8: =SUM(C8:F8) -> 5
A9: 18 | B9: 19 | C9: 5 | G9: =SUM(C9:F9) -> 5
A11: 21 | B11: 10 | C11: 0 | D11: 10 | F11: 20 | G11: =SUM(C11:F11) -> 30
A12: 22 | B12: 15 | C12: 10 | D12: 5 | F12: 10 | G12: =SUM(C12:F12) -> 25
A13: 23 | B13: 15 | C13: 0 | D13: 10 | F13: 10 | G13: =SUM(C13:F13) -> 20
A14: 24 | B14: 16 | C14: 5 | D14: 10 | G14: =SUM(C14:F14) -> 15
A15: 25 | B15: 15 | C15: 0 | D15: 10 | F15: 5 | G15: =SUM(C15:F15) -> 15
A16: 26 | B16: 13 | C16: 0 | D16: 10 | F16: 5 | G16: =SUM(C16:F16) -> 15
A17: 27 | B17: 19 | C17: 0 | G17: =SUM(C17:F17) -> 0
A18: 28 | B18: 7 | C18: 10 | G18: =SUM(C18:F18) -> 10
A20: 31 | B20: 20 | C20: 10 | G20: =SUM(C20:F20) -> 10
A21: 32 | B21: 19 | C21: 10 | G21: =SUM(C21:F21) -> 10
A22: 33 | B22: 17 | C22: 10 | G22: =SUM(C22:F22) -> 10
A23: 34 | B23: 16 | C23: 10 | G23: =SUM(C23:F23) -> 10
A24: 35 | B24: 13 | C24: 5 | D24: 10 | G24: =SUM(C24:F24) -> 15
A25: 36 | B25: 8 | C25: 0 | D25: 20 | G25: =SUM(C25:F25) -> 20
A26: 37 | B26: 13 | C26: 0 | D26: 10 | G26: =SUM(C26:F26) -> 10
A27: 38 | B27: 10 | C27: 10 | G27: =SUM(C27:F27) -> 10
A29: 41 | B29: 15 | C29: 10 | G29: =SUM(C29:F29) -> 10
A30: 42 | B30: 15 | C30: 10 | G30: =SUM(C30:F30) -> 10
A31: 43 | B31: 15 | C31: 10 | G31: =SUM(C31:F31) -> 10
A32: 44 | B32: 14 | C32: 10 | G32: =SUM(C32:F32) -> 10
A33: 45 | B33: 12 | C33: 10 | G33: =SUM(C33:F33) -> 10
A34: 46 | B34: 12 | C34: 10 | G34: =SUM(C34:F34) -> 10
A35: 47 | B35: 12 | C35: 5 | G35: =SUM(C35:F35) -> 5
A36: 48 | B36: 10 | C36: 5 | G36: =SUM(C36:F36) -> 5
A38: IVORINA PEDIATRICO
A39: 51 | E39: 0 | G39: =SUM(C39:F39) -> 0
A40: 52 | E40: 0 | G40: =SUM(C40:F40) -> 0
A41: 53 | E41: 0 | G41: =SUM(C41:F41) -> 0
A42: 54 | E42: 10 | F42: 5 | G42: =SUM(C42:F42) -> 15
A43: 55 | E43: 20 | F43: 10 | G43: =SUM(C43:F43) -> 30
A44: 56 | E44: 20 | F44: 10 | G44: =SUM(C44:F44) -> 30
A46: 61 | E46: 0 | G46: =SUM(C46:F46) -> 0
A47: 62 | E47: 0 | G47: =SUM(C47:F47) -> 0
A48: 63 | E48: 0 | G48: =SUM(C48:F48) -> 0
A49: 64 | E49: 10 | F49: 10 | G49: =SUM(C49:F49) -> 20
A50: 65 | E50: 20 | F50: 15 | G50: =SUM(C50:F50) -> 35
A51: 66 | E51: 10 | F51: 10 | G51: =SUM(C51:F51) -> 20
A53: 71 | E53: 5 | F53: 15 | G53: =SUM(C53:F53) -> 20
A54: 72 | E54: 5 | F54: 15 | G54: =SUM(C54:F54) -> 20
A55: 73 | E55: 0 | G55: =SUM(C55:F55) -> 0
A56: 74 | E56: 20 | F56: 10 | G56: =SUM(C56:F56) -> 30
A57: 75 | E57: 20 | F57: 10 | G57: =SUM(C57:F57) -> 30
A58: 76 | E58: 5 | F58: 10 | G58: =SUM(C58:F58) -> 15
